Workbook

Sheet Lisez-moi
A1: Univers Barça — Plan de réalisation et suivi du projet
A2: Fichier de pilotage : planning par jalons, Gantt, backlog complet et tableau de bord. Généré à partir du backlog des 3 dépôts GitHub.
A4: Comment l’utiliser
A5: 1. « Paramètres » : date de début, nombre de développeurs par flux, facteur de focus, marge. Tout le planning se recalcule.
A6: 2. « Étapes » : plan de réalisation étape par étape (phases 0 à 3), avec charge, dates et critères de sortie.
A7: 3. « Jalons » : jalons de fin de phase (dates calculées, date réelle à saisir) ; « Gantt » : barres par semaine et par épopée.
A8: 4. « Épopées » : plan détaillé par épopée (flux × phase) avec avancement ; « Backlog » : une ligne par issue avec statut à mettre à jour.
A9: 5. « Suivi » : tableau de bord (avancement par phase, par flux, par statut) ; « Scénarios » : durée selon la taille de l’équipe ; « Décisions et risques ».
A10: Code couleur
A11: Texte bleu sur fond jaune = cellule à modifier · texte noir = formule (ne pas écraser) · couleurs de phase : gris-bleu (0), grenat (1), bleu (2), or (3).
A12: Hypothèses (à valider)
A13: • Charge par taille d’issue (XS 0,25 j · S 0,5 · M 1 · L 2 · XL 3,5) : estimation indicative à recalibrer après les premiers sprints (feuille Paramètres).
... A18: Mettre à jour la colonne « Statut » (et, si utile, « Début réel » / « Fin réel ») dans « Backlog » : « Épopées », « Gantt », « Jalons » et « Suivi » se recalculent seuls.

Sheet Paramètres
A1: Paramètres du planning
A2: Cellules en bleu sur fond jaune = à modifier ; tout le planning (durées, dates, Gantt, jalons) se recalcule.
A4: Date de début du projet | B4: 46328 | C4: Lundi conseillé. Hypothèse : début après cadrage (secrets, VPS, Firebase, décisions).
A5: Facteur de focus (productivité réelle) | B5: 0.8 | C5: Réunions, revues, aléas : 80 % du temps nominal est productif.
A6: Marge pour aléas | B6: 0.15 | C6: Ajoutée à la charge de chaque épopée.
A7: Développeurs sur le flux API | B7: 3 | C7: Équivalents temps plein (peut être décimal : 1,5).
A8: Développeurs sur le flux Mobile | B8: 3
A9: Développeurs sur le flux Admin | B9: 2
A10: Décalage Mobile/Admin sur l’API (jours ouvrés) | B10: 20 | C10: En phases 1 à 3, Mobile/Admin démarrent N jours ouvrés après l’API (endpoints disponibles).
A11: Durée de recette par phase (jours ouvrés) | B11: 10 | C11: UAT + correctifs + observation staging (CDC §15).
A13: Barème de charge par taille (jours·personne)
A14: Taille | B14: Charge (j) | C14: Signification
A15: XS | B15: 0.25 | C15: ≈ 2 h : détail, libellé, petit test
A16: S | B16: 0.5 | C16: ≈ demi-journée
A17: M | B17: 1 | C17: ≈ 1 jour
A18: L | B18: 2 | C18: ≈ 2 jours (à redécouper si possible)
A19: XL | B19: 3.5 | C19: ≈ 3-4 jours (à redécouper)
A22: Phases
A23: Phase | B23: Intitulé | C23: Objectif de sortie (CDC §5.5)
A24: 0 | B24: Phase 0 — Socle technique | C24: Environnements opérationnels, premier commit déployé en staging
A25: 1 | B25: Phase 1 — MVP | C25: Version testable par un cercle restreint d’utilisateurs
A26: 2 | B26: Phase 2 — Communautaire & compétitif | C26: Version communautaire complète
A27: 3 | B27: Phase 3 — Fonctionnalités avancées | C27: Version complète du périmètre fonctionnel cible

Sheet Étapes
A1: Plan de réalisation — étapes détaillées
A2: Chaque étape regroupe des épopées du backlog ; charge, début et fin sont calculés depuis « Épopées ». Les étapes « Recette » ont une durée fixe (Paramètres).
A5: Étape | B5: Phase | C5: Intitulé | D5: Objectif | E5: Épopées (backlog) | F5: Prérequis | G5: Livrables | H5: Critères de sortie | I5: Charge (j) | J5: Début | K5: Fin | L5: Durée (jo) | M5: Statut
A6: 0.1 | B6: 0 | C6: Cadrage et mise en place (avant J0) | D6: Débloquer l’environnement de travail avant le premier jour de développement. | E6: Aucune (actions manuelles) | F6: — | G6: Secrets GitHub (VPS, Firebase, stores), environnements staging/production, projet GitHub relié, protection des branches, nom de domaine et DNS. | H6: Décisions « à confirmer » tranchées (voir feuille Décisions) ; pipelines CD capables de déployer. | I6: 0 | J6: =WORKDAY(Paramètres!$B$4,-10) -> 46314 | K6: =WORKDAY(Paramètres!$B$4,-1) -> 46325 | L6: =NETWORKDAYS(J6,K6) -> 10 | M6: À faire
A7: 0.2 | B7: 0 | C7: Socle API et plateforme | D7: Rendre l’API exploitable : configuration, observabilité, sécurité de base, identité. | E7: API-PLAT, API-AUTH | F7: 0.1 | G7: API en staging avec /health, /metrics, Swagger, migrations, jobs de base. | H7: CI verte ; staging déployé ; tests de charge « smoke » passants. | I7: =SUMIFS(Épopées!$G$6:$G$59,Épopées!$A$6:$A$59,"API-PLAT|0")+SUMIFS(Épopées!$G$6:$G$59,Épopées!$A$6:$A$59,"API-AUTH|0") -> 8.75 | J7: =MIN(SUMIFS(Épopées!$L$6:$L$59,Épopées!$A$6:$A$59,"API-PLAT|0"),SUMIFS(Épopées!$L$6:$L$59,Épopées!$A$6:$A$59,"API-AUTH|0")) -> 46328 | K7: =MAX(SUMIFS(Épopées!$M$6:$M$59,Épopées!$A$6:$A$59,"API-PLAT|0"),SUMIFS(Épopées!$M$6:$M$59,Épopées!$A$6:$A$59,"API-AUTH|0")) -> 46332 | L7: =NETWORKDAYS(J7,K7) -> 5 | M7: À faire
A8: 0.3 | B8: 0 | C8: Design system mobile | D8: Implémenter tokens, composants et animations du design system Flutter. | E8: MOB-ZA, MOB-ZB, MOB-ZC, MOB-ZD, MOB-ZE | F8: 0.1 | G8: Widgets sous lib/core/widgets, thèmes clair/sombre, golden tests. | H8: Planches ZA-ZE reproduites à l’identique ; goldens verts. | I8: =SUMIFS(Épopées!$G$6:$G$59,Épopées!$A$6:$A$59,"MOB-ZA|0")+SUMIFS(Épopées!$G$6:$G$59,Épopées!$A$6:$A$59,"MOB-ZB|0")+SUMIFS(Épopées!$G$6:$G$59,Épopées!$A$6:$A$59,"MOB-ZC|0")+SUMIFS(Épopées!$G$6:$G$59,Épopées!$A$6:$A$59,"MOB-ZD|0")+SUMIFS(Épopées!$G$6:$G$59,Épopées!$A$6:$A$59,"MOB-ZE|0") -> 89.5 | J8: =MIN(SUMIFS(Épopées!$L$6:$L$59,Épopées!$A$6:$A$59,"MOB-ZA|0"),SUMIFS(Épopées!$L$6:$L$59,Épopées!$A$6:$A$59,"MOB-ZB|0"),SUMIFS(Épopées!$L$6:$L$59,Épopées!$A$6:$A$59,"MOB-ZC|0"),SUMIFS(Épopées!$L$6:$L$59,Épopées!$A$6:$A$59,"MOB-ZD|0"),SUMIFS(Épopées!$L$6:$L$59,Épopées!$A$6:$A$59,"MOB-ZE|0")) -> 46363 | K8: =MAX(SUMIFS(Épopées!$M$6:$M$59,Épopées!$A$6:$A$59,"MOB-ZA|0"),SUMIFS(Épopées!$M$6:$M$59,Épopées!$A$6:$A$59,"MOB-ZB|0"),SUMIFS(Épopées!$M$6:$M$59,Épopées!$A$6:$A$59,"MOB-ZC|0"),SUMIFS(Épopées!$M$6:$M$59,Épopées!$A$6:$A$59,"MOB-ZD|0"),SUMIFS(Épopées!$M$6:$M$59,Épopées!$A$6:$A$59,"MOB-ZE|0")) -> 46423 | L8: =NETWORKDAYS(J8,K8) -> 45 | M8: À faire
A9: 0.4 | B9: 0 | C9: Socle Flutter et états système | D9: Navigation, réseau, stockage, i18n, Firebase, écrans système. | E9: MOB-FND, MOB-A | F9: 0.3 (en parallèle) | G9: ShellRoute 5 onglets, AuthBloc, Chopper + refresh, Drift, ARB FR/EN/ES, écrans A-01…A-10. | H9: App installable (APK/IPA) sur staging ; états offline/5xx/429/maintenance gérés. | I9: =SUMIFS(Épopées!$G$6:$G$59,Épopées!$A$6:$A$59,"MOB-FND|0")+SUMIFS(Épopées!$G$6:$G$59,Épopées!$A$6:$A$59,"MOB-A|0") -> 66.25 | J9: =MIN(SUMIFS(Épopées!$L$6:$L$59,Épopées!$A$6:$A$59,"MOB-FND|0"),SUMIFS(Épopées!$L$6:$L$59,Épopées!$A$6:$A$59,"MOB-A|0")) -> 46328 | K9: =MAX(SUMIFS(Épopées!$M$6:$M$59,Épopées!$A$6:$A$59,"MOB-FND|0"),SUMIFS(Épopées!$M$6:$M$59,Épopées!$A$6:$A$59,"MOB-A|0")) -> 46435 | L9: =NETWORKDAYS(J9,K9) -> 78 | M9: À faire
A10: 0.5 | B10: 0 | C10: Socle et design system admin | D10: Base du back-office : routage par rôle, composants, qualité. | E10: ADM-FND, ADM-ADS | F10: 0.1 | G10: Composants shadcn-style, layout responsive, tests Vitest/Playwright. | H10: Admin déployé en staging ; accessibilité de base validée. | I10: =SUMIFS(Épopées!$G$6:$G$59,Épopées!$A$6:$A$59,"ADM-FND|0")+SUMIFS(Épopées!$G$6:$G$59,Épopées!$A$6:$A$59,"ADM-ADS|0") -> 60 | J10: =MIN(SUMIFS(Épopées!$L$6:$L$59,Épopées!$A$6:$A$59,"ADM-FND|0"),SUMIFS(Épopées!$L$6:$L$59,Épopées!$A$6:$A$59,"ADM-ADS|0")) -> 46328 | K10: =MAX(SUMIFS(Épopées!$M$6:$M$59,Épopées!$A$6:$A$59,"ADM-FND|0"),SUMIFS(Épopées!$M$6:$M$59,Épopées!$A$6:$A$59,"ADM-ADS|0")) -> 46387 | L10: =NETWORKDAYS(J10,K10) -> 44 | M10: À faire
A11: 1.1 | B11: 1 | C11: Identité, comptes et paramètres | D11: Inscription, connexion, RGPD, profil et paramètres côté API, mobile et admin. | E11: API-AUTH, MOB-B, MOB-Q, ADM-WA, ADM-WI | F11: 0.2, 0.4, 0.5 | G11: Parcours onboarding → compte vérifié ; export/suppression RGPD ; comptes admin + 2FA. | H11: Parcours d’inscription E2E vert ; consentements historisés ; tests de sécurité auth verts. | I11: =SUMIFS(Épopées!$G$6:$G$59,Épopées!$A$6:$A$59,"API-AUTH|1")+SUMIFS(Épopées!$G$6:$G$59,Épopées!$A$6:$A$59,"MOB-B|1")+SUMIFS(Épopées!$G$6:$G$59,Épopées!$A$6:$A$59,"MOB-Q|1")+SUMIFS(Épopées!$G$6:$G$59,Épopées!$A$6:$A$59,"ADM-WA|1")+SUMIFS(Épopées!$G$6:$G$59,Épopées!$A$6:$A$59,"ADM-WI|1") -> 146.75 | J11: =MIN(SUMIFS(Épopées!$L$6:$L$59,Épopées!$A$6:$A$59,"API-AUTH|1"),SUMIFS(Épopées!$L$6:$L$59,Épopées!$A$6:$A$59,"MOB-B|1"),SUMIFS(Épopées!$L$6:$L$59,Épopées!$A$6:$A$59,"MOB-Q|1"),SUMIFS(Épopées!$L$6:$L$59,Épopées!$A$6:$A$59,"ADM-WA|1"),SUMIFS(Épopées!$L$6:$L$59,Épopées!$A$6:$A$59,"ADM-WI|1")) -> 46364 | K11: =MAX(SUMIFS(Épopées!$M$6:$M$59,Épopées!$A$6:$A$59,"API-AUTH|1"),SUMIFS(Épopées!$M$6:$M$59,Épopées!$A$6:$A$59,"MOB-B|1"),SUMIFS(Épopées!$M$6:$M$59,Épopées!$A$6:$A$59,"MOB-Q|1"),SUMIFS(Épopées!$M$6:$M$59,Épopées!$A$6:$A$59,"ADM-WA|1"),SUMIFS(Épopées!$M$6:$M$59,Épopées!$A$6:$A$59,"ADM-WI|1")) -> 46563 | L11: =NETWORKDAYS(J11,K11) -> 144 | M11: À faire
A12: 1.2 | B12: 1 | C12: Données football, historique et contenu | D12: Alimenter et publier les données joueurs/matchs ; consultation côté mobile. | E12: API-FOOT, MOB-F, ADM-WC, ADM-WD, ADM-WE | F12: 1.1 (auth) | G12: Synchro API football, CRUD joueurs/matchs/anecdotes, historique et fiches mobiles. | H12: Données réelles visibles dans l’app ; workflow de publication et traductions opérationnel. | I12: =SUMIFS(Épopées!$G$6:$G$59,Épopées!$A$6:$A$59,"API-FOOT|1")+SUMIFS(Épopées!$G$6:$G$59,Épopées!$A$6:$A$59,"MOB-F|1")+SUMIFS(Épopées!$G$6:$G$59,Épopées!$A$6:$A$59,"ADM-WC|1")+SUMIFS(Épopées!$G$6:$G$59,Épopées!$A$6:$A$59,"ADM-WD|1")+SUMIFS(Épopées!$G$6:$G$59,Épopées!$A$6:$A$59,"ADM-WE|1") -> 159.5 | J12: =MIN(SUMIFS(Épopées!$L$6:$L$59,Épopées!$A$6:$A$59,"API-FOOT|1"),SUMIFS(Épopées!$L$6:$L$59,Épopées!$A$6:$A$59,"MOB-F|1"),SUMIFS(Épopées!$L$6:$L$59,Épopées!$A$6:$A$59,"ADM-WC|1"),SUMIFS(Épopées!$L$6:$L$59,Épopées!$A$6:$A$59,"ADM-WD|1"),SUMIFS(Épopées!$L$6:$L$59,Épopées!$A$6:$A$59,"ADM-WE|1")) -> 46399 | K12: =MAX(SUMIFS(Épopées!$M$6:$M$59,Épopées!$A$6:$A$59,"API-FOOT|1"),SUMIFS(Épopées!$M$6:$M$59,Épopées!$A$6:$A$59,"MOB-F|1"),SUMIFS(Épopées!$M$6:$M$59,Épopées!$A$6:$A$59,"ADM-WC|1"),SUMIFS(Épopées!$M$6:$M$59,Épopées!$A$6:$A$59,"ADM-WD|1"),SUMIFS(Épopées!$M$6:$M$59,Épopées!$A$6:$A$59,"ADM-WE|1")) -> 46510 | L12: =NETWORKDAYS(J12,K12) -> 80 | M12: À faire
A13: 1.3 | B13: 1 | C13: Accueil, calendrier et tableau de bord | D13: Dashboard d’accueil, calendrier et export agenda, KPI admin. | E13: API-CAL, MOB-C, MOB-L, ADM-WB | F13: 1.2 | G13: Dashboard, calendrier, export ICS / abonnement, KPI admin et recherche globale. | H13: Export ICS validé sur iOS/Android ; recherche admin < 300 ms. | I13: =SUMIFS(Épopées!$G$6:$G$59,Épopées!$A$6:$A$59,"API-CAL|1")+SUMIFS(Épopées!$G$6:$G$59,Épopées!$A$6:$A$59,"MOB-C|1")+SUMIFS(Épopées!$G$6:$G$59,Épopées!$A$6:$A$59,"MOB-L|1")+SUMIFS(Épopées!$G$6:$G$59,Épopées!$A$6:$A$59,"ADM-WB|1") -> 94 | J13: =MIN(SUMIFS(Épopées!$L$6:$L$59,Épopées!$A$6:$A$59,"API-CAL|1"),SUMIFS(Épopées!$L$6:$L$59,Épopées!$A$6:$A$59,"MOB-C|1"),SUMIFS(Épopées!$L$6:$L$59,Épopées!$A$6:$A$59,"MOB-L|1"),SUMIFS(Épopées!$L$6:$L$59,Épopées!$A$6:$A$59,"ADM-WB|1")) -> 46407 | K13: =MAX(SUMIFS(Épopées!$M$6:$M$59,Épopées!$A$6:$A$59,"API-CAL|1"),SUMIFS(Épopées!$M$6:$M$59,Épopées!$A$6:$A$59,"MOB-C|1"),SUMIFS(Épopées!$M$6:$M$59,Épopées!$A$6:$A$59,"MOB-L|1"),SUMIFS(Épopées!$M$6:$M$59,Épopées!$A$6:$A$59,"ADM-WB|1")) -> 46533 | L13: =NETWORKDAYS(J13,K13) -> 91 | M13: À faire
A14: 1.4 | B14: 1 | C14: Jeux quotidiens | D14: Guess the Player et Quiz adaptatif, classements, streaks. | E14: API-JEUX, MOB-D, MOB-E, ADM-WF | F14: 1.2 | G14: Défi quotidien, quiz adaptatif, scoring, streaks, back-office des questions. | H14: Défi identique pour tous ; anti-triche testé ; test de charge « défi du soir ». | I14: =SUMIFS(Épopées!$G$6:$G$59,Épopées!$A$6:$A$59,"API-JEUX|1")+SUMIFS(Épopées!$G$6:$G$59,Épopées!$A$6:$A$59,"MOB-D|1")+SUMIFS(Épopées!$G$6:$G$59,Épopées!$A$6:$A$59,"MOB-E|1")+SUMIFS(Épopées!$G$6:$G$59,Épopées!$A$6:$A$59,"ADM-WF|1") -> 127 | J14: =MIN(SUMIFS(Épopées!$L$6:$L$59,Épopées!$A$6:$A$59,"API-JEUX|1"),SUMIFS(Épopées!$L$6:$L$59,Épopées!$A$6:$A$59,"MOB-D|1"),SUMIFS(Épopées!$L$6:$L$59,Épopées!$A$6:$A$59,"MOB-E|1"),SUMIFS(Épopées!$L$6:$L$59,Épopées!$A$6:$A$59,"ADM-WF|1")) -> 46454 | K14: =MAX(SUMIFS(Épopées!$M$6:$M$59,Épopées!$A$6:$A$59,"API-JEUX|1"),SUMIFS(Épopées!$M$6:$M$59,Épopées!$A$6:$A$59,"MOB-D|1"),SUMIFS(Épopées!$M$6:$M$59,Épopées!$A$6:$A$59,"MOB-E|1"),SUMIFS(Épopées!$M$6:$M$59,Épopées!$A$6:$A$59,"ADM-WF|1")) -> 46573 | L14: =NETWORKDAYS(J14,K14) -> 86 | M14: À faire
A15: 1.5 | B15: 1 | C15: Assistant IA Barça AI | D15: Assistant conversationnel borné aux faits, avec garde-fous et quotas. | E15: API-IA, MOB-N | F15: 1.2 | G15: Chat en streaming, historique, quotas, modération, kill switch. | H15: Jeu de tests de non-régression de prompts vert ; coûts suivis. | I15: =SUMIFS(Épopées!$G$6:$G$59,Épopées!$A$6:$A$59,"API-IA|1")+SUMIFS(Épopées!$G$6:$G$59,Épopées!$A$6:$A$59,"MOB-N|1") -> 66 | J15: =MIN(SUMIFS(Épopées!$L$6:$L$59,Épopées!$A$6:$A$59,"API-IA|1"),SUMIFS(Épopées!$L$6:$L$59,Épopées!$A$6:$A$59,"MOB-N|1")) -> 46506 | K15: =MAX(SUMIFS(Épopées!$M$6:$M$59,Épopées!$A$6:$A$59,"API-IA|1"),SUMIFS(Épopées!$M$6:$M$59,Épopées!$A$6:$A$59,"MOB-N|1")) -> 46597 | L15: =NETWORKDAYS(J15,K15) -> 66 | M15: À faire
A16: 1.6 | B16: 1 | C16: Notifications | D16: Notifications push et centre de notifications. | E16: API-NOTIF, MOB-O | F16: 1.1 | G16: Jetons d’appareil, préférences, envoi FCM, campagnes admin. | H16: Notification reçue sur iOS et Android en staging ; DLQ supervisée. | I16: =SUMIFS(Épopées!$G$6:$G$59,Épopées!$A$6:$A$59,"API-NOTIF|1")+SUMIFS(Épopées!$G$6:$G$59,Épopées!$A$6:$A$59,"MOB-O|1") -> 54.75 | J16: =MIN(SUMIFS(Épopées!$L$6:$L$59,Épopées!$A$6:$A$59,"API-NOTIF|1"),SUMIFS(Épopées!$L$6:$L$59,Épopées!$A$6:$A$59,"MOB-O|1")) -> 46485 | K16: =MAX(SUMIFS(Épopées!$M$6:$M$59,Épopées!$A$6:$A$59,"API-NOTIF|1"),SUMIFS(Épopées!$M$6:$M$59,Épopées!$A$6:$A$59,"MOB-O|1")) -> 46615 | L16: =NETWORKDAYS(J16,K16) -> 93 | M16: À faire
A17: 1.7 | B17: 1 | C17: Exploitation et supervision MVP | D17: Industrialiser : monitoring, sauvegardes, charge, supervision admin. | E17: API-PLAT, ADM-WH, ADM-WJ | F17: 1.1 à 1.6 (en continu) | G17: Dashboards Grafana, alertes, sauvegardes testées, supervision technique admin, capacité mesurée. | H17: Restauration testée ; dimensionnement serveur documenté (tests de charge). | I17: =SUMIFS(Épopées!$G$6:$G$59,Épopées!$A$6:$A$59,"API-PLAT|1")+SUMIFS(Épopées!$G$6:$G$59,Épopées!$A$6:$A$59,"ADM-WH|1")+SUMIFS(Épopées!$G$6:$G$59,Épopées!$A$6:$A$59,"ADM-WJ|1") -> 66.5 | J17: =MIN(SUMIFS(Épopées!$L$6:$L$59,Épopées!$A$6:$A$59,"API-PLAT|1"),SUMIFS(Épopées!$L$6:$L$59,Épopées!$A$6:$A$59,"ADM-WH|1"),SUMIFS(Épopées!$L$6:$L$59,Épopées!$A$6:$A$59,"ADM-WJ|1")) -> 46335 | K17: =MAX(SUMIFS(Épopées!$M$6:$M$59,Épopées!$A$6:$A$59,"API-PLAT|1"),SUMIFS(Épopées!$M$6:$M$59,Épopées!$A$6:$A$59,"ADM-WH|1"),SUMIFS(Épopées!$M$6:$M$59,Épopées!$A$6:$A$59,"ADM-WJ|1")) -> 46573 | L17: =NETWORKDAYS(J17,K17) -> 171 | M17: À faire
A18: 1.8 | B18: 1 | C18: Recette MVP et bêta fermée | D18: Valider le MVP avec un cercle restreint. | E18: Aucune épopée — durée fixe (Paramètres) | F18: 1.1 à 1.7 | G18: Rapport de recette, correctifs, version bêta (TestFlight / Firebase App Distribution). | H18: Critères de sortie du CDC §15.2 atteints (couverture, anomalies, doc, observation 48 h). | I18: 0 | J18: =WORKDAY(MAX(K11,K12,K13,K14,K15,K16,K17),1) -> 46616 | K18: =WORKDAY(J18,Paramètres!$B$11-1) -> 46629 | L18: =NETWORKDAYS(J18,K18) -> 10 | M18: À faire
A19: 2.1 | B19: 2 | C19: Communauté : carte, groupes et modération | D19: Carte communautaire, groupes locaux, modération (côté API, mobile, admin). | E19: API-COMM, API-MODER, MOB-J, MOB-K, ADM-WG, ADM-WJ | F19: Phase 1 | G19: Carte agrégée, groupes, signalements, sanctions, journal d’audit. | H19: Revue RGPD géolocalisation ; test de modération de bout en bout. | I19: =SUMIFS(Épopées!$G$6:$G$59,Épopées!$A$6:$A$59,"API-COMM|2")+SUMIFS(Épopées!$G$6:$G$59,Épopées!$A$6:$A$59,"API-MODER|2")+SUMIFS(Épopées!$G$6:$G$59,Épopées!$A$6:$A$59,"MOB-J|2")+SUMIFS(Épopées!$G$6:$G$59,Épopées!$A$6:$A$59,"MOB-K|2")+SUMIFS(Épopées!$G$6:$G$59,Épopées!$A$6:$A$59,"ADM-WG|2")+SUMIFS(Épopées!$G$6:$G$59,Épopées!$A$6:$A$59,"ADM-WJ|2") -> 168.5 | J19: =MIN(SUMIFS(Épopées!$L$6:$L$59,Épopées!$A$6:$A$59,"API-COMM|2"),SUMIFS(Épopées!$L$6:$L$59,Épopées!$A$6:$A$59,"API-MODER|2"),SUMIFS(Épopées!$L$6:$L$59,Épopées!$A$6:$A$59,"MOB-J|2"),SUMIFS(Épopées!$L$6:$L$59,Épopées!$A$6:$A$59,"MOB-K|2"),SUMIFS(Épopées!$L$6:$L$59,Épopées!$A$6:$A$59,"ADM-WG|2"),SUMIFS(Épopées!$L$6:$L$59,Épopées!$A$6:$A$59,"ADM-WJ|2")) -> 46527 | K19: =MAX(SUMIFS(Épopées!$M$6:$M$59,Épopées!$A$6:$A$59,"API-COMM|2"),SUMIFS(Épopées!$M$6:$M$59,Épopées!$A$6:$A$59,"API-MODER|2"),SUMIFS(Épopées!$M$6:$M$59,Épopées!$A$6:$A$59,"MOB-J|2"),SUMIFS(Épopées!$M$6:$M$59,Épopées!$A$6:$A$59,"MOB-K|2"),SUMIFS(Épopées!$M$6:$M$59,Épopées!$A$6:$A$59,"ADM-WG|2"),SUMIFS(Épopées!$M$6:$M$59,Épopées!$A$6:$A$59,"ADM-WJ|2")) -> 46695 | L19: =NETWORKDAYS(J19,K19) -> 121 | M19: À faire
A20: 2.2 | B20: 2 | C20: Comparateur GOAT | D20: Comparateur et votes. | E20: API-GOAT, MOB-G | F20: Phase 1 | G20: Comparateur, votes, agrégats. | H20: Anti-abus testé. | I20: =SUMIFS(Épopées!$G$6:$G$59,Épopées!$A$6:$A$59,"API-GOAT|2")+SUMIFS(Épopées!$G$6:$G$59,Épopées!$A$6:$A$59,"MOB-G|2") -> 43 | J20: =MIN(SUMIFS(Épopées!$L$6:$L$59,Épopées!$A$6:$A$59,"API-GOAT|2"),SUMIFS(Épopées!$L$6:$L$59,Épopées!$A$6:$A$59,"MOB-G|2")) -> 46580 | K20: =MAX(SUMIFS(Épopées!$M$6:$M$59,Épopées!$A$6:$A$59,"API-GOAT|2"),SUMIFS(Épopées!$M$6:$M$59,Épopées!$A$6:$A$59,"MOB-G|2")) -> 46626 | L20: =NETWORKDAYS(J20,K20) -> 35 | M20: À faire
A21: 2.3 | B21: 2 | C21: Fantasy Barça | D21: Équipes fantasy, journées, classements, ligues. | E21: API-FANT, MOB-H | F21: Phase 1 (données matchs) | G21: Composition, scoring par journée, ligues. | H21: Calcul des points idempotent et testé sur matchs réels. | I21: =SUMIFS(Épopées!$G$6:$G$59,Épopées!$A$6:$A$59,"API-FANT|2")+SUMIFS(Épopées!$G$6:$G$59,Épopées!$A$6:$A$59,"MOB-H|2") -> 71.5 | J21: =MIN(SUMIFS(Épopées!$L$6:$L$59,Épopées!$A$6:$A$59,"API-FANT|2"),SUMIFS(Épopées!$L$6:$L$59,Épopées!$A$6:$A$59,"MOB-H|2")) -> 46596 | K21: =MAX(SUMIFS(Épopées!$M$6:$M$59,Épopées!$A$6:$A$59,"API-FANT|2"),SUMIFS(Épopées!$M$6:$M$59,Épopées!$A$6:$A$59,"MOB-H|2")) -> 46653 | L21: =NETWORKDAYS(J21,K21) -> 42 | M21: À faire
A22: 2.4 | B22: 2 | C22: Culé Passport | D22: Profil de gamification transverse. | E22: API-PASS, MOB-P | F22: 2.2, 2.3 | G22: XP, niveaux, badges, historique. | H22: Règles de badges validées. | I22: =SUMIFS(Épopées!$G$6:$G$59,Épopées!$A$6:$A$59,"API-PASS|2")+SUMIFS(Épopées!$G$6:$G$59,Épopées!$A$6:$A$59,"MOB-P|2") -> 54.5 | J22: =MIN(SUMIFS(Épopées!$L$6:$L$59,Épopées!$A$6:$A$59,"API-PASS|2"),SUMIFS(Épopées!$L$6:$L$59,Épopées!$A$6:$A$59,"MOB-P|2")) -> 46619 | K22: =MAX(SUMIFS(Épopées!$M$6:$M$59,Épopées!$A$6:$A$59,"API-PASS|2"),SUMIFS(Épopées!$M$6:$M$59,Épopées!$A$6:$A$59,"MOB-P|2")) -> 46710 | L22: =NETWORKDAYS(J22,K22) -> 66 | M22: À faire
A23: 2.5 | B23: 2 | C23: Durcissement plateforme | D23: Performance, sécurité et charge de la phase 2. | E23: API-PLAT | F23: Phase 2 (en continu) | G23: Index, caches, tests de charge étendus. | H23: Test de charge « soir de match » validé. | I23: =SUMIFS(Épopées!$G$6:$G$59,Épopées!$A$6:$A$59,"API-PLAT|2") -> 3 | J23: =MIN(SUMIFS(Épopées!$L$6:$L$59,Épopées!$A$6:$A$59,"API-PLAT|2")) -> 46643 | K23: =MAX(SUMIFS(Épopées!$M$6:$M$59,Épopées!$A$6:$A$59,"API-PLAT|2")) -> 46644 | L23: =NETWORKDAYS(J23,K23) -> 2 | M23: À faire
A24: 2.6 | B24: 2 | C24: Recette phase 2 | D24: Valider la version communautaire. | E24: Aucune épopée — durée fixe (Paramètres) | F24: 2.1 à 2.5 | G24: Rapport de recette phase 2. | H24: Critères §15.2 atteints. | I24: 0 | J24: =WORKDAY(MAX(K19,K20,K21,K22,K23),1) -> 46713 | K24: =WORKDAY(J24,Paramètres!$B$11-1) -> 46724 | L24: =NETWORKDAYS(J24,K24) -> 10 | M24: À faire
A25: 3.1 | B25: 3 | C25: La Masia Academy | D25: Académie fantasy. | E25: API-FANT, MOB-I | F25: Phase 2 (Fantasy) | G25: Joueurs d’académie, progression. | H25: Règles validées avec le porteur du projet. | I25: =SUMIFS(Épopées!$G$6:$G$59,Épopées!$A$6:$A$59,"API-FANT|3")+SUMIFS(Épopées!$G$6:$G$59,Épopées!$A$6:$A$59,"MOB-I|3") -> 34 | J25: =MIN(SUMIFS(Épopées!$L$6:$L$59,Épopées!$A$6:$A$59,"API-FANT|3"),SUMIFS(Épopées!$L$6:$L$59,Épopées!$A$6:$A$59,"MOB-I|3")) -> 46645 | K25: =MAX(SUMIFS(Épopées!$M$6:$M$59,Épopées!$A$6:$A$59,"API-FANT|3"),SUMIFS(Épopées!$M$6:$M$59,Épopées!$A$6:$A$59,"MOB-I|3")) -> 46727 | L25: =NETWORKDAYS(J25,K25) -> 59 | M25: À faire
A26: 3.2 | B26: 3 | C26: Wallpapers IA | D26: Génération d’images, galerie, partage. | E26: API-WALL, MOB-M | F26: Phase 1 (IA) | G26: Génération, file d’attente, modération des images, galerie. | H26: Aucun logo du club ; coûts maîtrisés. | I26: =SUMIFS(Épopées!$G$6:$G$59,Épopées!$A$6:$A$59,"API-WALL|3")+SUMIFS(Épopées!$G$6:$G$59,Épopées!$A$6:$A$59,"MOB-M|3") -> 52.25 | J26: =MIN(SUMIFS(Épopées!$L$6:$L$59,Épopées!$A$6:$A$59,"API-WALL|3"),SUMIFS(Épopées!$L$6:$L$59,Épopées!$A$6:$A$59,"MOB-M|3")) -> 46653 | K26: =MAX(SUMIFS(Épopées!$M$6:$M$59,Épopées!$A$6:$A$59,"API-WALL|3"),SUMIFS(Épopées!$M$6:$M$59,Épopées!$A$6:$A$59,"MOB-M|3")) -> 46748 | L26: =NETWORKDAYS(J26,K26) -> 68 | M26: À faire
A27: 3.3 | B27: 3 | C27: Évolutions admin phase 3 | D27: Compléments du back-office. | E27: ADM-WJ | F27: Phase 2 | G27: Écrans évolutions phase 3. | H27: Recette admin. | I27: =SUMIFS(Épopées!$G$6:$G$59,Épopées!$A$6:$A$59,"ADM-WJ|3") -> 6 | J27: =MIN(SUMIFS(Épopées!$L$6:$L$59,Épopées!$A$6:$A$59,"ADM-WJ|3")) -> 46673 | K27: =MAX(SUMIFS(Épopées!$M$6:$M$59,Épopées!$A$6:$A$59,"ADM-WJ|3")) -> 46679 | L27: =NETWORKDAYS(J27,K27) -> 5 | M27: À faire
A28: 3.4 | B28: 3 | C28: Recette finale, charge et mise en production | D28: Finaliser, mesurer et publier. | E28: Aucune épopée — durée fixe (Paramètres) | F28: 3.1 à 3.3 | G28: Campagne de charge finale, documentation, publication stores, tag de version production. | H28: Périmètre complet livré ; observabilité sans anomalie. | I28: 0 | J28: =WORKDAY(MAX(K25,K26,K27),1) -> 46749 | K28: =WORKDAY(J28,Paramètres!$B$11-1) -> 46762 | L28: =NETWORKDAYS(J28,K28) -> 10 | M28: À faire

Sheet Jalons
A1: Jalons du projet
A2: Dates calculées depuis le planning ; « Date réelle » et « Statut » sont à saisir au fil de l’eau.
A5: N° | B5: Jalon | C5: Phase | D5: Date prévue | E5: Critères de sortie (CDC §5.5 et §15.2) | F5: Date réelle | G5: Écart (jours) | H5: Statut
A6: M0 | B6: Lancement du projet (kick-off) | C6: 0 | D6: =Paramètres!$B$4 -> 46328 | E6: Secrets, environnements, projet GitHub et décisions « à confirmer » traités. | G6: =IF(F6="","",F6-D6) | H6: Terminé
A7: M1 | B7: Phase 0 terminée — socle opérationnel | C7: 0 | D7: =WORKDAY(_xlfn.MAXIFS(Épopées!$M$6:$M$59,Épopées!$E$6:$E$59,0),Paramètres!$B$11) -> 46449 | E7: Environnements opérationnels ; premier commit déployé en staging ; CI/CD verte ; design system implémenté (mobile + admin) ; observabilité de base. | G7: =IF(F7="","",F7-D7) | H7: À faire
A8: M2 | B8: Phase 1 terminée — MVP | C8: 1 | D8: =WORKDAY(_xlfn.MAXIFS(Épopées!$M$6:$M$59,Épopées!$E$6:$E$59,1),Paramètres!$B$11) -> 46629 | E8: Dashboard, jeux quotidiens, historique, calendrier + export agenda, assistant IA v1, admin de base ; version testable par un cercle restreint ; recette UAT validée ; aucune anomalie bloquante ; 48 h d’observation staging. | G8: =IF(F8="","",F8-D8) | H8: À faire
A9: M3 | B9: Phase 2 terminée — version communautaire | C9: 2 | D9: =WORKDAY(_xlfn.MAXIFS(Épopées!$M$6:$M$59,Épopées!$E$6:$E$59,2),Paramètres!$B$11) -> 46724 | E9: GOAT, Fantasy, carte communautaire et groupes, modération, Culé Passport ; test de charge « soir de match » ; revue RGPD de la géolocalisation. | G9: =IF(F9="","",F9-D9) | H9: À faire
A10: M4 | B10: Phase 3 terminée — périmètre complet | C10: 3 | D10: =WORKDAY(_xlfn.MAXIFS(Épopées!$M$6:$M$59,Épopées!$E$6:$E$59,3),Paramètres!$B$11) -> 46762 | E10: La Masia, Wallpapers IA, approfondissement IA ; recette finale ; campagne de charge finale ; documentation à jour ; publication sur les stores. | G10: =IF(F10="","",F10-D10) | H10: À faire
A12: Jalons intermédiaires par flux
A13: N° | B13: Jalon | C13: Phase | D13: Date prévue | E13: Contenu | F13: Date réelle | G13: Écart (jours) | H13: Statut
A14: API-P0 | B14: Fin du flux API — phase 0 | C14: 0 | D14: =_xlfn.MAXIFS(Épopées!$M$6:$M$59,Épopées!$E$6:$E$59,0,Épopées!$B$6:$B$59,"API") -> 46332 | E14: Toutes les épopées API de la phase 0 terminées (voir « Épopées »). | G14: =IF(F14="","",F14-D14) | H14: À faire
A15: API-P1 | B15: Fin du flux API — phase 1 | C15: 1 | D15: =_xlfn.MAXIFS(Épopées!$M$6:$M$59,Épopées!$E$6:$E$59,1,Épopées!$B$6:$B$59,"API") -> 46526 | E15: Toutes les épopées API de la phase 1 terminées (voir « Épopées »). | G15: =IF(F15="","",F15-D15) | H15: À faire
A16: API-P2 | B16: Fin du flux API — phase 2 | C16: 2 | D16: =_xlfn.MAXIFS(Épopées!$M$6:$M$59,Épopées!$E$6:$E$59,2,Épopées!$B$6:$B$59,"API") -> 46644 | E16: Toutes les épopées API de la phase 2 terminées (voir « Épopées »). | G16: =IF(F16="","",F16-D16) | H16: À faire
A17: API-P3 | B17: Fin du flux API — phase 3 | C17: 3 | D17: =_xlfn.MAXIFS(Épopées!$M$6:$M$59,Épopées!$E$6:$E$59,3,Épopées!$B$6:$B$59,"API") -> 46667 | E17: Toutes les épopées API de la phase 3 terminées (voir « Épopées »). | G17: =IF(F17="","",F17-D17) | H17: À faire
A18: MOB-P0 | B18: Fin du flux Mobile — phase 0 | C18: 0 | D18: =_xlfn.MAXIFS(Épopées!$M$6:$M$59,Épopées!$E$6:$E$59,0,Épopées!$B$6:$B$59,"Mobile") -> 46435 | E18: Toutes les épopées Mobile de la phase 0 terminées (voir « Épopées »). | G18: =IF(F18="","",F18-D18) | H18: À faire
A19: MOB-P1 | B19: Fin du flux Mobile — phase 1 | C19: 1 | D19: =_xlfn.MAXIFS(Épopées!$M$6:$M$59,Épopées!$E$6:$E$59,1,Épopées!$B$6:$B$59,"Mobile") -> 46615 | E19: Toutes les épopées Mobile de la phase 1 terminées (voir « Épopées »). | G19: =IF(F19="","",F19-D19) | H19: À faire
A20: MOB-P2 | B20: Fin du flux Mobile — phase 2 | C20: 2 | D20: =_xlfn.MAXIFS(Épopées!$M$6:$M$59,Épopées!$E$6:$E$59,2,Épopées!$B$6:$B$59,"Mobile") -> 46710 | E20: Toutes les épopées Mobile de la phase 2 terminées (voir « Épopées »). | G20: =IF(F20="","",F20-D20) | H20: À faire
A21: MOB-P3 | B21: Fin du flux Mobile — phase 3 | C21: 3 | D21: =_xlfn.MAXIFS(Épopées!$M$6:$M$59,Épopées!$E$6:$E$59,3,Épopées!$B$6:$B$59,"Mobile") -> 46748 | E21: Toutes les épopées Mobile de la phase 3 terminées (voir « Épopées »). | G21: =IF(F21="","",F21-D21) | H21: À faire
A22: ADM-P0 | B22: Fin du flux Admin — phase 0 | C22: 0 | D22: =_xlfn.MAXIFS(Épopées!$M$6:$M$59,Épopées!$E$6:$E$59,0,Épopées!$B$6:$B$59,"Admin") -> 46387 | E22: Toutes les épopées Admin de la phase 0 terminées (voir « Épopées »). | G22: =IF(F22="","",F22-D22) | H22: À faire
A23: ADM-P1 | B23: Fin du flux Admin — phase 1 | C23: 1 | D23: =_xlfn.MAXIFS(Épopées!$M$6:$M$59,Épopées!$E$6:$E$59,1,Épopées!$B$6:$B$59,"Admin") -> 46573 | E23: Toutes les épopées Admin de la phase 1 terminées (voir « Épopées »). | G23: =IF(F23="","",F23-D23) | H23: À faire
A24: ADM-P2 | B24: Fin du flux Admin — phase 2 | C24: 2 | D24: =_xlfn.MAXIFS(Épopées!$M$6:$M$59,Épopées!$E$6:$E$59,2,Épopées!$B$6:$B$59,"Admin") -> 46609 | E24: Toutes les épopées Admin de la phase 2 terminées (voir « Épopées »). | G24: =IF(F24="","",F24-D24) | H24: À faire
A25: ADM-P3 | B25: Fin du flux Admin — phase 3 | C25: 3 | D25: =_xlfn.MAXIFS(Épopées!$M$6:$M$59,Épopées!$E$6:$E$59,3,Épopées!$B$6:$B$59,"Admin") -> 46679 | E25: Toutes les épopées Admin de la phase 3 terminées (voir « Épopées »). | G25: =IF(F25="","",F25-D25) | H25: À faire

Sheet Gantt
A1: Diagramme de Gantt (par semaine)
A2: Barres colorées par phase, calculées depuis « Épopées ». Trait rouge = semaine en cours. Ligne ◆ = jalons de fin de phase.
A5: Flux | B5: Épopée | C5: Intitulé | D5: Phase | E5: Début | F5: Fin | G5: Avancement | H5: =Paramètres!$B$4-WEEKDAY(Paramètres!$B$4,2)+1 -> 46328 | I5: =H5+7 -> 46335 | J5: =I5+7 -> 46342 | K5: =J5+7 -> 46349 | L5: =K5+7 -> 46356 | M5: =L5+7 -> 46363 | N5: =M5+7 -> 46370 | O5: =N5+7 -> 46377 | P5: =O5+7 -> 46384 | ... CS5: =CR5+7 -> 46951
A6: =Épopées!B6 -> API | B6: =Épopées!C6 -> API-PLAT | C6: =Épopées!D6 -> Plateforme, qualité, performance et exploitation | D6: =Épopées!E6 -> 0 | E6: =Épopées!L6 -> 46328 | F6: =Épopées!M6 -> 46331 | G6: =Épopées!O6 -> 0
A7: =Épopées!B7 -> API | B7: =Épopées!C7 -> API-AUTH | C7: =Épopées!D7 -> Identité, authentification, comptes et RGPD | D7: =Épopées!E7 -> 0 | E7: =Épopées!L7 -> 46332 | F7: =Épopées!M7 -> 46332 | G7: =Épopées!O7 -> 0
A8: =Épopées!B8 -> API | B8: =Épopées!C8 -> API-PLAT | C8: =Épopées!D8 -> Plateforme, qualité, performance et exploitation | D8: =Épopées!E8 -> 1 | E8: =Épopées!L8 -> 46335 | F8: =Épopées!M8 -> 46363 | G8: =Épopées!O8 -> 0
A9: =Épopées!B9 -> API | B9: =Épopées!C9 -> API-AUTH | C9: =Épopées!D9 -> Identité, authentification, comptes et RGPD | D9: =Épopées!E9 -> 1 | E9: =Épopées!L9 -> 46364 | F9: =Épopées!M9 -> 46398 | G9: =Épopées!O9 -> 0
A10: =Épopées!B10 -> API | B10: =Épopées!C10 -> API-FOOT | C10: =Épopées!D10 -> Données football et contenu éditorial | D10: =Épopées!E10 -> 1 | E10: =Épopées!L10 -> 46399 | F10: =Épopées!M10 -> 46440 | G10: =Épopées!O10 -> 0
A11: =Épopées!B11 -> API | B11: =Épopées!C11 -> API-CAL | C11: =Épopées!D11 -> Calendrier et export agenda | D11: =Épopées!E11 -> 1 | E11: =Épopées!L11 -> 46441 | F11: =Épopées!M11 -> 46451 | G11: =Épopées!O11 -> 0
A12: =Épopées!B12 -> API | B12: =Épopées!C12 -> API-JEUX | C12: =Épopées!D12 -> Guess the Player & Quiz adaptatif | D12: =Épopées!E12 -> 1 | E12: =Épopées!L12 -> 46454 | F12: =Épopées!M12 -> 46484 | G12: =Épopées!O12 -> 0
A13: =Épopées!B13 -> API | B13: =Épopées!C13 -> API-NOTIF | C13: =Épopées!D13 -> Notifications push et centre de notifications | D13: =Épopées!E13 -> 1 | E13: =Épopées!L13 -> 46485 | F13: =Épopées!M13 -> 46505 | G13: =Épopées!O13 -> 0
A14: =Épopées!B14 -> API | B14: =Épopées!C14 -> API-IA | C14: =Épopées!D14 -> Assistant IA Barça AI | D14: =Épopées!E14 -> 1 | E14: =Épopées!L14 -> 46506 | F14: =Épopées!M14 -> 46526 | G14: =Épopées!O14 -> 0
A15: =Épopées!B15 -> API | B15: =Épopées!C15 -> API-COMM | C15: =Épopées!D15 -> Carte communautaire et groupes locaux | D15: =Épopées!E15 -> 2 | E15: =Épopées!L15 -> 46527 | F15: =Épopées!M15 -> 46552 | G15: =Épopées!O15 -> 0
A16: =Épopées!B16 -> API | B16: =Épopées!C16 -> API-MODER | C16: =Épopées!D16 -> Modération et sécurité communautaire | D16: =Épopées!E16 -> 2 | E16: =Épopées!L16 -> 46553 | F16: =Épopées!M16 -> 46577 | G16: =Épopées!O16 -> 0
A17: =Épopées!B17 -> API | B17: =Épopées!C17 -> API-GOAT | C17: =Épopées!D17 -> Comparateur GOAT et votes | D17: =Épopées!E17 -> 2 | E17: =Épopées!L17 -> 46580 | F17: =Épopées!M17 -> 46595 | G17: =Épopées!O17 -> 0
... A59: =Épopées!B59 -> Admin | B59: =Épopées!C59 -> ADM-WJ | C59: =Épopées!D59 -> Utilisateurs et évolutions phase 2-3 | D59: =Épopées!E59 -> 3 | E59: =Épopées!L59 -> 46673 | F59: =Épopées!M59 -> 46679 | G59: =Épopées!O59 -> 0
C61: Jalons (fin de phase + recette) | H61: =IF(OR(AND(Jalons!$D$7>=H$5,Jalons!$D$7<H$5+7),AND(Jalons!$D$8>=H$5,Jalons!$D$8<H$5+7),AND(Jalons!$D$9>=H$5,Jalons!$D$9<H$5+7),AND(Jalons!$D$10>=H$5,Jalons!$D$10<H$5+7)),"◆","") | I61: =IF(OR(AND(Jalons!$D$7>=I$5,Jalons!$D$7<I$5+7),AND(Jalons!$D$8>=I$5,Jalons!$D$8<I$5+7),AND(Jalons!$D$9>=I$5,Jalons!$D$9<I$5+7),AND(Jalons!$D$10>=I$5,Jalons!$D$10<I$5+7)),"◆","") | J61: =IF(OR(AND(Jalons!$D$7>=J$5,Jalons!$D$7<J$5+7),AND(Jalons!$D$8>=J$5,Jalons!$D$8<J$5+7),AND(Jalons!$D$9>=J$5,Jalons!$D$9<J$5+7),AND(Jalons!$D$10>=J$5,Jalons!$D$10<J$5+7)),"◆","") | K61: =IF(OR(AND(Jalons!$D$7>=K$5,Jalons!$D$7<K$5+7),AND(Jalons!$D$8>=K$5,Jalons!$D$8<K$5+7),AND(Jalons!$D$9>=K$5,Jalons!$D$9<K$5+7),AND(Jalons!$D$10>=K$5,Jalons!$D$10<K$5+7)),"◆","") | L61: =IF(OR(AND(Jalons!$D$7>=L$5,Jalons!$D$7<L$5+7),AND(Jalons!$D$8>=L$5,Jalons!$D$8<L$5+7),AND(Jalons!$D$9>=L$5,Jalons!$D$9<L$5+7),AND(Jalons!$D$10>=L$5,Jalons!$D$10<L$5+7)),"◆","") | M61: =IF(OR(AND(Jalons!$D$7>=M$5,Jalons!$D$7<M$5+7),AND(Jalons!$D$8>=M$5,Jalons!$D$8<M$5+7),AND(Jalons!$D$9>=M$5,Jalons!$D$9<M$5+7),AND(Jalons!$D$10>=M$5,Jalons!$D$10<M$5+7)),"◆","") | N61: =IF(OR(AND(Jalons!$D$7>=N$5,Jalons!$D$7<N$5+7),AND(Jalons!$D$8>=N$5,Jalons!$D$8<N$5+7),AND(Jalons!$D$9>=N$5,Jalons!$D$9<N$5+7),AND(Jalons!$D$10>=N$5,Jalons!$D$10<N$5+7)),"◆","") | O61: =IF(OR(AND(Jalons!$D$7>=O$5,Jalons!$D$7<O$5+7),AND(Jalons!$D$8>=O$5,Jalons!$D$8<O$5+7),AND(Jalons!$D$9>=O$5,Jalons!$D$9<O$5+7),AND(Jalons!$D$10>=O$5,Jalons!$D$10<O$5+7)),"◆","") | ... CS61: =IF(OR(AND(Jalons!$D$7>=CS$5,Jalons!$D$7<CS$5+7),AND(Jalons!$D$8>=CS$5,Jalons!$D$8<CS$5+7),AND(Jalons!$D$9>=CS$5,Jalons!$D$9<CS$5+7),AND(Jalons!$D$10>=CS$5,Jalons!$D$10<CS$5+7)),"◆","")

Sheet Épopées
A1: Plan par épopée (flux × phase)
A2: Durée = charge × (1 + marge) ÷ (développeurs × focus). Début = max(fin de l’épopée précédente du flux, porte de phase). Tout est recalculé depuis « Paramètres ».
A5: Clé | B5: Flux | C5: Épopée | D5: Intitulé | E5: Phase | F5: Nb issues | G5: Charge (j) | H5: Devs | I5: Durée (jo) | J5: Porte de phase | K5: Semaines | L5: Début | M5: Fin | N5: Terminées | O5: % avancement | P5: Statut
A6: API-PLAT|0 | B6: API | C6: API-PLAT | D6: Plateforme, qualité, performance et exploitation | E6: 0 | F6: =COUNTIFS(Backlog!$K$6:$K$1327,A6) -> 10 | G6: =SUMIFS(Backlog!$I$6:$I$1327,Backlog!$K$6:$K$1327,A6) -> 6.75 | H6: =IF(B6="API",Paramètres!$B$7,IF(B6="Mobile",Paramètres!$B$8,Paramètres!$B$9)) -> 3 | I6: =MAX(1,ROUNDUP(G6*(1+Paramètres!$B$6)/(H6*Paramètres!$B$5),0)) -> 4 | J6: =Paramètres!$B$4 -> 46328 | K6: =ROUNDUP(I6/5,0) -> 1 | L6: =J6 -> 46328 | M6: =WORKDAY(L6,I6-1) -> 46331 | N6: =COUNTIFS(Backlog!$K$6:$K$1327,A6,Backlog!$O$6:$O$1327,"Terminé") -> 0 | O6: =IF(F6=0,0,N6/F6) -> 0 | P6: =IF(O6=1,"Terminé",IF(OR(O6>0,COUNTIFS(Backlog!$K$6:$K$1327,A6,Backlog!$O$6:$O$1327,"En cours")>0),"En cours","À faire")) -> À faire
A7: API-AUTH|0 | B7: API | C7: API-AUTH | D7: Identité, authentification, comptes et RGPD | E7: 0 | F7: =COUNTIFS(Backlog!$K$6:$K$1327,A7) -> 2 | G7: =SUMIFS(Backlog!$I$6:$I$1327,Backlog!$K$6:$K$1327,A7) -> 2 | H7: =IF(B7="API",Paramètres!$B$7,IF(B7="Mobile",Paramètres!$B$8,Paramètres!$B$9)) -> 3 | I7: =MAX(1,ROUNDUP(G7*(1+Paramètres!$B$6)/(H7*Paramètres!$B$5),0)) -> 1 | J7: =Paramètres!$B$4 -> 46328 | K7: =ROUNDUP(I7/5,0) -> 1 | L7: =MAX(J7,WORKDAY(M6,1)) -> 46332 | M7: =WORKDAY(L7,I7-1) -> 46332 | N7: =COUNTIFS(Backlog!$K$6:$K$1327,A7,Backlog!$O$6:$O$1327,"Terminé") -> 0 | O7: =IF(F7=0,0,N7/F7) -> 0 | P7: =IF(O7=1,"Terminé",IF(OR(O7>0,COUNTIFS(Backlog!$K$6:$K$1327,A7,Backlog!$O$6:$O$1327,"En cours")>0),"En cours","À faire")) -> À faire
A8: API-PLAT|1 | B8: API | C8: API-PLAT | D8: Plateforme, qualité, performance et exploitation | E8: 1 | F8: =COUNTIFS(Backlog!$K$6:$K$1327,A8) -> 43 | G8: =SUMIFS(Backlog!$I$6:$I$1327,Backlog!$K$6:$K$1327,A8) -> 42 | H8: =IF(B8="API",Paramètres!$B$7,IF(B8="Mobile",Paramètres!$B$8,Paramètres!$B$9)) -> 3 | I8: =MAX(1,ROUNDUP(G8*(1+Paramètres!$B$6)/(H8*Paramètres!$B$5),0)) -> 21 | J8: =Paramètres!$B$4 -> 46328 | K8: =ROUNDUP(I8/5,0) -> 5 | L8: =MAX(J8,WORKDAY(M7,1)) -> 46335 | M8: =WORKDAY(L8,I8-1) -> 46363 | N8: =COUNTIFS(Backlog!$K$6:$K$1327,A8,Backlog!$O$6:$O$1327,"Terminé") -> 0 | O8: =IF(F8=0,0,N8/F8) -> 0 | P8: =IF(O8=1,"Terminé",IF(OR(O8>0,COUNTIFS(Backlog!$K$6:$K$1327,A8,Backlog!$O$6:$O$1327,"En cours")>0),"En cours","À faire")) -> À faire
A9: API-AUTH|1 | B9: API | C9: API-AUTH | D9: Identité, authentification, comptes et RGPD | E9: 1 | F9: =COUNTIFS(Backlog!$K$6:$K$1327,A9) -> 43 | G9: =SUMIFS(Backlog!$I$6:$I$1327,Backlog!$K$6:$K$1327,A9) -> 51 | H9: =IF(B9="API",Paramètres!$B$7,IF(B9="Mobile",Paramètres!$B$8,Paramètres!$B$9)) -> 3 | I9: =MAX(1,ROUNDUP(G9*(1+Paramètres!$B$6)/(H9*Paramètres!$B$5),0)) -> 25 | J9: =Paramètres!$B$4 -> 46328 | K9: =ROUNDUP(I9/5,0) -> 5 | L9: =MAX(J9,WORKDAY(M8,1)) -> 46364 | M9: =WORKDAY(L9,I9-1) -> 46398 | N9: =COUNTIFS(Backlog!$K$6:$K$1327,A9,Backlog!$O$6:$O$1327,"Terminé") -> 0 | O9: =IF(F9=0,0,N9/F9) -> 0 | P9: =IF(O9=1,"Terminé",IF(OR(O9>0,COUNTIFS(Backlog!$K$6:$K$1327,A9,Backlog!$O$6:$O$1327,"En cours")>0),"En cours","À faire")) -> À faire
A10: API-FOOT|1 | B10: API | C10: API-FOOT | D10: Données football et contenu éditorial | E10: 1 | F10: =COUNTIFS(Backlog!$K$6:$K$1327,A10) -> 56 | G10: =SUMIFS(Backlog!$I$6:$I$1327,Backlog!$K$6:$K$1327,A10) -> 61.5 | H10: =IF(B10="API",Paramètres!$B$7,IF(B10="Mobile",Paramètres!$B$8,Paramètres!$B$9)) -> 3 | I10: =MAX(1,ROUNDUP(G10*(1+Paramètres!$B$6)/(H10*Paramètres!$B$5),0)) -> 30 | J10: =Paramètres!$B$4 -> 46328 | K10: =ROUNDUP(I10/5,0) -> 6 | L10: =MAX(J10,WORKDAY(M9,1)) -> 46399 | M10: =WORKDAY(L10,I10-1) -> 46440 | N10: =COUNTIFS(Backlog!$K$6:$K$1327,A10,Backlog!$O$6:$O$1327,"Terminé") -> 0 | O10: =IF(F10=0,0,N10/F10) -> 0 | P10: =IF(O10=1,"Terminé",IF(OR(O10>0,COUNTIFS(Backlog!$K$6:$K$1327,A10,Backlog!$O$6:$O$1327,"En cours")>0),"En cours","À faire")) -> À faire
A11: API-CAL|1 | B11: API | C11: API-CAL | D11: Calendrier et export agenda | E11: 1 | F11: =COUNTIFS(Backlog!$K$6:$K$1327,A11) -> 24 | G11: =SUMIFS(Backlog!$I$6:$I$1327,Backlog!$K$6:$K$1327,A11) -> 18 | H11: =IF(B11="API",Paramètres!$B$7,IF(B11="Mobile",Paramètres!$B$8,Paramètres!$B$9)) -> 3 | I11: =MAX(1,ROUNDUP(G11*(1+Paramètres!$B$6)/(H11*Paramètres!$B$5),0)) -> 9 | J11: =Paramètres!$B$4 -> 46328 | K11: =ROUNDUP(I11/5,0) -> 2 | L11: =MAX(J11,WORKDAY(M10,1)) -> 46441 | M11: =WORKDAY(L11,I11-1) -> 46451 | N11: =COUNTIFS(Backlog!$K$6:$K$1327,A11,Backlog!$O$6:$O$1327,"Terminé") -> 0 | O11: =IF(F11=0,0,N11/F11) -> 0 | P11: =IF(O11=1,"Terminé",IF(OR(O11>0,COUNTIFS(Backlog!$K$6:$K$1327,A11,Backlog!$O$6:$O$1327,"En cours")>0),"En cours","À faire")) -> À faire
A12: API-JEUX|1 | B12: API | C12: API-JEUX | D12: Guess the Player & Quiz adaptatif | E12: 1 | F12: =COUNTIFS(Backlog!$K$6:$K$1327,A12) -> 37 | G12: =SUMIFS(Backlog!$I$6:$I$1327,Backlog!$K$6:$K$1327,A12) -> 48 | H12: =IF(B12="API",Paramètres!$B$7,IF(B12="Mobile",Paramètres!$B$8,Paramètres!$B$9)) -> 3 | I12: =MAX(1,ROUNDUP(G12*(1+Paramètres!$B$6)/(H12*Paramètres!$B$5),0)) -> 23 | J12: =Paramètres!$B$4 -> 46328 | K12: =ROUNDUP(I12/5,0) -> 5 | L12: =MAX(J12,WORKDAY(M11,1)) -> 46454 | M12: =WORKDAY(L12,I12-1) -> 46484 | N12: =COUNTIFS(Backlog!$K$6:$K$1327,A12,Backlog!$O$6:$O$1327,"Terminé") -> 0 | O12: =IF(F12=0,0,N12/F12) -> 0 | P12: =IF(O12=1,"Terminé",IF(OR(O12>0,COUNTIFS(Backlog!$K$6:$K$1327,A12,Backlog!$O$6:$O$1327,"En cours")>0),"En cours","À faire")) -> À faire
A13: API-NOTIF|1 | B13: API | C13: API-NOTIF | D13: Notifications push et centre de notifications | E13: 1 | F13: =COUNTIFS(Backlog!$K$6:$K$1327,A13) -> 31 | G13: =SUMIFS(Backlog!$I$6:$I$1327,Backlog!$K$6:$K$1327,A13) -> 30 | H13: =IF(B13="API",Paramètres!$B$7,IF(B13="Mobile",Paramètres!$B$8,Paramètres!$B$9)) -> 3 | I13: =MAX(1,ROUNDUP(G13*(1+Paramètres!$B$6)/(H13*Paramètres!$B$5),0)) -> 15 | J13: =Paramètres!$B$4 -> 46328 | K13: =ROUNDUP(I13/5,0) -> 3 | L13: =MAX(J13,WORKDAY(M12,1)) -> 46485 | M13: =WORKDAY(L13,I13-1) -> 46505 | N13: =COUNTIFS(Backlog!$K$6:$K$1327,A13,Backlog!$O$6:$O$1327,"Terminé") -> 0 | O13: =IF(F13=0,0,N13/F13) -> 0 | P13: =IF(O13=1,"Terminé",IF(OR(O13>0,COUNTIFS(Backlog!$K$6:$K$1327,A13,Backlog!$O$6:$O$1327,"En cours")>0),"En cours","À faire")) -> À faire
A14: API-IA|1 | B14: API | C14: API-IA | D14: Assistant IA Barça AI | E14: 1 | F14: =COUNTIFS(Backlog!$K$6:$K$1327,A14) -> 34 | G14: =SUMIFS(Backlog!$I$6:$I$1327,Backlog!$K$6:$K$1327,A14) -> 30.5 | H14: =IF(B14="API",Paramètres!$B$7,IF(B14="Mobile",Paramètres!$B$8,Paramètres!$B$9)) -> 3 | I14: =MAX(1,ROUNDUP(G14*(1+Paramètres!$B$6)/(H14*Paramètres!$B$5),0)) -> 15 | J14: =Paramètres!$B$4 -> 46328 | K14: =ROUNDUP(I14/5,0) -> 3 | L14: =MAX(J14,WORKDAY(M13,1)) -> 46506 | M14: =WORKDAY(L14,I14-1) -> 46526 | N14: =COUNTIFS(Backlog!$K$6:$K$1327,A14,Backlog!$O$6:$O$1327,"Terminé") -> 0 | O14: =IF(F14=0,0,N14/F14) -> 0 | P14: =IF(O14=1,"Terminé",IF(OR(O14>0,COUNTIFS(Backlog!$K$6:$K$1327,A14,Backlog!$O$6:$O$1327,"En cours")>0),"En cours","À faire")) -> À faire
A15: API-COMM|2 | B15: API | C15: API-COMM | D15: Carte communautaire et groupes locaux | E15: 2 | F15: =COUNTIFS(Backlog!$K$6:$K$1327,A15) -> 33 | G15: =SUMIFS(Backlog!$I$6:$I$1327,Backlog!$K$6:$K$1327,A15) -> 36 | H15: =IF(B15="API",Paramètres!$B$7,IF(B15="Mobile",Paramètres!$B$8,Paramètres!$B$9)) -> 3 | I15: =MAX(1,ROUNDUP(G15*(1+Paramètres!$B$6)/(H15*Paramètres!$B$5),0)) -> 18 | J15: =Paramètres!$B$4 -> 46328 | K15: =ROUNDUP(I15/5,0) -> 4 | L15: =MAX(J15,WORKDAY(M14,1)) -> 46527 | M15: =WORKDAY(L15,I15-1) -> 46552 | N15: =COUNTIFS(Backlog!$K$6:$K$1327,A15,Backlog!$O$6:$O$1327,"Terminé") -> 0 | O15: =IF(F15=0,0,N15/F15) -> 0 | P15: =IF(O15=1,"Terminé",IF(OR(O15>0,COUNTIFS(Backlog!$K$6:$K$1327,A15,Backlog!$O$6:$O$1327,"En cours")>0),"En cours","À faire")) -> À faire
A16: API-MODER|2 | B16: API | C16: API-MODER | D16: Modération et sécurité communautaire | E16: 2 | F16: =COUNTIFS(Backlog!$K$6:$K$1327,A16) -> 32 | G16: =SUMIFS(Backlog!$I$6:$I$1327,Backlog!$K$6:$K$1327,A16) -> 38.5 | H16: =IF(B16="API",Paramètres!$B$7,IF(B16="Mobile",Paramètres!$B$8,Paramètres!$B$9)) -> 3 | I16: =MAX(1,ROUNDUP(G16*(1+Paramètres!$B$6)/(H16*Paramètres!$B$5),0)) -> 19 | J16: =Paramètres!$B$4 -> 46328 | K16: =ROUNDUP(I16/5,0) -> 4 | L16: =MAX(J16,WORKDAY(M15,1)) -> 46553 | M16: =WORKDAY(L16,I16-1) -> 46577 | N16: =COUNTIFS(Backlog!$K$6:$K$1327,A16,Backlog!$O$6:$O$1327,"Terminé") -> 0 | O16: =IF(F16=0,0,N16/F16) -> 0 | P16: =IF(O16=1,"Terminé",IF(OR(O16>0,COUNTIFS(Backlog!$K$6:$K$1327,A16,Backlog!$O$6:$O$1327,"En cours")>0),"En cours","À faire")) -> À faire
A17: API-GOAT|2 | B17: API | C17: API-GOAT | D17: Comparateur GOAT et votes | E17: 2 | F17: =COUNTIFS(Backlog!$K$6:$K$1327,A17) -> 26 | G17: =SUMIFS(Backlog!$I$6:$I$1327,Backlog!$K$6:$K$1327,A17) -> 25 | H17: =IF(B17="API",Paramètres!$B$7,IF(B17="Mobile",Paramètres!$B$8,Paramètres!$B$9)) -> 3 | I17: =MAX(1,ROUNDUP(G17*(1+Paramètres!$B$6)/(H17*Paramètres!$B$5),0)) -> 12 | J17: =Paramètres!$B$4 -> 46328 | K17: =ROUNDUP(I17/5,0) -> 3 | L17: =MAX(J17,WORKDAY(M16,1)) -> 46580 | M17: =WORKDAY(L17,I17-1) -> 46595 | N17: =COUNTIFS(Backlog!$K$6:$K$1327,A17,Backlog!$O$6:$O$1327,"Terminé") -> 0 | O17: =IF(F17=0,0,N17/F17) -> 0 | P17: =IF(O17=1,"Terminé",IF(OR(O17>0,COUNTIFS(Backlog!$K$6:$K$1327,A17,Backlog!$O$6:$O$1327,"En cours")>0),"En cours","À faire")) -> À faire
A18: API-FANT|2 | B18: API | C18: API-FANT | D18: Fantasy Barça et La Masia Academy | E18: 2 | F18: =COUNTIFS(Backlog!$K$6:$K$1327,A18) -> 24 | G18: =SUMIFS(Backlog!$I$6:$I$1327,Backlog!$K$6:$K$1327,A18) -> 33.5 | H18: =IF(B18="API",Paramètres!$B$7,IF(B18="Mobile",Paramètres!$B$8,Paramètres!$B$9)) -> 3 | I18: =MAX(1,ROUNDUP(G18*(1+Paramètres!$B$6)/(H18*Paramètres!$B$5),0)) -> 17 | J18: =Paramètres!$B$4 -> 46328 | K18: =ROUNDUP(I18/5,0) -> 4 | L18: =MAX(J18,WORKDAY(M17,1)) -> 46596 | M18: =WORKDAY(L18,I18-1) -> 46618 | N18: =COUNTIFS(Backlog!$K$6:$K$1327,A18,Backlog!$O$6:$O$1327,"Terminé") -> 0 | O18: =IF(F18=0,0,N18/F18) -> 0 | P18: =IF(O18=1,"Terminé",IF(OR(O18>0,COUNTIFS(Backlog!$K$6:$K$1327,A18,Backlog!$O$6:$O$1327,"En cours")>0),"En cours","À faire")) -> À faire
... A22: API-WALL|3 | B22: API | C22: API-WALL | D22: Wallpapers IA | E22: 3 | F22: =COUNTIFS(Backlog!$K$6:$K$1327,A22) -> 31 | G22: =SUMIFS(Backlog!$I$6:$I$1327,Backlog!$K$6:$K$1327,A22) -> 22.75 | H22: =IF(B22="API",Paramètres!$B$7,IF(B22="Mobile",Paramètres!$B$8,Paramètres!$B$9)) -> 3 | I22: =MAX(1,ROUNDUP(G22*(1+Paramètres!$B$6)/(H22*Paramètres!$B$5),0)) -> 11 | J22: =Paramètres!$B$4 -> 46328 | K22: =ROUNDUP(I22/5,0) -> 3 | L22: =MAX(J22,WORKDAY(M21,1)) -> 46653 | M22: =WORKDAY(L22,I22-1) -> 46667 | N22: =COUNTIFS(Backlog!$K$6:$K$1327,A22,Backlog!$O$6:$O$1327,"Terminé") -> 0 | O22: =IF(F22=0,0,N22/F22) -> 0 | P22: =IF(O22=1,"Terminé",IF(OR(O22>0,COUNTIFS(Backlog!$K$6:$K$1327,A22,Backlog!$O$6:$O$1327,"En cours")>0),"En cours","À faire")) -> À faire
A23: MOB-FND|0 | B23: Mobile | C23: MOB-FND | D23: Socle technique Flutter | E23: 0 | F23: =COUNTIFS(Backlog!$K$6:$K$1327,A23) -> 47 | G23: =SUMIFS(Backlog!$I$6:$I$1327,Backlog!$K$6:$K$1327,A23) -> 50.25 | H23: =IF(B23="API",Paramètres!$B$7,IF(B23="Mobile",Paramètres!$B$8,Paramètres!$B$9)) -> 3 | I23: =MAX(1,ROUNDUP(G23*(1+Paramètres!$B$6)/(H23*Paramètres!$B$5),0)) -> 25 | J23: =Paramètres!$B$4 -> 46328 | K23: =ROUNDUP(I23/5,0) -> 5 | L23: =J23 -> 46328 | M23: =WORKDAY(L23,I23-1) -> 46360 | N23: =COUNTIFS(Backlog!$K$6:$K$1327,A23,Backlog!$O$6:$O$1327,"Terminé") -> 0 | O23: =IF(F23=0,0,N23/F23) -> 0 | P23: =IF(O23=1,"Terminé",IF(OR(O23>0,COUNTIFS(Backlog!$K$6:$K$1327,A23,Backlog!$O$6:$O$1327,"En cours")>0),"En cours","À faire")) -> À faire
A24: MOB-ZA|0 | B24: Mobile | C24: MOB-ZA | D24: Fondations | E24: 0 | F24: =COUNTIFS(Backlog!$K$6:$K$1327,A24) -> 16 | G24: =SUMIFS(Backlog!$I$6:$I$1327,Backlog!$K$6:$K$1327,A24) -> 14.5 | H24: =IF(B24="API",Paramètres!$B$7,IF(B24="Mobile",Paramètres!$B$8,Paramètres!$B$9)) -> 3 | I24: =MAX(1,ROUNDUP(G24*(1+Paramètres!$B$6)/(H24*Paramètres!$B$5),0)) -> 7 | J24: =Paramètres!$B$4 -> 46328 | K24: =ROUNDUP(I24/5,0) -> 2 | L24: =MAX(J24,WORKDAY(M23,1)) -> 46363 | M24: =WORKDAY(L24,I24-1) -> 46371 | N24: =COUNTIFS(Backlog!$K$6:$K$1327,A24,Backlog!$O$6:$O$1327,"Terminé") -> 0 | O24: =IF(F24=0,0,N24/F24) -> 0 | P24: =IF(O24=1,"Terminé",IF(OR(O24>0,COUNTIFS(Backlog!$K$6:$K$1327,A24,Backlog!$O$6:$O$1327,"En cours")>0),"En cours","À faire")) -> À faire
A25: MOB-ZB|0 | B25: Mobile | C25: MOB-ZB | D25: Composants de base | E25: 0 | F25: =COUNTIFS(Backlog!$K$6:$K$1327,A25) -> 18 | G25: =SUMIFS(Backlog!$I$6:$I$1327,Backlog!$K$6:$K$1327,A25) -> 21 | H25: =IF(B25="API",Paramètres!$B$7,IF(B25="Mobile",Paramètres!$B$8,Paramètres!$B$9)) -> 3 | I25: =MAX(1,ROUNDUP(G25*(1+Paramètres!$B$6)/(H25*Paramètres!$B$5),0)) -> 11 | J25: =Paramètres!$B$4 -> 46328 | K25: =ROUNDUP(I25/5,0) -> 3 | L25: =MAX(J25,WORKDAY(M24,1)) -> 46372 | M25: =WORKDAY(L25,I25-1) -> 46386 | N25: =COUNTIFS(Backlog!$K$6:$K$1327,A25,Backlog!$O$6:$O$1327,"Terminé") -> 0 | O25: =IF(F25=0,0,N25/F25) -> 0 | P25: =IF(O25=1,"Terminé",IF(OR(O25>0,COUNTIFS(Backlog!$K$6:$K$1327,A25,Backlog!$O$6:$O$1327,"En cours")>0),"En cours","À faire")) -> À faire
A26: MOB-ZC|0 | B26: Mobile | C26: MOB-ZC | D26: Retours et états | E26: 0 | F26: =COUNTIFS(Backlog!$K$6:$K$1327,A26) -> 17 | G26: =SUMIFS(Backlog!$I$6:$I$1327,Backlog!$K$6:$K$1327,A26) -> 18 | H26: =IF(B26="API",Paramètres!$B$7,IF(B26="Mobile",Paramètres!$B$8,Paramètres!$B$9)) -> 3 | I26: =MAX(1,ROUNDUP(G26*(1+Paramètres!$B$6)/(H26*Paramètres!$B$5),0)) -> 9 | J26: =Paramètres!$B$4 -> 46328 | K26: =ROUNDUP(I26/5,0) -> 2 | L26: =MAX(J26,WORKDAY(M25,1)) -> 46387 | M26: =WORKDAY(L26,I26-1) -> 46399 | N26: =COUNTIFS(Backlog!$K$6:$K$1327,A26,Backlog!$O$6:$O$1327,"Terminé") -> 0 | O26: =IF(F26=0,0,N26/F26) -> 0 | P26: =IF(O26=1,"Terminé",IF(OR(O26>0,COUNTIFS(Backlog!$K$6:$K$1327,A26,Backlog!$O$6:$O$1327,"En cours")>0),"En cours","À faire")) -> À faire
A27: MOB-ZD|0 | B27: Mobile | C27: MOB-ZD | D27: Composants métier et responsive | E27: 0 | F27: =COUNTIFS(Backlog!$K$6:$K$1327,A27) -> 14 | G27: =SUMIFS(Backlog!$I$6:$I$1327,Backlog!$K$6:$K$1327,A27) -> 16.5 | H27: =IF(B27="API",Paramètres!$B$7,IF(B27="Mobile",Paramètres!$B$8,Paramètres!$B$9)) -> 3 | I27: =MAX(1,ROUNDUP(G27*(1+Paramètres!$B$6)/(H27*Paramètres!$B$5),0)) -> 8 | J27: =Paramètres!$B$4 -> 46328 | K27: =ROUNDUP(I27/5,0) -> 2 | L27: =MAX(J27,WORKDAY(M26,1)) -> 46400 | M27: =WORKDAY(L27,I27-1) -> 46409 | N27: =COUNTIFS(Backlog!$K$6:$K$1327,A27,Backlog!$O$6:$O$1327,"Terminé") -> 0 | O27: =IF(F27=0,0,N27/F27) -> 0 | P27: =IF(O27=1,"Terminé",IF(OR(O27>0,COUNTIFS(Backlog!$K$6:$K$1327,A27,Backlog!$O$6:$O$1327,"En cours")>0),"En cours","À faire")) -> À faire
A28: MOB-ZE|0 | B28: Mobile | C28: MOB-ZE | D28: Animations et micro-interactions | E28: 0 | F28: =COUNTIFS(Backlog!$K$6:$K$1327,A28) -> 18 | G28: =SUMIFS(Backlog!$I$6:$I$1327,Backlog!$K$6:$K$1327,A28) -> 19.5 | H28: =IF(B28="API",Paramètres!$B$7,IF(B28="Mobile",Paramètres!$B$8,Paramètres!$B$9)) -> 3 | I28: =MAX(1,ROUNDUP(G28*(1+Paramètres!$B$6)/(H28*Paramètres!$B$5),0)) -> 10 | J28: =Paramètres!$B$4 -> 46328 | K28: =ROUNDUP(I28/5,0) -> 2 | L28: =MAX(J28,WORKDAY(M27,1)) -> 46412 | M28: =WORKDAY(L28,I28-1) -> 46423 | N28: =COUNTIFS(Backlog!$K$6:$K$1327,A28,Backlog!$O$6:$O$1327,"Terminé") -> 0 | O28: =IF(F28=0,0,N28/F28) -> 0 | P28: =IF(O28=1,"Terminé",IF(OR(O28>0,COUNTIFS(Backlog!$K$6:$K$1327,A28,Backlog!$O$6:$O$1327,"En cours")>0),"En cours","À faire")) -> À faire
A29: MOB-A|0 | B29: Mobile | C29: MOB-A | D29: Lancement et système | E29: 0 | F29: =COUNTIFS(Backlog!$K$6:$K$1327,A29) -> 19 | G29: =SUMIFS(Backlog!$I$6:$I$1327,Backlog!$K$6:$K$1327,A29) -> 16 | H29: =IF(B29="API",Paramètres!$B$7,IF(B29="Mobile",Paramètres!$B$8,Paramètres!$B$9)) -> 3 | I29: =MAX(1,ROUNDUP(G29*(1+Paramètres!$B$6)/(H29*Paramètres!$B$5),0)) -> 8 | J29: =Paramètres!$B$4 -> 46328 | K29: =ROUNDUP(I29/5,0) -> 2 | L29: =MAX(J29,WORKDAY(M28,1)) -> 46426 | M29: =WORKDAY(L29,I29-1) -> 46435 | N29: =COUNTIFS(Backlog!$K$6:$K$1327,A29,Backlog!$O$6:$O$1327,"Terminé") -> 0 | O29: =IF(F29=0,0,N29/F29) -> 0 | P29: =IF(O29=1,"Terminé",IF(OR(O29>0,COUNTIFS(Backlog!$K$6:$K$1327,A29,Backlog!$O$6:$O$1327,"En cours")>0),"En cours","À faire")) -> À faire
A30: MOB-B|1 | B30: Mobile | C30: MOB-B | D30: Onboarding et authentification | E30: 1 | F30: =COUNTIFS(Backlog!$K$6:$K$1327,A30) -> 29 | G30: =SUMIFS(Backlog!$I$6:$I$1327,Backlog!$K$6:$K$1327,A30) -> 27.75 | H30: =IF(B30="API",Paramètres!$B$7,IF(B30="Mobile",Paramètres!$B$8,Paramètres!$B$9)) -> 3 | I30: =MAX(1,ROUNDUP(G30*(1+Paramètres!$B$6)/(H30*Paramètres!$B$5),0)) -> 14 | J30: =WORKDAY(_xlfn.MINIFS($L$6:$L$22,$E$6:$E$22,E30),Paramètres!$B$10) -> 46363 | K30: =ROUNDUP(I30/5,0) -> 3 | L30: =MAX(J30,WORKDAY(M29,1)) -> 46436 | M30: =WORKDAY(L30,I30-1) -> 46455 | N30: =COUNTIFS(Backlog!$K$6:$K$1327,A30,Backlog!$O$6:$O$1327,"Terminé") -> 0 | O30: =IF(F30=0,0,N30/F30) -> 0 | P30: =IF(O30=1,"Terminé",IF(OR(O30>0,COUNTIFS(Backlog!$K$6:$K$1327,A30,Backlog!$O$6:$O$1327,"En cours")>0),"En cours","À faire")) -> À faire
A31: MOB-Q|1 | B31: Mobile | C31: MOB-Q | D31: Paramètres et compte | E31: 1 | F31: =COUNTIFS(Backlog!$K$6:$K$1327,A31) -> 31 | G31: =SUMIFS(Backlog!$I$6:$I$1327,Backlog!$K$6:$K$1327,A31) -> 26.5 | H31: =IF(B31="API",Paramètres!$B$7,IF(B31="Mobile",Paramètres!$B$8,Paramètres!$B$9)) -> 3 | I31: =MAX(1,ROUNDUP(G31*(1+Paramètres!$B$6)/(H31*Paramètres!$B$5),0)) -> 13 | J31: =WORKDAY(_xlfn.MINIFS($L$6:$L$22,$E$6:$E$22,E31),Paramètres!$B$10) -> 46363 | K31: =ROUNDUP(I31/5,0) -> 3 | L31: =MAX(J31,WORKDAY(M30,1)) -> 46456 | M31: =WORKDAY(L31,I31-1) -> 46472 | N31: =COUNTIFS(Backlog!$K$6:$K$1327,A31,Backlog!$O$6:$O$1327,"Terminé") -> 0 | O31: =IF(F31=0,0,N31/F31) -> 0 | P31: =IF(O31=1,"Terminé",IF(OR(O31>0,COUNTIFS(Backlog!$K$6:$K$1327,A31,Backlog!$O$6:$O$1327,"En cours")>0),"En cours","À faire")) -> À faire
A32: MOB-C|1 | B32: Mobile | C32: MOB-C | D32: Accueil — dashboard | E32: 1 | F32: =COUNTIFS(Backlog!$K$6:$K$1327,A32) -> 27 | G32: =SUMIFS(Backlog!$I$6:$I$1327,Backlog!$K$6:$K$1327,A32) -> 24.5 | H32: =IF(B32="API",Paramètres!$B$7,IF(B32="Mobile",Paramètres!$B$8,Paramètres!$B$9)) -> 3 | I32: =MAX(1,ROUNDUP(G32*(1+Paramètres!$B$6)/(H32*Paramètres!$B$5),0)) -> 12 | J32: =WORKDAY(_xlfn.MINIFS($L$6:$L$22,$E$6:$E$22,E32),Paramètres!$B$10) -> 46363 | K32: =ROUNDUP(I32/5,0) -> 3 | L32: =MAX(J32,WORKDAY(M31,1)) -> 46475 | M32: =WORKDAY(L32,I32-1) -> 46490 | N32: =COUNTIFS(Backlog!$K$6:$K$1327,A32,Backlog!$O$6:$O$1327,"Terminé") -> 0 | O32: =IF(F32=0,0,N32/F32) -> 0 | P32: =IF(O32=1,"Terminé",IF(OR(O32>0,COUNTIFS(Backlog!$K$6:$K$1327,A32,Backlog!$O$6:$O$1327,"En cours")>0),"En cours","À faire")) -> À faire
A33: MOB-F|1 | B33: Mobile | C33: MOB-F | D33: Historique et fiches | E33: 1 | F33: =COUNTIFS(Backlog!$K$6:$K$1327,A33) -> 27 | G33: =SUMIFS(Backlog!$I$6:$I$1327,Backlog!$K$6:$K$1327,A33) -> 27.5 | H33: =IF(B33="API",Paramètres!$B$7,IF(B33="Mobile",Paramètres!$B$8,Paramètres!$B$9)) -> 3 | I33: =MAX(1,ROUNDUP(G33*(1+Paramètres!$B$6)/(H33*Paramètres!$B$5),0)) -> 14 | J33: =WORKDAY(_xlfn.MINIFS($L$6:$L$22,$E$6:$E$22,E33),Paramètres!$B$10) -> 46363 | K33: =ROUNDUP(I33/5,0) -> 3 | L33: =MAX(J33,WORKDAY(M32,1)) -> 46491 | M33: =WORKDAY(L33,I33-1) -> 46510 | N33: =COUNTIFS(Backlog!$K$6:$K$1327,A33,Backlog!$O$6:$O$1327,"Terminé") -> 0 | O33: =IF(F33=0,0,N33/F33) -> 0 | P33: =IF(O33=1,"Terminé",IF(OR(O33>0,COUNTIFS(Backlog!$K$6:$K$1327,A33,Backlog!$O$6:$O$1327,"En cours")>0),"En cours","À faire")) -> À faire
A34: MOB-L|1 | B34: Mobile | C34: MOB-L | D34: Calendrier et export agenda | E34: 1 | F34: =COUNTIFS(Backlog!$K$6:$K$1327,A34) -> 29 | G34: =SUMIFS(Backlog!$I$6:$I$1327,Backlog!$K$6:$K$1327,A34) -> 34 | H34: =IF(B34="API",Paramètres!$B$7,IF(B34="Mobile",Paramètres!$B$8,Paramètres!$B$9)) -> 3 | I34: =MAX(1,ROUNDUP(G34*(1+Paramètres!$B$6)/(H34*Paramètres!$B$5),0)) -> 17 | J34: =WORKDAY(_xlfn.MINIFS($L$6:$L$22,$E$6:$E$22,E34),Paramètres!$B$10) -> 46363 | K34: =ROUNDUP(I34/5,0) -> 4 | L34: =MAX(J34,WORKDAY(M33,1)) -> 46511 | M34: =WORKDAY(L34,I34-1) -> 46533 | N34: =COUNTIFS(Backlog!$K$6:$K$1327,A34,Backlog!$O$6:$O$1327,"Terminé") -> 0 | O34: =IF(F34=0,0,N34/F34) -> 0 | P34: =IF(O34=1,"Terminé",IF(OR(O34>0,COUNTIFS(Backlog!$K$6:$K$1327,A34,Backlog!$O$6:$O$1327,"En cours")>0),"En cours","À faire")) -> À faire
A35: MOB-D|1 | B35: Mobile | C35: MOB-D | D35: Jeux — Guess the Player | E35: 1 | F35: =COUNTIFS(Backlog!$K$6:$K$1327,A35) -> 30 | G35: =SUMIFS(Backlog!$I$6:$I$1327,Backlog!$K$6:$K$1327,A35) -> 25.75 | H35: =IF(B35="API",Paramètres!$B$7,IF(B35="Mobile",Paramètres!$B$8,Paramètres!$B$9)) -> 3 | I35: =MAX(1,ROUNDUP(G35*(1+Paramètres!$B$6)/(H35*Paramètres!$B$5),0)) -> 13 | J35: =WORKDAY(_xlfn.MINIFS($L$6:$L$22,$E$6:$E$22,E35),Paramètres!$B$10) -> 46363 | K35: =ROUNDUP(I35/5,0) -> 3 | L35: =MAX(J35,WORKDAY(M34,1)) -> 46534 | M35: =WORKDAY(L35,I35-1) -> 46552 | N35: =COUNTIFS(Backlog!$K$6:$K$1327,A35,Backlog!$O$6:$O$1327,"Terminé") -> 0 | O35: =IF(F35=0,0,N35/F35) -> 0 | P35: =IF(O35=1,"Terminé",IF(OR(O35>0,COUNTIFS(Backlog!$K$6:$K$1327,A35,Backlog!$O$6:$O$1327,"En cours")>0),"En cours","À faire")) -> À faire
A36: MOB-E|1 | B36: Mobile | C36: MOB-E | D36: Quiz adaptatif | E36: 1 | F36: =COUNTIFS(Backlog!$K$6:$K$1327,A36) -> 34 | G36: =SUMIFS(Backlog!$I$6:$I$1327,Backlog!$K$6:$K$1327,A36) -> 29.25 | H36: =IF(B36="API",Paramètres!$B$7,IF(B36="Mobile",Paramètres!$B$8,Paramètres!$B$9)) -> 3 | I36: =MAX(1,ROUNDUP(G36*(1+Paramètres!$B$6)/(H36*Paramètres!$B$5),0)) -> 15 | J36: =WORKDAY(_xlfn.MINIFS($L$6:$L$22,$E$6:$E$22,E36),Paramètres!$B$10) -> 46363 | K36: =ROUNDUP(I36/5,0) -> 3 | L36: =MAX(J36,WORKDAY(M35,1)) -> 46553 | M36: =WORKDAY(L36,I36-1) -> 46573 | N36: =COUNTIFS(Backlog!$K$6:$K$1327,A36,Backlog!$O$6:$O$1327,"Terminé") -> 0 | O36: =IF(F36=0,0,N36/F36) -> 0 | P36: =IF(O36=1,"Terminé",IF(OR(O36>0,COUNTIFS(Backlog!$K$6:$K$1327,A36,Backlog!$O$6:$O$1327,"En cours")>0),"En cours","À faire")) -> À faire
A37: MOB-N|1 | B37: Mobile | C37: MOB-N | D37: Assistant IA Barça AI | E37: 1 | F37: =COUNTIFS(Backlog!$K$6:$K$1327,A37) -> 31 | G37: =SUMIFS(Backlog!$I$6:$I$1327,Backlog!$K$6:$K$1327,A37) -> 35.5 | H37: =IF(B37="API",Paramètres!$B$7,IF(B37="Mobile",Paramètres!$B$8,Paramètres!$B$9)) -> 3 | I37: =MAX(1,ROUNDUP(G37*(1+Paramètres!$B$6)/(H37*Paramètres!$B$5),0)) -> 18 | J37: =WORKDAY(_xlfn.MINIFS($L$6:$L$22,$E$6:$E$22,E37),Paramètres!$B$10) -> 46363 | K37: =ROUNDUP(I37/5,0) -> 4 | L37: =MAX(J37,WORKDAY(M36,1)) -> 46574 | M37: =WORKDAY(L37,I37-1) -> 46597 | N37: =COUNTIFS(Backlog!$K$6:$K$1327,A37,Backlog!$O$6:$O$1327,"Terminé") -> 0 | O37: =IF(F37=0,0,N37/F37) -> 0 | P37: =IF(O37=1,"Terminé",IF(OR(O37>0,COUNTIFS(Backlog!$K$6:$K$1327,A37,Backlog!$O$6:$O$1327,"En cours")>0),"En cours","À faire")) -> À faire
A38: MOB-O|1 | B38: Mobile | C38: MOB-O | D38: Notifications | E38: 1 | F38: =COUNTIFS(Backlog!$K$6:$K$1327,A38) -> 28 | G38: =SUMIFS(Backlog!$I$6:$I$1327,Backlog!$K$6:$K$1327,A38) -> 24.75 | H38: =IF(B38="API",Paramètres!$B$7,IF(B38="Mobile",Paramètres!$B$8,Paramètres!$B$9)) -> 3 | I38: =MAX(1,ROUNDUP(G38*(1+Paramètres!$B$6)/(H38*Paramètres!$B$5),0)) -> 12 | J38: =WORKDAY(_xlfn.MINIFS($L$6:$L$22,$E$6:$E$22,E38),Paramètres!$B$10) -> 46363 | K38: =ROUNDUP(I38/5,0) -> 3 | L38: =MAX(J38,WORKDAY(M37,1)) -> 46598 | M38: =WORKDAY(L38,I38-1) -> 46615 | N38: =COUNTIFS(Backlog!$K$6:$K$1327,A38,Backlog!$O$6:$O$1327,"Terminé") -> 0 | O38: =IF(F38=0,0,N38/F38) -> 0 | P38: =IF(O38=1,"Terminé",IF(OR(O38>0,COUNTIFS(Backlog!$K$6:$K$1327,A38,Backlog!$O$6:$O$1327,"En cours")>0),"En cours","À faire")) -> À faire
A39: MOB-G|2 | B39: Mobile | C39: MOB-G | D39: Comparateur GOAT | E39: 2 | F39: =COUNTIFS(Backlog!$K$6:$K$1327,A39) -> 17 | G39: =SUMIFS(Backlog!$I$6:$I$1327,Backlog!$K$6:$K$1327,A39) -> 18 | H39: =IF(B39="API",Paramètres!$B$7,IF(B39="Mobile",Paramètres!$B$8,Paramètres!$B$9)) -> 3 | I39: =MAX(1,ROUNDUP(G39*(1+Paramètres!$B$6)/(H39*Paramètres!$B$5),0)) -> 9 | J39: =WORKDAY(_xlfn.MINIFS($L$6:$L$22,$E$6:$E$22,E39),Paramètres!$B$10) -> 46555 | K39: =ROUNDUP(I39/5,0) -> 2 | L39: =MAX(J39,WORKDAY(M38,1)) -> 46616 | M39: =WORKDAY(L39,I39-1) -> 46626 | N39: =COUNTIFS(Backlog!$K$6:$K$1327,A39,Backlog!$O$6:$O$1327,"Terminé") -> 0 | O39: =IF(F39=0,0,N39/F39) -> 0 | P39: =IF(O39=1,"Terminé",IF(OR(O39>0,COUNTIFS(Backlog!$K$6:$K$1327,A39,Backlog!$O$6:$O$1327,"En cours")>0),"En cours","À faire")) -> À faire
A40: MOB-H|2 | B40: Mobile | C40: MOB-H | D40: Fantasy Barça | E40: 2 | F40: =COUNTIFS(Backlog!$K$6:$K$1327,A40) -> 35 | G40: =SUMIFS(Backlog!$I$6:$I$1327,Backlog!$K$6:$K$1327,A40) -> 38 | H40: =IF(B40="API",Paramètres!$B$7,IF(B40="Mobile",Paramètres!$B$8,Paramètres!$B$9)) -> 3 | I40: =MAX(1,ROUNDUP(G40*(1+Paramètres!$B$6)/(H40*Paramètres!$B$5),0)) -> 19 | J40: =WORKDAY(_xlfn.MINIFS($L$6:$L$22,$E$6:$E$22,E40),Paramètres!$B$10) -> 46555 | K40: =ROUNDUP(I40/5,0) -> 4 | L40: =MAX(J40,WORKDAY(M39,1)) -> 46629 | M40: =WORKDAY(L40,I40-1) -> 46653 | N40: =COUNTIFS(Backlog!$K$6:$K$1327,A40,Backlog!$O$6:$O$1327,"Terminé") -> 0 | O40: =IF(F40=0,0,N40/F40) -> 0 | P40: =IF(O40=1,"Terminé",IF(OR(O40>0,COUNTIFS(Backlog!$K$6:$K$1327,A40,Backlog!$O$6:$O$1327,"En cours")>0),"En cours","À faire")) -> À faire
A41: MOB-J|2 | B41: Mobile | C41: MOB-J | D41: Carte communautaire | E41: 2 | F41: =COUNTIFS(Backlog!$K$6:$K$1327,A41) -> 27 | G41: =SUMIFS(Backlog!$I$6:$I$1327,Backlog!$K$6:$K$1327,A41) -> 27.5 | H41: =IF(B41="API",Paramètres!$B$7,IF(B41="Mobile",Paramètres!$B$8,Paramètres!$B$9)) -> 3 | I41: =MAX(1,ROUNDUP(G41*(1+Paramètres!$B$6)/(H41*Paramètres!$B$5),0)) -> 14 | J41: =WORKDAY(_xlfn.MINIFS($L$6:$L$22,$E$6:$E$22,E41),Paramètres!$B$10) -> 46555 | K41: =ROUNDUP(I41/5,0) -> 3 | L41: =MAX(J41,WORKDAY(M40,1)) -> 46654 | M41: =WORKDAY(L41,I41-1) -> 46673 | N41: =COUNTIFS(Backlog!$K$6:$K$1327,A41,Backlog!$O$6:$O$1327,"Terminé") -> 0 | O41: =IF(F41=0,0,N41/F41) -> 0 | P41: =IF(O41=1,"Terminé",IF(OR(O41>0,COUNTIFS(Backlog!$K$6:$K$1327,A41,Backlog!$O$6:$O$1327,"En cours")>0),"En cours","À faire")) -> À faire
... A45: MOB-M|3 | B45: Mobile | C45: MOB-M | D45: Wallpapers IA | E45: 3 | F45: =COUNTIFS(Backlog!$K$6:$K$1327,A45) -> 31 | G45: =SUMIFS(Backlog!$I$6:$I$1327,Backlog!$K$6:$K$1327,A45) -> 29.5 | H45: =IF(B45="API",Paramètres!$B$7,IF(B45="Mobile",Paramètres!$B$8,Paramètres!$B$9)) -> 3 | I45: =MAX(1,ROUNDUP(G45*(1+Paramètres!$B$6)/(H45*Paramètres!$B$5),0)) -> 15 | J45: =WORKDAY(_xlfn.MINIFS($L$6:$L$22,$E$6:$E$22,E45),Paramètres!$B$10) -> 46673 | K45: =ROUNDUP(I45/5,0) -> 3 | L45: =MAX(J45,WORKDAY(M44,1)) -> 46728 | M45: =WORKDAY(L45,I45-1) -> 46748 | N45: =COUNTIFS(Backlog!$K$6:$K$1327,A45,Backlog!$O$6:$O$1327,"Terminé") -> 0 | O45: =IF(F45=0,0,N45/F45) -> 0 | P45: =IF(O45=1,"Terminé",IF(OR(O45>0,COUNTIFS(Backlog!$K$6:$K$1327,A45,Backlog!$O$6:$O$1327,"En cours")>0),"En cours","À faire")) -> À faire
A46: ADM-FND|0 | B46: Admin | C46: ADM-FND | D46: Socle technique admin | E46: 0 | F46: =COUNTIFS(Backlog!$K$6:$K$1327,A46) -> 25 | G46: =SUMIFS(Backlog!$I$6:$I$1327,Backlog!$K$6:$K$1327,A46) -> 27.5 | H46: =IF(B46="API",Paramètres!$B$7,IF(B46="Mobile",Paramètres!$B$8,Paramètres!$B$9)) -> 2 | I46: =MAX(1,ROUNDUP(G46*(1+Paramètres!$B$6)/(H46*Paramètres!$B$5),0)) -> 20 | J46: =Paramètres!$B$4 -> 46328 | K46: =ROUNDUP(I46/5,0) -> 4 | L46: =J46 -> 46328 | M46: =WORKDAY(L46,I46-1) -> 46353 | N46: =COUNTIFS(Backlog!$K$6:$K$1327,A46,Backlog!$O$6:$O$1327,"Terminé") -> 0 | O46: =IF(F46=0,0,N46/F46) -> 0 | P46: =IF(O46=1,"Terminé",IF(OR(O46>0,COUNTIFS(Backlog!$K$6:$K$1327,A46,Backlog!$O$6:$O$1327,"En cours")>0),"En cours","À faire")) -> À faire
A47: ADM-ADS|0 | B47: Admin | C47: ADM-ADS | D47: Design system admin | E47: 0 | F47: =COUNTIFS(Backlog!$K$6:$K$1327,A47) -> 37 | G47: =SUMIFS(Backlog!$I$6:$I$1327,Backlog!$K$6:$K$1327,A47) -> 32.5 | H47: =IF(B47="API",Paramètres!$B$7,IF(B47="Mobile",Paramètres!$B$8,Paramètres!$B$9)) -> 2 | I47: =MAX(1,ROUNDUP(G47*(1+Paramètres!$B$6)/(H47*Paramètres!$B$5),0)) -> 24 | J47: =Paramètres!$B$4 -> 46328 | K47: =ROUNDUP(I47/5,0) -> 5 | L47: =MAX(J47,WORKDAY(M46,1)) -> 46356 | M47: =WORKDAY(L47,I47-1) -> 46387 | N47: =COUNTIFS(Backlog!$K$6:$K$1327,A47,Backlog!$O$6:$O$1327,"Terminé") -> 0 | O47: =IF(F47=0,0,N47/F47) -> 0 | P47: =IF(O47=1,"Terminé",IF(OR(O47>0,COUNTIFS(Backlog!$K$6:$K$1327,A47,Backlog!$O$6:$O$1327,"En cours")>0),"En cours","À faire")) -> À faire
A48: ADM-WA|1 | B48: Admin | C48: ADM-WA | D48: Authentification et erreurs | E48: 1 | F48: =COUNTIFS(Backlog!$K$6:$K$1327,A48) -> 19 | G48: =SUMIFS(Backlog!$I$6:$I$1327,Backlog!$K$6:$K$1327,A48) -> 18 | H48: =IF(B48="API",Paramètres!$B$7,IF(B48="Mobile",Paramètres!$B$8,Paramètres!$B$9)) -> 2 | I48: =MAX(1,ROUNDUP(G48*(1+Paramètres!$B$6)/(H48*Paramètres!$B$5),0)) -> 13 | J48: =WORKDAY(_xlfn.MINIFS($L$6:$L$22,$E$6:$E$22,E48),Paramètres!$B$10) -> 46363 | K48: =ROUNDUP(I48/5,0) -> 3 | L48: =MAX(J48,WORKDAY(M47,1)) -> 46388 | M48: =WORKDAY(L48,I48-1) -> 46406 | N48: =COUNTIFS(Backlog!$K$6:$K$1327,A48,Backlog!$O$6:$O$1327,"Terminé") -> 0 | O48: =IF(F48=0,0,N48/F48) -> 0 | P48: =IF(O48=1,"Terminé",IF(OR(O48>0,COUNTIFS(Backlog!$K$6:$K$1327,A48,Backlog!$O$6:$O$1327,"En cours")>0),"En cours","À faire")) -> À faire
A49: ADM-WB|1 | B49: Admin | C49: ADM-WB | D49: Tableau de bord et recherche | E49: 1 | F49: =COUNTIFS(Backlog!$K$6:$K$1327,A49) -> 16 | G49: =SUMIFS(Backlog!$I$6:$I$1327,Backlog!$K$6:$K$1327,A49) -> 17.5 | H49: =IF(B49="API",Paramètres!$B$7,IF(B49="Mobile",Paramètres!$B$8,Paramètres!$B$9)) -> 2 | I49: =MAX(1,ROUNDUP(G49*(1+Paramètres!$B$6)/(H49*Paramètres!$B$5),0)) -> 13 | J49: =WORKDAY(_xlfn.MINIFS($L$6:$L$22,$E$6:$E$22,E49),Paramètres!$B$10) -> 46363 | K49: =ROUNDUP(I49/5,0) -> 3 | L49: =MAX(J49,WORKDAY(M48,1)) -> 46407 | M49: =WORKDAY(L49,I49-1) -> 46423 | N49: =COUNTIFS(Backlog!$K$6:$K$1327,A49,Backlog!$O$6:$O$1327,"Terminé") -> 0 | O49: =IF(F49=0,0,N49/F49) -> 0 | P49: =IF(O49=1,"Terminé",IF(OR(O49>0,COUNTIFS(Backlog!$K$6:$K$1327,A49,Backlog!$O$6:$O$1327,"En cours")>0),"En cours","À faire")) -> À faire
A50: ADM-WC|1 | B50: Admin | C50: ADM-WC | D50: Gestion des joueurs | E50: 1 | F50: =COUNTIFS(Backlog!$K$6:$K$1327,A50) -> 28 | G50: =SUMIFS(Backlog!$I$6:$I$1327,Backlog!$K$6:$K$1327,A50) -> 30.5 | H50: =IF(B50="API",Paramètres!$B$7,IF(B50="Mobile",Paramètres!$B$8,Paramètres!$B$9)) -> 2 | I50: =MAX(1,ROUNDUP(G50*(1+Paramètres!$B$6)/(H50*Paramètres!$B$5),0)) -> 22 | J50: =WORKDAY(_xlfn.MINIFS($L$6:$L$22,$E$6:$E$22,E50),Paramètres!$B$10) -> 46363 | K50: =ROUNDUP(I50/5,0) -> 5 | L50: =MAX(J50,WORKDAY(M49,1)) -> 46426 | M50: =WORKDAY(L50,I50-1) -> 46455 | N50: =COUNTIFS(Backlog!$K$6:$K$1327,A50,Backlog!$O$6:$O$1327,"Terminé") -> 0 | O50: =IF(F50=0,0,N50/F50) -> 0 | P50: =IF(O50=1,"Terminé",IF(OR(O50>0,COUNTIFS(Backlog!$K$6:$K$1327,A50,Backlog!$O$6:$O$1327,"En cours")>0),"En cours","À faire")) -> À faire
A51: ADM-WD|1 | B51: Admin | C51: ADM-WD | D51: Matchs et compétitions | E51: 1 | F51: =COUNTIFS(Backlog!$K$6:$K$1327,A51) -> 14 | G51: =SUMIFS(Backlog!$I$6:$I$1327,Backlog!$K$6:$K$1327,A51) -> 20.5 | H51: =IF(B51="API",Paramètres!$B$7,IF(B51="Mobile",Paramètres!$B$8,Paramètres!$B$9)) -> 2 | I51: =MAX(1,ROUNDUP(G51*(1+Paramètres!$B$6)/(H51*Paramètres!$B$5),0)) -> 15 | J51: =WORKDAY(_xlfn.MINIFS($L$6:$L$22,$E$6:$E$22,E51),Paramètres!$B$10) -> 46363 | K51: =ROUNDUP(I51/5,0) -> 3 | L51: =MAX(J51,WORKDAY(M50,1)) -> 46456 | M51: =WORKDAY(L51,I51-1) -> 46476 | N51: =COUNTIFS(Backlog!$K$6:$K$1327,A51,Backlog!$O$6:$O$1327,"Terminé") -> 0 | O51: =IF(F51=0,0,N51/F51) -> 0 | P51: =IF(O51=1,"Terminé",IF(OR(O51>0,COUNTIFS(Backlog!$K$6:$K$1327,A51,Backlog!$O$6:$O$1327,"En cours")>0),"En cours","À faire")) -> À faire
A52: ADM-WE|1 | B52: Admin | C52: ADM-WE | D52: Contenu éditorial | E52: 1 | F52: =COUNTIFS(Backlog!$K$6:$K$1327,A52) -> 14 | G52: =SUMIFS(Backlog!$I$6:$I$1327,Backlog!$K$6:$K$1327,A52) -> 19.5 | H52: =IF(B52="API",Paramètres!$B$7,IF(B52="Mobile",Paramètres!$B$8,Paramètres!$B$9)) -> 2 | I52: =MAX(1,ROUNDUP(G52*(1+Paramètres!$B$6)/(H52*Paramètres!$B$5),0)) -> 15 | J52: =WORKDAY(_xlfn.MINIFS($L$6:$L$22,$E$6:$E$22,E52),Paramètres!$B$10) -> 46363 | K52: =ROUNDUP(I52/5,0) -> 3 | L52: =MAX(J52,WORKDAY(M51,1)) -> 46477 | M52: =WORKDAY(L52,I52-1) -> 46497 | N52: =COUNTIFS(Backlog!$K$6:$K$1327,A52,Backlog!$O$6:$O$1327,"Terminé") -> 0 | O52: =IF(F52=0,0,N52/F52) -> 0 | P52: =IF(O52=1,"Terminé",IF(OR(O52>0,COUNTIFS(Backlog!$K$6:$K$1327,A52,Backlog!$O$6:$O$1327,"En cours")>0),"En cours","À faire")) -> À faire
A53: ADM-WF|1 | B53: Admin | C53: ADM-WF | D53: Questions de quiz | E53: 1 | F53: =COUNTIFS(Backlog!$K$6:$K$1327,A53) -> 23 | G53: =SUMIFS(Backlog!$I$6:$I$1327,Backlog!$K$6:$K$1327,A53) -> 24 | H53: =IF(B53="API",Paramètres!$B$7,IF(B53="Mobile",Paramètres!$B$8,Paramètres!$B$9)) -> 2 | I53: =MAX(1,ROUNDUP(G53*(1+Paramètres!$B$6)/(H53*Paramètres!$B$5),0)) -> 18 | J53: =WORKDAY(_xlfn.MINIFS($L$6:$L$22,$E$6:$E$22,E53),Paramètres!$B$10) -> 46363 | K53: =ROUNDUP(I53/5,0) -> 4 | L53: =MAX(J53,WORKDAY(M52,1)) -> 46498 | M53: =WORKDAY(L53,I53-1) -> 46521 | N53: =COUNTIFS(Backlog!$K$6:$K$1327,A53,Backlog!$O$6:$O$1327,"Terminé") -> 0 | O53: =IF(F53=0,0,N53/F53) -> 0 | P53: =IF(O53=1,"Terminé",IF(OR(O53>0,COUNTIFS(Backlog!$K$6:$K$1327,A53,Backlog!$O$6:$O$1327,"En cours")>0),"En cours","À faire")) -> À faire
A54: ADM-WH|1 | B54: Admin | C54: ADM-WH | D54: Supervision technique | E54: 1 | F54: =COUNTIFS(Backlog!$K$6:$K$1327,A54) -> 15 | G54: =SUMIFS(Backlog!$I$6:$I$1327,Backlog!$K$6:$K$1327,A54) -> 17.5 | H54: =IF(B54="API",Paramètres!$B$7,IF(B54="Mobile",Paramètres!$B$8,Paramètres!$B$9)) -> 2 | I54: =MAX(1,ROUNDUP(G54*(1+Paramètres!$B$6)/(H54*Paramètres!$B$5),0)) -> 13 | J54: =WORKDAY(_xlfn.MINIFS($L$6:$L$22,$E$6:$E$22,E54),Paramètres!$B$10) -> 46363 | K54: =ROUNDUP(I54/5,0) -> 3 | L54: =MAX(J54,WORKDAY(M53,1)) -> 46524 | M54: =WORKDAY(L54,I54-1) -> 46540 | N54: =COUNTIFS(Backlog!$K$6:$K$1327,A54,Backlog!$O$6:$O$1327,"Terminé") -> 0 | O54: =IF(F54=0,0,N54/F54) -> 0 | P54: =IF(O54=1,"Terminé",IF(OR(O54>0,COUNTIFS(Backlog!$K$6:$K$1327,A54,Backlog!$O$6:$O$1327,"En cours")>0),"En cours","À faire")) -> À faire
A55: ADM-WI|1 | B55: Admin | C55: ADM-WI | D55: Comptes, configuration et notifications | E55: 1 | F55: =COUNTIFS(Backlog!$K$6:$K$1327,A55) -> 21 | G55: =SUMIFS(Backlog!$I$6:$I$1327,Backlog!$K$6:$K$1327,A55) -> 23.5 | H55: =IF(B55="API",Paramètres!$B$7,IF(B55="Mobile",Paramètres!$B$8,Paramètres!$B$9)) -> 2 | I55: =MAX(1,ROUNDUP(G55*(1+Paramètres!$B$6)/(H55*Paramètres!$B$5),0)) -> 17 | J55: =WORKDAY(_xlfn.MINIFS($L$6:$L$22,$E$6:$E$22,E55),Paramètres!$B$10) -> 46363 | K55: =ROUNDUP(I55/5,0) -> 4 | L55: =MAX(J55,WORKDAY(M54,1)) -> 46541 | M55: =WORKDAY(L55,I55-1) -> 46563 | N55: =COUNTIFS(Backlog!$K$6:$K$1327,A55,Backlog!$O$6:$O$1327,"Terminé") -> 0 | O55: =IF(F55=0,0,N55/F55) -> 0 | P55: =IF(O55=1,"Terminé",IF(OR(O55>0,COUNTIFS(Backlog!$K$6:$K$1327,A55,Backlog!$O$6:$O$1327,"En cours")>0),"En cours","À faire")) -> À faire
A56: ADM-WJ|1 | B56: Admin | C56: ADM-WJ | D56: Utilisateurs et évolutions phase 2-3 | E56: 1 | F56: =COUNTIFS(Backlog!$K$6:$K$1327,A56) -> 4 | G56: =SUMIFS(Backlog!$I$6:$I$1327,Backlog!$K$6:$K$1327,A56) -> 7 | H56: =IF(B56="API",Paramètres!$B$7,IF(B56="Mobile",Paramètres!$B$8,Paramètres!$B$9)) -> 2 | I56: =MAX(1,ROUNDUP(G56*(1+Paramètres!$B$6)/(H56*Paramètres!$B$5),0)) -> 6 | J56: =WORKDAY(_xlfn.MINIFS($L$6:$L$22,$E$6:$E$22,E56),Paramètres!$B$10) -> 46363 | K56: =ROUNDUP(I56/5,0) -> 2 | L56: =MAX(J56,WORKDAY(M55,1)) -> 46566 | M56: =WORKDAY(L56,I56-1) -> 46573 | N56: =COUNTIFS(Backlog!$K$6:$K$1327,A56,Backlog!$O$6:$O$1327,"Terminé") -> 0 | O56: =IF(F56=0,0,N56/F56) -> 0 | P56: =IF(O56=1,"Terminé",IF(OR(O56>0,COUNTIFS(Backlog!$K$6:$K$1327,A56,Backlog!$O$6:$O$1327,"En cours")>0),"En cours","À faire")) -> À faire
A57: ADM-WG|2 | B57: Admin | C57: ADM-WG | D57: Modération communautaire | E57: 2 | F57: =COUNTIFS(Backlog!$K$6:$K$1327,A57) -> 27 | G57: =SUMIFS(Backlog!$I$6:$I$1327,Backlog!$K$6:$K$1327,A57) -> 27.5 | H57: =IF(B57="API",Paramètres!$B$7,IF(B57="Mobile",Paramètres!$B$8,Paramètres!$B$9)) -> 2 | I57: =MAX(1,ROUNDUP(G57*(1+Paramètres!$B$6)/(H57*Paramètres!$B$5),0)) -> 20 | J57: =WORKDAY(_xlfn.MINIFS($L$6:$L$22,$E$6:$E$22,E57),Paramètres!$B$10) -> 46555 | K57: =ROUNDUP(I57/5,0) -> 4 | L57: =MAX(J57,WORKDAY(M56,1)) -> 46574 | M57: =WORKDAY(L57,I57-1) -> 46601 | N57: =COUNTIFS(Backlog!$K$6:$K$1327,A57,Backlog!$O$6:$O$1327,"Terminé") -> 0 | O57: =IF(F57=0,0,N57/F57) -> 0 | P57: =IF(O57=1,"Terminé",IF(OR(O57>0,COUNTIFS(Backlog!$K$6:$K$1327,A57,Backlog!$O$6:$O$1327,"En cours")>0),"En cours","À faire")) -> À faire
A58: ADM-WJ|2 | B58: Admin | C58: ADM-WJ | D58: Utilisateurs et évolutions phase 2-3 | E58: 2 | F58: =COUNTIFS(Backlog!$K$6:$K$1327,A58) -> 5 | G58: =SUMIFS(Backlog!$I$6:$I$1327,Backlog!$K$6:$K$1327,A58) -> 7 | H58: =IF(B58="API",Paramètres!$B$7,IF(B58="Mobile",Paramètres!$B$8,Paramètres!$B$9)) -> 2 | I58: =MAX(1,ROUNDUP(G58*(1+Paramètres!$B$6)/(H58*Paramètres!$B$5),0)) -> 6 | J58: =WORKDAY(_xlfn.MINIFS($L$6:$L$22,$E$6:$E$22,E58),Paramètres!$B$10) -> 46555 | K58: =ROUNDUP(I58/5,0) -> 2 | L58: =MAX(J58,WORKDAY(M57,1)) -> 46602 | M58: =WORKDAY(L58,I58-1) -> 46609 | N58: =COUNTIFS(Backlog!$K$6:$K$1327,A58,Backlog!$O$6:$O$1327,"Terminé") -> 0 | O58: =IF(F58=0,0,N58/F58) -> 0 | P58: =IF(O58=1,"Terminé",IF(OR(O58>0,COUNTIFS(Backlog!$K$6:$K$1327,A58,Backlog!$O$6:$O$1327,"En cours")>0),"En cours","À faire")) -> À faire
A59: ADM-WJ|3 | B59: Admin | C59: ADM-WJ | D59: Utilisateurs et évolutions phase 2-3 | E59: 3 | F59: =COUNTIFS(Backlog!$K$6:$K$1327,A59) -> 4 | G59: =SUMIFS(Backlog!$I$6:$I$1327,Backlog!$K$6:$K$1327,A59) -> 6 | H59: =IF(B59="API",Paramètres!$B$7,IF(B59="Mobile",Paramètres!$B$8,Paramètres!$B$9)) -> 2 | I59: =MAX(1,ROUNDUP(G59*(1+Paramètres!$B$6)/(H59*Paramètres!$B$5),0)) -> 5 | J59: =WORKDAY(_xlfn.MINIFS($L$6:$L$22,$E$6:$E$22,E59),Paramètres!$B$10) -> 46673 | K59: =ROUNDUP(I59/5,0) -> 1 | L59: =MAX(J59,WORKDAY(M58,1)) -> 46673 | M59: =WORKDAY(L59,I59-1) -> 46679 | N59: =COUNTIFS(Backlog!$K$6:$K$1327,A59,Backlog!$O$6:$O$1327,"Terminé") -> 0 | O59: =IF(F59=0,0,N59/F59) -> 0 | P59: =IF(O59=1,"Terminé",IF(OR(O59>0,COUNTIFS(Backlog!$K$6:$K$1327,A59,Backlog!$O$6:$O$1327,"En cours")>0),"En cours","À faire")) -> À faire
D60: TOTAL | F60: =SUM(F6:F59) -> 1322 | G60: =SUM(G6:G59) -> 1371.75 | L60: =MIN(L6:L59) -> 46328 | M60: =MAX(M6:M59) -> 46748

Sheet Backlog
A1: Backlog complet (toutes les issues des 3 dépôts)
A2: Une ligne par issue. Colonnes bleues = saisie de suivi (statut, dates réelles, assigné). Le lien ouvre l’issue sur GitHub.
A5: Code | B5: Flux | C5: Épopée | D5: Module | E5: Titre | F5: Type | G5: Priorité | H5: Taille | I5: Charge (j) | J5: Phase | K5: Clé plan | L5: Dépendances | M5: Écrans | N5: Assigné | O5: Statut | P5: Début réel | Q5: Fin réel | R5: Début prévu (épopée) | S5: Fin prévue (épopée) | T5: Lien GitHub
A6: API-PLAT-01 | B6: API | C6: API-PLAT | D6: Plateforme, qualité, performance et exploitation | E6: GET /config : configuration publique de démarrage consommée par le mobile | F6: api | G6: P0 | H6: M | I6: =VLOOKUP(H6,Paramètres!$A$15:$B$19,2,FALSE()) -> 1 | J6: 0 | K6: =C6&"|"&J6 -> API-PLAT|0 | M6: 3 | N6: BorisGautier | O6: À faire | R6: =INDEX(Épopées!$L$6:$L$59,MATCH(K6,Épopées!$A$6:$A$59,0)) -> 46328 | S6: =INDEX(Épopées!$M$6:$M$59,MATCH(K6,Épopées!$A$6:$A$59,0)) -> 46331 | T6: Ouvrir
A7: API-PLAT-02 | B7: API | C7: API-PLAT | D7: Plateforme, qualité, performance et exploitation | E7: GET /version : version de l'API, du build et du contrat | F7: api | G7: P1 | H7: XS | I7: =VLOOKUP(H7,Paramètres!$A$15:$B$19,2,FALSE()) -> 0.25 | J7: 0 | K7: =C7&"|"&J7 -> API-PLAT|0 | L7: API-PLAT-01 | M7: 1 | N7: BorisGautier | O7: À faire | R7: =INDEX(Épopées!$L$6:$L$59,MATCH(K7,Épopées!$A$6:$A$59,0)) -> 46328 | S7: =INDEX(Épopées!$M$6:$M$59,MATCH(K7,Épopées!$A$6:$A$59,0)) -> 46331 | T7: Ouvrir
A8: API-PLAT-27 | B8: API | C8: API-PLAT | D8: Plateforme, qualité, performance et exploitation | E8: Audit des dépendances en CI : npm audit, Dependabot, Trivy bloquant, licences | F8: securite | G8: P0 | H8: S | I8: =VLOOKUP(H8,Paramètres!$A$15:$B$19,2,FALSE()) -> 0.5 | J8: 0 | K8: =C8&"|"&J8 -> API-PLAT|0 | M8: 0 | N8: BorisGautier | O8: À faire | R8: =INDEX(Épopées!$L$6:$L$59,MATCH(K8,Épopées!$A$6:$A$59,0)) -> 46328 | S8: =INDEX(Épopées!$M$6:$M$59,MATCH(K8,Épopées!$A$6:$A$59,0)) -> 46331 | T8: Ouvrir
A9: API-PLAT-36 | B9: API | C9: API-PLAT | D9: Plateforme, qualité, performance et exploitation | E9: Seuils de couverture par couche appliqués en CI (CDC §8.2) | F9: tests | G9: P0 | H9: S | I9: =VLOOKUP(H9,Paramètres!$A$15:$B$19,2,FALSE()) -> 0.5 | J9: 0 | K9: =C9&"|"&J9 -> API-PLAT|0 | M9: 0 | N9: BorisGautier | O9: À faire | R9: =INDEX(Épopées!$L$6:$L$59,MATCH(K9,Épopées!$A$6:$A$59,0)) -> 46328 | S9: =INDEX(Épopées!$M$6:$M$59,MATCH(K9,Épopées!$A$6:$A$59,0)) -> 46331 | T9: Ouvrir
A10: API-PLAT-38 | B10: API | C10: API-PLAT | D10: Plateforme, qualité, performance et exploitation | E10: Fixtures, factories et jeu de données de test partagés | F10: tests | G10: P1 | H10: S | I10: =VLOOKUP(H10,Paramètres!$A$15:$B$19,2,FALSE()) -> 0.5 | J10: 0 | K10: =C10&"|"&J10 -> API-PLAT|0 | M10: 0 | N10: BorisGautier | O10: À faire | R10: =INDEX(Épopées!$L$6:$L$59,MATCH(K10,Épopées!$A$6:$A$59,0)) -> 46328 | S10: =INDEX(Épopées!$M$6:$M$59,MATCH(K10,Épopées!$A$6:$A$59,0)) -> 46331 | T10: Ouvrir
A11: API-PLAT-39 | B11: API | C11: API-PLAT | D11: Plateforme, qualité, performance et exploitation | E11: Règle obligatoire : chaque nouvelle route est ajoutée aux scénarios k6 (garde CI) | F11: tests | G11: P0 | H11: M | I11: =VLOOKUP(H11,Paramètres!$A$15:$B$19,2,FALSE()) -> 1 | J11: 0 | K11: =C11&"|"&J11 -> API-PLAT|0 | M11: 0 | N11: BorisGautier | O11: À faire | R11: =INDEX(Épopées!$L$6:$L$59,MATCH(K11,Épopées!$A$6:$A$59,0)) -> 46328 | S11: =INDEX(Épopées!$M$6:$M$59,MATCH(K11,Épopées!$A$6:$A$59,0)) -> 46331 | T11: Ouvrir
A12: API-PLAT-40 | B12: API | C12: API-PLAT | D12: Plateforme, qualité, performance et exploitation | E12: Seuils k6 par endpoint (p95/p99/erreurs) et budgets de performance | F12: tests | G12: P0 | H12: M | I12: =VLOOKUP(H12,Paramètres!$A$15:$B$19,2,FALSE()) -> 1 | J12: 0 | K12: =C12&"|"&J12 -> API-PLAT|0 | L12: API-PLAT-39 | M12: 1 | N12: BorisGautier | O12: À faire | R12: =INDEX(Épopées!$L$6:$L$59,MATCH(K12,Épopées!$A$6:$A$59,0)) -> 46328 | S12: =INDEX(Épopées!$M$6:$M$59,MATCH(K12,Épopées!$A$6:$A$59,0)) -> 46331 | T12: Ouvrir
A13: API-PLAT-45 | B13: API | C13: API-PLAT | D13: Plateforme, qualité, performance et exploitation | E13: Portes de qualité du pipeline : charge, contrat, sécurité avant staging et production | F13: infra | G13: P0 | H13: M | I13: =VLOOKUP(H13,Paramètres!$A$15:$B$19,2,FALSE()) -> 1 | J13: 0 | K13: =C13&"|"&J13 -> API-PLAT|0 | M13: 0 | N13: BorisGautier | O13: À faire | R13: =INDEX(Épopées!$L$6:$L$59,MATCH(K13,Épopées!$A$6:$A$59,0)) -> 46328 | S13: =INDEX(Épopées!$M$6:$M$59,MATCH(K13,Épopées!$A$6:$A$59,0)) -> 46331 | T13: Ouvrir
A14: API-PLAT-47 | B14: API | C14: API-PLAT | D14: Plateforme, qualité, performance et exploitation | E14: Environnements dev/staging/prod : matrice de configuration et gestion des secrets | F14: infra | G14: P0 | H14: S | I14: =VLOOKUP(H14,Paramètres!$A$15:$B$19,2,FALSE()) -> 0.5 | J14: 0 | K14: =C14&"|"&J14 -> API-PLAT|0 | M14: 0 | N14: BorisGautier | O14: À faire | R14: =INDEX(Épopées!$L$6:$L$59,MATCH(K14,Épopées!$A$6:$A$59,0)) -> 46328 | S14: =INDEX(Épopées!$M$6:$M$59,MATCH(K14,Épopées!$A$6:$A$59,0)) -> 46331 | T14: Ouvrir
A15: API-PLAT-51 | B15: API | C15: API-PLAT | D15: Plateforme, qualité, performance et exploitation | E15: Migrations migrate-mongo et seed par environnement | F15: donnees | G15: P1 | H15: S | I15: =VLOOKUP(H15,Paramètres!$A$15:$B$19,2,FALSE()) -> 0.5 | J15: 0 | K15: =C15&"|"&J15 -> API-PLAT|0 | M15: 0 | N15: BorisGautier | O15: À faire | R15: =INDEX(Épopées!$L$6:$L$59,MATCH(K15,Épopées!$A$6:$A$59,0)) -> 46328 | S15: =INDEX(Épopées!$M$6:$M$59,MATCH(K15,Épopées!$A$6:$A$59,0)) -> 46331 | T15: Ouvrir
A16: API-AUTH-01 | B16: API | C16: API-AUTH | D16: Identité, authentification, comptes et RGPD | E16: Abstraction du fournisseur d'e-mails (SMTP / API HTTP) avec mode sandbox | F16: infra | G16: P0 | H16: M | I16: =VLOOKUP(H16,Paramètres!$A$15:$B$19,2,FALSE()) -> 1 | J16: 0 | K16: =C16&"|"&J16 -> API-AUTH|0 | M16: 4 | N16: BorisGautier | O16: À faire | R16: =INDEX(Épopées!$L$6:$L$59,MATCH(K16,Épopées!$A$6:$A$59,0)) -> 46332 | S16: =INDEX(Épopées!$M$6:$M$59,MATCH(K16,Épopées!$A$6:$A$59,0)) -> 46332 | T16: Ouvrir
A17: API-AUTH-02 | B17: API | C17: API-AUTH | D17: Identité, authentification, comptes et RGPD | E17: Worker BullMQ `email` : envoi asynchrone, retries, dead-letter | F17: fonctionnel | G17: P0 | H17: M | I17: =VLOOKUP(H17,Paramètres!$A$15:$B$19,2,FALSE()) -> 1 | J17: 0 | K17: =C17&"|"&J17 -> API-AUTH|0 | L17: API-AUTH-01 | M17: 3 | N17: BorisGautier | O17: À faire | R17: =INDEX(Épopées!$L$6:$L$59,MATCH(K17,Épopées!$A$6:$A$59,0)) -> 46332 | S17: =INDEX(Épopées!$M$6:$M$59,MATCH(K17,Épopées!$A$6:$A$59,0)) -> 46332 | T17: Ouvrir
A18: API-PLAT-03 | B18: API | C18: API-PLAT | D18: Plateforme, qualité, performance et exploitation | E18: Maintenance planifiée : fenêtre datée, message et réponse 503 normalisée (A-06) | F18: fonctionnel | G18: P0 | H18: M | I18: =VLOOKUP(H18,Paramètres!$A$15:$B$19,2,FALSE()) -> 1 | J18: 1 | K18: =C18&"|"&J18 -> API-PLAT|1 | L18: API-PLAT-01 | M18: 2 | N18: BorisGautier | O18: À faire | R18: =INDEX(Épopées!$L$6:$L$59,MATCH(K18,Épopées!$A$6:$A$59,0)) -> 46335 | S18: =INDEX(Épopées!$M$6:$M$59,MATCH(K18,Épopées!$A$6:$A$59,0)) -> 46363 | T18: Ouvrir
A19: API-PLAT-04 | B19: API | C19: API-PLAT | D19: Plateforme, qualité, performance et exploitation | E19: Version minimale requise : en-tête X-App-Version et réponse 426 (A-07) | F19: fonctionnel | G19: P0 | H19: M | I19: =VLOOKUP(H19,Paramètres!$A$15:$B$19,2,FALSE()) -> 1 | J19: 1 | K19: =C19&"|"&J19 -> API-PLAT|1 | L19: API-PLAT-01, API-PLAT-03 | M19: 1 | N19: BorisGautier | O19: À faire | R19: =INDEX(Épopées!$L$6:$L$59,MATCH(K19,Épopées!$A$6:$A$59,0)) -> 46335 | S19: =INDEX(Épopées!$M$6:$M$59,MATCH(K19,Épopées!$A$6:$A$59,0)) -> 46363 | T19: Ouvrir
A20: API-PLAT-05 | B20: API | C20: API-PLAT | D20: Plateforme, qualité, performance et exploitation | E20: Erreurs 5xx : code d'incident utilisateur et traceId systématique (A-04) | F20: fonctionnel | G20: P0 | H20: S | I20: =VLOOKUP(H20,Paramètres!$A$15:$B$19,2,FALSE()) -> 0.5 | J20: 1 | K20: =C20&"|"&J20 -> API-PLAT|1 | M20: 1 | N20: BorisGautier | O20: À faire | R20: =INDEX(Épopées!$L$6:$L$59,MATCH(K20,Épopées!$A$6:$A$59,0)) -> 46335 | S20: =INDEX(Épopées!$M$6:$M$59,MATCH(K20,Épopées!$A$6:$A$59,0)) -> 46363 | T20: Ouvrir
A21: API-PLAT-06 | B21: API | C21: API-PLAT | D21: Plateforme, qualité, performance et exploitation | E21: 429 : en-tête Retry-After, quotas restants et compte à rebours (A-05) | F21: fonctionnel | G21: P0 | H21: M | I21: =VLOOKUP(H21,Paramètres!$A$15:$B$19,2,FALSE()) -> 1 | J21: 1 | K21: =C21&"|"&J21 -> API-PLAT|1 | L21: API-PLAT-05 | M21: 1 | N21: BorisGautier | O21: À faire | R21: =INDEX(Épopées!$L$6:$L$59,MATCH(K21,Épopées!$A$6:$A$59,0)) -> 46335 | S21: =INDEX(Épopées!$M$6:$M$59,MATCH(K21,Épopées!$A$6:$A$59,0)) -> 46363 | T21: Ouvrir
A22: API-PLAT-07 | B22: API | C22: API-PLAT | D22: Plateforme, qualité, performance et exploitation | E22: Catalogue des codes d'erreur et états système (contrat mobile A-03 à A-08) | F22: doc | G22: P1 | H22: S | I22: =VLOOKUP(H22,Paramètres!$A$15:$B$19,2,FALSE()) -> 0.5 | J22: 1 | K22: =C22&"|"&J22 -> API-PLAT|1 | L22: API-PLAT-05, API-PLAT-06, API-PLAT-03, API-PLAT-04 | M22: 6 | N22: BorisGautier | O22: À faire | R22: =INDEX(Épopées!$L$6:$L$59,MATCH(K22,Épopées!$A$6:$A$59,0)) -> 46335 | S22: =INDEX(Épopées!$M$6:$M$59,MATCH(K22,Épopées!$A$6:$A$59,0)) -> 46363 | T22: Ouvrir
A23: API-PLAT-08 | B23: API | C23: API-PLAT | D23: Plateforme, qualité, performance et exploitation | E23: Feature flags : modèle durci et évaluation déterministe par utilisateur | F23: donnees | G23: P0 | H23: M | I23: =VLOOKUP(H23,Paramètres!$A$15:$B$19,2,FALSE()) -> 1 | J23: 1 | K23: =C23&"|"&J23 -> API-PLAT|1 | M23: 1 | N23: BorisGautier | O23: À faire | R23: =INDEX(Épopées!$L$6:$L$59,MATCH(K23,Épopées!$A$6:$A$59,0)) -> 46335 | S23: =INDEX(Épopées!$M$6:$M$59,MATCH(K23,Épopées!$A$6:$A$59,0)) -> 46363 | T23: Ouvrir
A24: API-PLAT-09 | B24: API | C24: API-PLAT | D24: Plateforme, qualité, performance et exploitation | E24: Feature flags : exposition évaluée dans /config et /config/flags | F24: api | G24: P0 | H24: S | I24: =VLOOKUP(H24,Paramètres!$A$15:$B$19,2,FALSE()) -> 0.5 | J24: 1 | K24: =C24&"|"&J24 -> API-PLAT|1 | L24: API-PLAT-08, API-PLAT-01 | M24: 2 | N24: BorisGautier | O24: À faire | R24: =INDEX(Épopées!$L$6:$L$59,MATCH(K24,Épopées!$A$6:$A$59,0)) -> 46335 | S24: =INDEX(Épopées!$M$6:$M$59,MATCH(K24,Épopées!$A$6:$A$59,0)) -> 46363 | T24: Ouvrir
A25: API-PLAT-10 | B25: API | C25: API-PLAT | D25: Plateforme, qualité, performance et exploitation | E25: Admin : GET/PATCH /admin/config/feature-flags (WI-05) | F25: api | G25: P1 | H25: M | I25: =VLOOKUP(H25,Paramètres!$A$15:$B$19,2,FALSE()) -> 1 | J25: 1 | K25: =C25&"|"&J25 -> API-PLAT|1 | L25: API-PLAT-08 | M25: 1 | N25: BorisGautier | O25: À faire | R25: =INDEX(Épopées!$L$6:$L$59,MATCH(K25,Épopées!$A$6:$A$59,0)) -> 46335 | S25: =INDEX(Épopées!$M$6:$M$59,MATCH(K25,Épopées!$A$6:$A$59,0)) -> 46363 | T25: Ouvrir
A26: API-PLAT-11 | B26: API | C26: API-PLAT | D26: Plateforme, qualité, performance et exploitation | E26: Admin : GET/PATCH /admin/config/ai-quotas (WI-06) | F26: api | G26: P1 | H26: M | I26: =VLOOKUP(H26,Paramètres!$A$15:$B$19,2,FALSE()) -> 1 | J26: 1 | K26: =C26&"|"&J26 -> API-PLAT|1 | L26: API-PLAT-06 | M26: 1 | N26: BorisGautier | O26: À faire | R26: =INDEX(Épopées!$L$6:$L$59,MATCH(K26,Épopées!$A$6:$A$59,0)) -> 46335 | S26: =INDEX(Épopées!$M$6:$M$59,MATCH(K26,Épopées!$A$6:$A$59,0)) -> 46363 | T26: Ouvrir
A27: API-PLAT-12 | B27: API | C27: API-PLAT | D27: Plateforme, qualité, performance et exploitation | E27: GET /admin/observability/health : statut agrégé et séries p50/p95/p99 (WH-01) | F27: api | G27: P1 | H27: L | I27: =VLOOKUP(H27,Paramètres!$A$15:$B$19,2,FALSE()) -> 2 | J27: 1 | K27: =C27&"|"&J27 -> API-PLAT|1 | M27: 1 | N27: BorisGautier | O27: À faire | R27: =INDEX(Épopées!$L$6:$L$59,MATCH(K27,Épopées!$A$6:$A$59,0)) -> 46335 | S27: =INDEX(Épopées!$M$6:$M$59,MATCH(K27,Épopées!$A$6:$A$59,0)) -> 46363 | T27: Ouvrir
A28: API-PLAT-13 | B28: API | C28: API-PLAT | D28: Plateforme, qualité, performance et exploitation | E28: Alertes actives (Alertmanager) pour le tableau de bord de supervision (WH-01) | F28: api | G28: P1 | H28: S | I28: =VLOOKUP(H28,Paramètres!$A$15:$B$19,2,FALSE()) -> 0.5 | J28: 1 | K28: =C28&"|"&J28 -> API-PLAT|1 | L28: API-PLAT-12 | M28: 1 | N28: BorisGautier | O28: À faire | R28: =INDEX(Épopées!$L$6:$L$59,MATCH(K28,Épopées!$A$6:$A$59,0)) -> 46335 | S28: =INDEX(Épopées!$M$6:$M$59,MATCH(K28,Épopées!$A$6:$A$59,0)) -> 46363 | T28: Ouvrir
A29: API-PLAT-14 | B29: API | C29: API-PLAT | D29: Plateforme, qualité, performance et exploitation | E29: GET /admin/observability/queues : état de chaque file BullMQ (WH-02) | F29: api | G29: P1 | H29: M | I29: =VLOOKUP(H29,Paramètres!$A$15:$B$19,2,FALSE()) -> 1 | J29: 1 | K29: =C29&"|"&J29 -> API-PLAT|1 | M29: 1 | N29: BorisGautier | O29: À faire | R29: =INDEX(Épopées!$L$6:$L$59,MATCH(K29,Épopées!$A$6:$A$59,0)) -> 46335 | S29: =INDEX(Épopées!$M$6:$M$59,MATCH(K29,Épopées!$A$6:$A$59,0)) -> 46363 | T29: Ouvrir
A30: API-PLAT-15 | B30: API | C30: API-PLAT | D30: Plateforme, qualité, performance et exploitation | E30: POST /admin/observability/queues/:jobId/retry : relance manuelle d'un job en échec | F30: api | G30: P1 | H30: M | I30: =VLOOKUP(H30,Paramètres!$A$15:$B$19,2,FALSE()) -> 1 | J30: 1 | K30: =C30&"|"&J30 -> API-PLAT|1 | L30: API-PLAT-14 | M30: 1 | N30: BorisGautier | O30: À faire | R30: =INDEX(Épopées!$L$6:$L$59,MATCH(K30,Épopées!$A$6:$A$59,0)) -> 46335 | S30: =INDEX(Épopées!$M$6:$M$59,MATCH(K30,Épopées!$A$6:$A$59,0)) -> 46363 | T30: Ouvrir
A31: API-PLAT-16 | B31: API | C31: API-PLAT | D31: Plateforme, qualité, performance et exploitation | E31: GET /admin/observability/logs : recherche Graylog filtrée et masquée (WH-03) | F31: api | G31: P1 | H31: L | I31: =VLOOKUP(H31,Paramètres!$A$15:$B$19,2,FALSE()) -> 2 | J31: 1 | K31: =C31&"|"&J31 -> API-PLAT|1 | L31: API-PLAT-25 | M31: 1 | N31: BorisGautier | O31: À faire | R31: =INDEX(Épopées!$L$6:$L$59,MATCH(K31,Épopées!$A$6:$A$59,0)) -> 46335 | S31: =INDEX(Épopées!$M$6:$M$59,MATCH(K31,Épopées!$A$6:$A$59,0)) -> 46363 | T31: Ouvrir
A32: API-PLAT-17 | B32: API | C32: API-PLAT | D32: Plateforme, qualité, performance et exploitation | E32: Consommation IA : mesure, quotas et projection de dépassement (WH-04) | F32: api | G32: P1 | H32: L | I32: =VLOOKUP(H32,Paramètres!$A$15:$B$19,2,FALSE()) -> 2 | J32: 1 | K32: =C32&"|"&J32 -> API-PLAT|1 | L32: API-PLAT-11 | M32: 2 | N32: BorisGautier | O32: À faire | R32: =INDEX(Épopées!$L$6:$L$59,MATCH(K32,Épopées!$A$6:$A$59,0)) -> 46335 | S32: =INDEX(Épopées!$M$6:$M$59,MATCH(K32,Épopées!$A$6:$A$59,0)) -> 46363 | T32: Ouvrir
A33: API-PLAT-18 | B33: API | C33: API-PLAT | D33: Plateforme, qualité, performance et exploitation | E33: Journal d'audit : immuabilité, filtres complets et export CSV (WH-05) | F33: securite | G33: P1 | H33: M | I33: =VLOOKUP(H33,Paramètres!$A$15:$B$19,2,FALSE()) -> 1 | J33: 1 | K33: =C33&"|"&J33 -> API-PLAT|1 | M33: 1 | N33: BorisGautier | O33: À faire | R33: =INDEX(Épopées!$L$6:$L$59,MATCH(K33,Épopées!$A$6:$A$59,0)) -> 46335 | S33: =INDEX(Épopées!$M$6:$M$59,MATCH(K33,Épopées!$A$6:$A$59,0)) -> 46363 | T33: Ouvrir
A34: API-PLAT-19 | B34: API | C34: API-PLAT | D34: Plateforme, qualité, performance et exploitation | E34: Audit des actions comptes, sessions, configuration et notifications manuelles (WI-01 à WI-09) | F34: securite | G34: P1 | H34: M | I34: =VLOOKUP(H34,Paramètres!$A$15:$B$19,2,FALSE()) -> 1 | J34: 1 | K34: =C34&"|"&J34 -> API-PLAT|1 | L34: API-PLAT-18 | M34: 6 | N34: BorisGautier | O34: À faire | R34: =INDEX(Épopées!$L$6:$L$59,MATCH(K34,Épopées!$A$6:$A$59,0)) -> 46335 | S34: =INDEX(Épopées!$M$6:$M$59,MATCH(K34,Épopées!$A$6:$A$59,0)) -> 46363 | T34: Ouvrir
A35: API-PLAT-21 | B35: API | C35: API-PLAT | D35: Plateforme, qualité, performance et exploitation | E35: Métriques Prometheus métier et RED par route (ub_*) | F35: infra | G35: P0 | H35: M | I35: =VLOOKUP(H35,Paramètres!$A$15:$B$19,2,FALSE()) -> 1 | J35: 1 | K35: =C35&"|"&J35 -> API-PLAT|1 | M35: 2 | N35: BorisGautier | O35: À faire | R35: =INDEX(Épopées!$L$6:$L$59,MATCH(K35,Épopées!$A$6:$A$59,0)) -> 46335 | S35: =INDEX(Épopées!$M$6:$M$59,MATCH(K35,Épopées!$A$6:$A$59,0)) -> 46363 | T35: Ouvrir
A36: API-PLAT-22 | B36: API | C36: API-PLAT | D36: Plateforme, qualité, performance et exploitation | E36: Tableaux de bord Grafana provisionnés (santé, usage, coûts IA, sécurité) | F36: infra | G36: P1 | H36: M | I36: =VLOOKUP(H36,Paramètres!$A$15:$B$19,2,FALSE()) -> 1 | J36: 1 | K36: =C36&"|"&J36 -> API-PLAT|1 | L36: API-PLAT-21 | M36: 2 | N36: BorisGautier | O36: À faire | R36: =INDEX(Épopées!$L$6:$L$59,MATCH(K36,Épopées!$A$6:$A$59,0)) -> 46335 | S36: =INDEX(Épopées!$M$6:$M$59,MATCH(K36,Épopées!$A$6:$A$59,0)) -> 46363 | T36: Ouvrir
A37: API-PLAT-23 | B37: API | C37: API-PLAT | D37: Plateforme, qualité, performance et exploitation | E37: Alerting : règles complètes et canaux de notification (e-mail / webhook) | F37: infra | G37: P0 | H37: M | I37: =VLOOKUP(H37,Paramètres!$A$15:$B$19,2,FALSE()) -> 1 | J37: 1 | K37: =C37&"|"&J37 -> API-PLAT|1 | L37: API-PLAT-21 | M37: 1 | N37: BorisGautier | O37: À faire | R37: =INDEX(Épopées!$L$6:$L$59,MATCH(K37,Épopées!$A$6:$A$59,0)) -> 46335 | S37: =INDEX(Épopées!$M$6:$M$59,MATCH(K37,Épopées!$A$6:$A$59,0)) -> 46363 | T37: Ouvrir
A38: API-PLAT-24 | B38: API | C38: API-PLAT | D38: Plateforme, qualité, performance et exploitation | E38: OpenTelemetry : traces, spans Mongo/Redis/BullMQ et propagation traceId | F38: infra | G38: P1 | H38: M | I38: =VLOOKUP(H38,Paramètres!$A$15:$B$19,2,FALSE()) -> 1 | J38: 1 | K38: =C38&"|"&J38 -> API-PLAT|1 | L38: API-PLAT-21 | M38: 2 | N38: BorisGautier | O38: À faire | R38: =INDEX(Épopées!$L$6:$L$59,MATCH(K38,Épopées!$A$6:$A$59,0)) -> 46335 | S38: =INDEX(Épopées!$M$6:$M$59,MATCH(K38,Épopées!$A$6:$A$59,0)) -> 46363 | T38: Ouvrir
A39: API-PLAT-25 | B39: API | C39: API-PLAT | D39: Plateforme, qualité, performance et exploitation | E39: Logs structurés Winston vers Graylog (GELF) avec masquage et rétention 90 jours | F39: infra | G39: P1 | H39: M | I39: =VLOOKUP(H39,Paramètres!$A$15:$B$19,2,FALSE()) -> 1 | J39: 1 | K39: =C39&"|"&J39 -> API-PLAT|1 | M39: 1 | N39: BorisGautier | O39: À faire | R39: =INDEX(Épopées!$L$6:$L$59,MATCH(K39,Épopées!$A$6:$A$59,0)) -> 46335 | S39: =INDEX(Épopées!$M$6:$M$59,MATCH(K39,Épopées!$A$6:$A$59,0)) -> 46363 | T39: Ouvrir
A40: API-PLAT-26 | B40: API | C40: API-PLAT | D40: Plateforme, qualité, performance et exploitation | E40: En-têtes de sécurité (Helmet, CSP), CORS strict et cookies admin | F40: securite | G40: P0 | H40: S | I40: =VLOOKUP(H40,Paramètres!$A$15:$B$19,2,FALSE()) -> 0.5 | J40: 1 | K40: =C40&"|"&J40 -> API-PLAT|1 | M40: 0 | N40: BorisGautier | O40: À faire | R40: =INDEX(Épopées!$L$6:$L$59,MATCH(K40,Épopées!$A$6:$A$59,0)) -> 46335 | S40: =INDEX(Épopées!$M$6:$M$59,MATCH(K40,Épopées!$A$6:$A$59,0)) -> 46363 | T40: Ouvrir
A41: API-PLAT-28 | B41: API | C41: API-PLAT | D41: Plateforme, qualité, performance et exploitation | E41: Rotation des secrets : JWT à clés multiples (kid), clés tierces et procédure | F41: securite | G41: P1 | H41: M | I41: =VLOOKUP(H41,Paramètres!$A$15:$B$19,2,FALSE()) -> 1 | J41: 1 | K41: =C41&"|"&J41 -> API-PLAT|1 | M41: 0 | N41: BorisGautier | O41: À faire | R41: =INDEX(Épopées!$L$6:$L$59,MATCH(K41,Épopées!$A$6:$A$59,0)) -> 46335 | S41: =INDEX(Épopées!$M$6:$M$59,MATCH(K41,Épopées!$A$6:$A$59,0)) -> 46363 | T41: Ouvrir
A42: API-PLAT-30 | B42: API | C42: API-PLAT | D42: Plateforme, qualité, performance et exploitation | E42: Protection SSRF : client HTTP sortant avec liste blanche et validation d'URL | F42: securite | G42: P1 | H42: S | I42: =VLOOKUP(H42,Paramètres!$A$15:$B$19,2,FALSE()) -> 0.5 | J42: 1 | K42: =C42&"|"&J42 -> API-PLAT|1 | M42: 0 | N42: BorisGautier | O42: À faire | R42: =INDEX(Épopées!$L$6:$L$59,MATCH(K42,Épopées!$A$6:$A$59,0)) -> 46335 | S42: =INDEX(Épopées!$M$6:$M$59,MATCH(K42,Épopées!$A$6:$A$59,0)) -> 46363 | T42: Ouvrir
A43: API-PLAT-31 | B43: API | C43: API-PLAT | D43: Plateforme, qualité, performance et exploitation | E43: Audit des index MongoDB : explain, profiler et budget de requêtes | F43: performance | G43: P1 | H43: M | I43: =VLOOKUP(H43,Paramètres!$A$15:$B$19,2,FALSE()) -> 1 | J43: 1 | K43: =C43&"|"&J43 -> API-PLAT|1 | M43: 0 | N43: BorisGautier | O43: À faire | R43: =INDEX(Épopées!$L$6:$L$59,MATCH(K43,Épopées!$A$6:$A$59,0)) -> 46335 | S43: =INDEX(Épopées!$M$6:$M$59,MATCH(K43,Épopées!$A$6:$A$59,0)) -> 46363 | T43: Ouvrir
A44: API-PLAT-32 | B44: API | C44: API-PLAT | D44: Plateforme, qualité, performance et exploitation | E44: Cache Redis cache-aside standard : TTL du CDC, invalidation et anti-stampede | F44: performance | G44: P0 | H44: M | I44: =VLOOKUP(H44,Paramètres!$A$15:$B$19,2,FALSE()) -> 1 | J44: 1 | K44: =C44&"|"&J44 -> API-PLAT|1 | M44: 0 | N44: BorisGautier | O44: À faire | R44: =INDEX(Épopées!$L$6:$L$59,MATCH(K44,Épopées!$A$6:$A$59,0)) -> 46335 | S44: =INDEX(Épopées!$M$6:$M$59,MATCH(K44,Épopées!$A$6:$A$59,0)) -> 46363 | T44: Ouvrir
A45: API-PLAT-33 | B45: API | C45: API-PLAT | D45: Plateforme, qualité, performance et exploitation | E45: Timeouts serveur, pool MongoDB/Redis et limites de requête | F45: performance | G45: P1 | H45: S | I45: =VLOOKUP(H45,Paramètres!$A$15:$B$19,2,FALSE()) -> 0.5 | J45: 1 | K45: =C45&"|"&J45 -> API-PLAT|1 | M45: 1 | N45: BorisGautier | O45: À faire | R45: =INDEX(Épopées!$L$6:$L$59,MATCH(K45,Épopées!$A$6:$A$59,0)) -> 46335 | S45: =INDEX(Épopées!$M$6:$M$59,MATCH(K45,Épopées!$A$6:$A$59,0)) -> 46363 | T45: Ouvrir
A46: API-PLAT-34 | B46: API | C46: API-PLAT | D46: Plateforme, qualité, performance et exploitation | E46: Circuit breakers et dégradation gracieuse vers les fournisseurs externes | F46: fonctionnel | G46: P1 | H46: M | I46: =VLOOKUP(H46,Paramètres!$A$15:$B$19,2,FALSE()) -> 1 | J46: 1 | K46: =C46&"|"&J46 -> API-PLAT|1 | M46: 2 | N46: BorisGautier | O46: À faire | R46: =INDEX(Épopées!$L$6:$L$59,MATCH(K46,Épopées!$A$6:$A$59,0)) -> 46335 | S46: =INDEX(Épopées!$M$6:$M$59,MATCH(K46,Épopées!$A$6:$A$59,0)) -> 46363 | T46: Ouvrir
A47: API-PLAT-35 | B47: API | C47: API-PLAT | D47: Plateforme, qualité, performance et exploitation | E47: Arrêt gracieux, processus worker dédié et readiness | F47: infra | G47: P1 | H47: M | I47: =VLOOKUP(H47,Paramètres!$A$15:$B$19,2,FALSE()) -> 1 | J47: 1 | K47: =C47&"|"&J47 -> API-PLAT|1 | M47: 0 | N47: BorisGautier | O47: À faire | R47: =INDEX(Épopées!$L$6:$L$59,MATCH(K47,Épopées!$A$6:$A$59,0)) -> 46335 | S47: =INDEX(Épopées!$M$6:$M$59,MATCH(K47,Épopées!$A$6:$A$59,0)) -> 46363 | T47: Ouvrir
A48: API-PLAT-37 | B48: API | C48: API-PLAT | D48: Plateforme, qualité, performance et exploitation | E48: Tests de contrat OpenAPI et non-régression nocturne | F48: tests | G48: P1 | H48: M | I48: =VLOOKUP(H48,Paramètres!$A$15:$B$19,2,FALSE()) -> 1 | J48: 1 | K48: =C48&"|"&J48 -> API-PLAT|1 | M48: 0 | N48: BorisGautier | O48: À faire | R48: =INDEX(Épopées!$L$6:$L$59,MATCH(K48,Épopées!$A$6:$A$59,0)) -> 46335 | S48: =INDEX(Épopées!$M$6:$M$59,MATCH(K48,Épopées!$A$6:$A$59,0)) -> 46363 | T48: Ouvrir
A49: API-PLAT-41 | B49: API | C49: API-PLAT | D49: Plateforme, qualité, performance et exploitation | E49: Profils de trafic réalistes : soir de match, annonce push, ouverture d'app | F49: tests | G49: P1 | H49: M | I49: =VLOOKUP(H49,Paramètres!$A$15:$B$19,2,FALSE()) -> 1 | J49: 1 | K49: =C49&"|"&J49 -> API-PLAT|1 | L49: API-PLAT-39, API-PLAT-40 | M49: 3 | N49: BorisGautier | O49: À faire | R49: =INDEX(Épopées!$L$6:$L$59,MATCH(K49,Épopées!$A$6:$A$59,0)) -> 46335 | S49: =INDEX(Épopées!$M$6:$M$59,MATCH(K49,Épopées!$A$6:$A$59,0)) -> 46363 | T49: Ouvrir
A50: API-PLAT-42 | B50: API | C50: API-PLAT | D50: Plateforme, qualité, performance et exploitation | E50: Seed volumétrique pour les tests de charge (100 000 utilisateurs, catalogue réaliste) | F50: donnees | G50: P1 | H50: M | I50: =VLOOKUP(H50,Paramètres!$A$15:$B$19,2,FALSE()) -> 1 | J50: 1 | K50: =C50&"|"&J50 -> API-PLAT|1 | M50: 0 | N50: BorisGautier | O50: À faire | R50: =INDEX(Épopées!$L$6:$L$59,MATCH(K50,Épopées!$A$6:$A$59,0)) -> 46335 | S50: =INDEX(Épopées!$M$6:$M$59,MATCH(K50,Épopées!$A$6:$A$59,0)) -> 46363 | T50: Ouvrir
A51: API-PLAT-43 | B51: API | C51: API-PLAT | D51: Plateforme, qualité, performance et exploitation | E51: Suivi de capacité : baseline versionnée, tendance et journal des capacités mesurées | F51: tests | G51: P0 | H51: M | I51: =VLOOKUP(H51,Paramètres!$A$15:$B$19,2,FALSE()) -> 1 | J51: 1 | K51: =C51&"|"&J51 -> API-PLAT|1 | L51: API-PLAT-40 | M51: 0 | N51: BorisGautier | O51: À faire | R51: =INDEX(Épopées!$L$6:$L$59,MATCH(K51,Épopées!$A$6:$A$59,0)) -> 46335 | S51: =INDEX(Épopées!$M$6:$M$59,MATCH(K51,Épopées!$A$6:$A$59,0)) -> 46363 | T51: Ouvrir
A52: API-PLAT-44 | B52: API | C52: API-PLAT | D52: Plateforme, qualité, performance et exploitation | E52: Dimensionnement du serveur : protocole de mesure, règles et plan d'évolution | F52: infra | G52: P0 | H52: M | I52: =VLOOKUP(H52,Paramètres!$A$15:$B$19,2,FALSE()) -> 1 | J52: 1 | K52: =C52&"|"&J52 -> API-PLAT|1 | L52: API-PLAT-43, API-PLAT-42 | M52: 0 | N52: BorisGautier | O52: À faire | R52: =INDEX(Épopées!$L$6:$L$59,MATCH(K52,Épopées!$A$6:$A$59,0)) -> 46335 | S52: =INDEX(Épopées!$M$6:$M$59,MATCH(K52,Épopées!$A$6:$A$59,0)) -> 46363 | T52: Ouvrir
A53: API-PLAT-46 | B53: API | C53: API-PLAT | D53: Plateforme, qualité, performance et exploitation | E53: Rollback documenté et testé : image précédente et migration inverse | F53: infra | G53: P1 | H53: M | I53: =VLOOKUP(H53,Paramètres!$A$15:$B$19,2,FALSE()) -> 1 | J53: 1 | K53: =C53&"|"&J53 -> API-PLAT|1 | M53: 0 | N53: BorisGautier | O53: À faire | R53: =INDEX(Épopées!$L$6:$L$59,MATCH(K53,Épopées!$A$6:$A$59,0)) -> 46335 | S53: =INDEX(Épopées!$M$6:$M$59,MATCH(K53,Épopées!$A$6:$A$59,0)) -> 46363 | T53: Ouvrir
A54: API-PLAT-48 | B54: API | C54: API-PLAT | D54: Plateforme, qualité, performance et exploitation | E54: Runbooks d'exploitation et d'incident (un par alerte) | F54: doc | G54: P1 | H54: M | I54: =VLOOKUP(H54,Paramètres!$A$15:$B$19,2,FALSE()) -> 1 | J54: 1 | K54: =C54&"|"&J54 -> API-PLAT|1 | M54: 3 | N54: BorisGautier | O54: À faire | R54: =INDEX(Épopées!$L$6:$L$59,MATCH(K54,Épopées!$A$6:$A$59,0)) -> 46335 | S54: =INDEX(Épopées!$M$6:$M$59,MATCH(K54,Épopées!$A$6:$A$59,0)) -> 46363 | T54: Ouvrir
A55: API-PLAT-49 | B55: API | C55: API-PLAT | D55: Plateforme, qualité, performance et exploitation | E55: Sauvegardes automatiques : job database-backup, rétention 30 j + 6 mois, copie hors VPS | F55: infra | G55: P0 | H55: M | I55: =VLOOKUP(H55,Paramètres!$A$15:$B$19,2,FALSE()) -> 1 | J55: 1 | K55: =C55&"|"&J55 -> API-PLAT|1 | M55: 1 | N55: BorisGautier | O55: À faire | R55: =INDEX(Épopées!$L$6:$L$59,MATCH(K55,Épopées!$A$6:$A$59,0)) -> 46335 | S55: =INDEX(Épopées!$M$6:$M$59,MATCH(K55,Épopées!$A$6:$A$59,0)) -> 46363 | T55: Ouvrir
A56: API-PLAT-50 | B56: API | C56: API-PLAT | D56: Plateforme, qualité, performance et exploitation | E56: Restauration et reprise après sinistre : test trimestriel automatisé (RPO/RTO) | F56: infra | G56: P1 | H56: M | I56: =VLOOKUP(H56,Paramètres!$A$15:$B$19,2,FALSE()) -> 1 | J56: 1 | K56: =C56&"|"&J56 -> API-PLAT|1 | L56: API-PLAT-49 | M56: 0 | N56: BorisGautier | O56: À faire | R56: =INDEX(Épopées!$L$6:$L$59,MATCH(K56,Épopées!$A$6:$A$59,0)) -> 46335 | S56: =INDEX(Épopées!$M$6:$M$59,MATCH(K56,Épopées!$A$6:$A$59,0)) -> 46363 | T56: Ouvrir
A57: API-PLAT-52 | B57: API | C57: API-PLAT | D57: Plateforme, qualité, performance et exploitation | E57: Jobs de purge et politique de rétention des données techniques | F57: rgpd | G57: P1 | H57: M | I57: =VLOOKUP(H57,Paramètres!$A$15:$B$19,2,FALSE()) -> 1 | J57: 1 | K57: =C57&"|"&J57 -> API-PLAT|1 | M57: 0 | N57: BorisGautier | O57: À faire | R57: =INDEX(Épopées!$L$6:$L$59,MATCH(K57,Épopées!$A$6:$A$59,0)) -> 46335 | S57: =INDEX(Épopées!$M$6:$M$59,MATCH(K57,Épopées!$A$6:$A$59,0)) -> 46363 | T57: Ouvrir
A58: API-PLAT-53 | B58: API | C58: API-PLAT | D58: Plateforme, qualité, performance et exploitation | E58: Dead-letter centralisée et politique de retry par type de job | F58: fonctionnel | G58: P1 | H58: M | I58: =VLOOKUP(H58,Paramètres!$A$15:$B$19,2,FALSE()) -> 1 | J58: 1 | K58: =C58&"|"&J58 -> API-PLAT|1 | M58: 1 | N58: BorisGautier | O58: À faire | R58: =INDEX(Épopées!$L$6:$L$59,MATCH(K58,Épopées!$A$6:$A$59,0)) -> 46335 | S58: =INDEX(Épopées!$M$6:$M$59,MATCH(K58,Épopées!$A$6:$A$59,0)) -> 46363 | T58: Ouvrir
A59: API-PLAT-54 | B59: API | C59: API-PLAT | D59: Plateforme, qualité, performance et exploitation | E59: Registre des traitements RGPD, minimisation et revue de conformité | F59: rgpd | G59: P1 | H59: M | I59: =VLOOKUP(H59,Paramètres!$A$15:$B$19,2,FALSE()) -> 1 | J59: 1 | K59: =C59&"|"&J59 -> API-PLAT|1 | M59: 2 | N59: BorisGautier | O59: À faire | R59: =INDEX(Épopées!$L$6:$L$59,MATCH(K59,Épopées!$A$6:$A$59,0)) -> 46335 | S59: =INDEX(Épopées!$M$6:$M$59,MATCH(K59,Épopées!$A$6:$A$59,0)) -> 46363 | T59: Ouvrir
A60: API-PLAT-55 | B60: API | C60: API-PLAT | D60: Plateforme, qualité, performance et exploitation | E60: Documentation plateforme : OpenAPI système/supervision, guides d'intégration mobile/admin | F60: doc | G60: P1 | H60: S | I60: =VLOOKUP(H60,Paramètres!$A$15:$B$19,2,FALSE()) -> 0.5 | J60: 1 | K60: =C60&"|"&J60 -> API-PLAT|1 | M60: 14 | N60: BorisGautier | O60: À faire | R60: =INDEX(Épopées!$L$6:$L$59,MATCH(K60,Épopées!$A$6:$A$59,0)) -> 46335 | S60: =INDEX(Épopées!$M$6:$M$59,MATCH(K60,Épopées!$A$6:$A$59,0)) -> 46363 | T60: Ouvrir
A61: API-AUTH-03 | B61: API | C61: API-AUTH | D61: Identité, authentification, comptes et RGPD | E61: Modèles d'e-mails transactionnels FR/EN/ES (vérification, reset, export, invitation, alertes) | F61: i18n | G61: P0 | H61: L | I61: =VLOOKUP(H61,Paramètres!$A$15:$B$19,2,FALSE()) -> 2 | J61: 1 | K61: =C61&"|"&J61 -> API-AUTH|1 | L61: API-AUTH-02 | M61: 4 | N61: BorisGautier | O61: À faire | R61: =INDEX(Épopées!$L$6:$L$59,MATCH(K61,Épopées!$A$6:$A$59,0)) -> 46364 | S61: =INDEX(Épopées!$M$6:$M$59,MATCH(K61,Épopées!$A$6:$A$59,0)) -> 46398 | T61: Ouvrir
A62: API-AUTH-04 | B62: API | C62: API-AUTH | D62: Identité, authentification, comptes et RGPD | E62: Vérification d'e-mail par code à 6 chiffres + lien, renvoi avec délai de 60 s | F62: fonctionnel | G62: P0 | H62: M | I62: =VLOOKUP(H62,Paramètres!$A$15:$B$19,2,FALSE()) -> 1 | J62: 1 | K62: =C62&"|"&J62 -> API-AUTH|1 | L62: API-AUTH-03 | M62: 3 | N62: BorisGautier | O62: À faire | R62: =INDEX(Épopées!$L$6:$L$59,MATCH(K62,Épopées!$A$6:$A$59,0)) -> 46364 | S62: =INDEX(Épopées!$M$6:$M$59,MATCH(K62,Épopées!$A$6:$A$59,0)) -> 46398 | T62: Ouvrir
A63: API-AUTH-05 | B63: API | C63: API-AUTH | D63: Identité, authentification, comptes et RGPD | E63: Inscription : alignement validations B-06/B-07, pseudo, charte et statut | F63: fonctionnel | G63: P0 | H63: M | I63: =VLOOKUP(H63,Paramètres!$A$15:$B$19,2,FALSE()) -> 1 | J63: 1 | K63: =C63&"|"&J63 -> API-AUTH|1 | L63: API-AUTH-04 | M63: 4 | N63: BorisGautier | O63: À faire | R63: =INDEX(Épopées!$L$6:$L$59,MATCH(K63,Épopées!$A$6:$A$59,0)) -> 46364 | S63: =INDEX(Épopées!$M$6:$M$59,MATCH(K63,Épopées!$A$6:$A$59,0)) -> 46398 | T63: Ouvrir
A64: API-AUTH-06 | B64: API | C64: API-AUTH | D64: Identité, authentification, comptes et RGPD | E64: Politique de mot de passe unifiée, liste de mots de passe courants et indicateur de force | F64: securite | G64: P1 | H64: M | I64: =VLOOKUP(H64,Paramètres!$A$15:$B$19,2,FALSE()) -> 1 | J64: 1 | K64: =C64&"|"&J64 -> API-AUTH|1 | L64: API-AUTH-05 | M64: 5 | N64: BorisGautier | O64: À faire | R64: =INDEX(Épopées!$L$6:$L$59,MATCH(K64,Épopées!$A$6:$A$59,0)) -> 46364 | S64: =INDEX(Épopées!$M$6:$M$59,MATCH(K64,Épopées!$A$6:$A$59,0)) -> 46398 | T64: Ouvrir
A65: API-AUTH-07 | B65: API | C65: API-AUTH | D65: Identité, authentification, comptes et RGPD | E65: Verrouillage progressif et décompte des essais restants à la connexion | F65: securite | G65: P0 | H65: M | I65: =VLOOKUP(H65,Paramètres!$A$15:$B$19,2,FALSE()) -> 1 | J65: 1 | K65: =C65&"|"&J65 -> API-AUTH|1 | M65: 2 | N65: BorisGautier | O65: À faire | R65: =INDEX(Épopées!$L$6:$L$59,MATCH(K65,Épopées!$A$6:$A$59,0)) -> 46364 | S65: =INDEX(Épopées!$M$6:$M$59,MATCH(K65,Épopées!$A$6:$A$59,0)) -> 46398 | T65: Ouvrir
A66: API-AUTH-08 | B66: API | C66: API-AUTH | D66: Identité, authentification, comptes et RGPD | E66: États du compte (actif, suspendu, banni, supprimé) et contrat d'erreur pour A-09 / A-10 | F66: fonctionnel | G66: P0 | H66: M | I66: =VLOOKUP(H66,Paramètres!$A$15:$B$19,2,FALSE()) -> 1 | J66: 1 | K66: =C66&"|"&J66 -> API-AUTH|1 | L66: API-AUTH-07 | M66: 4 | N66: BorisGautier | O66: À faire | R66: =INDEX(Épopées!$L$6:$L$59,MATCH(K66,Épopées!$A$6:$A$59,0)) -> 46364 | S66: =INDEX(Épopées!$M$6:$M$59,MATCH(K66,Épopées!$A$6:$A$59,0)) -> 46398 | T66: Ouvrir
A67: API-AUTH-09 | B67: API | C67: API-AUTH | D67: Identité, authentification, comptes et RGPD | E67: Contrat « session expirée » : codes 401 distincts pour A-08 et le refresh silencieux | F67: api | G67: P0 | H67: S | I67: =VLOOKUP(H67,Paramètres!$A$15:$B$19,2,FALSE()) -> 0.5 | J67: 1 | K67: =C67&"|"&J67 -> API-AUTH|1 | L67: API-AUTH-08 | M67: 2 | N67: BorisGautier | O67: À faire | R67: =INDEX(Épopées!$L$6:$L$59,MATCH(K67,Épopées!$A$6:$A$59,0)) -> 46364 | S67: =INDEX(Épopées!$M$6:$M$59,MATCH(K67,Épopées!$A$6:$A$59,0)) -> 46398 | T67: Ouvrir
A68: API-AUTH-10 | B68: API | C68: API-AUTH | D68: Identité, authentification, comptes et RGPD | E68: Connexion / inscription Google : vérification de l'id token côté serveur | F68: fonctionnel | G68: P0 | H68: L | I68: =VLOOKUP(H68,Paramètres!$A$15:$B$19,2,FALSE()) -> 2 | J68: 1 | K68: =C68&"|"&J68 -> API-AUTH|1 | L68: API-AUTH-05, API-AUTH-08 | M68: 3 | N68: BorisGautier | O68: À faire | R68: =INDEX(Épopées!$L$6:$L$59,MATCH(K68,Épopées!$A$6:$A$59,0)) -> 46364 | S68: =INDEX(Épopées!$M$6:$M$59,MATCH(K68,Épopées!$A$6:$A$59,0)) -> 46398 | T68: Ouvrir
A69: API-AUTH-11 | B69: API | C69: API-AUTH | D69: Identité, authentification, comptes et RGPD | E69: Connexion / inscription Sign in with Apple (obligatoire iOS) avec vérification du jeton | F69: fonctionnel | G69: P0 | H69: L | I69: =VLOOKUP(H69,Paramètres!$A$15:$B$19,2,FALSE()) -> 2 | J69: 1 | K69: =C69&"|"&J69 -> API-AUTH|1 | L69: API-AUTH-10 | M69: 3 | N69: BorisGautier | O69: À faire | R69: =INDEX(Épopées!$L$6:$L$59,MATCH(K69,Épopées!$A$6:$A$59,0)) -> 46364 | S69: =INDEX(Épopées!$M$6:$M$59,MATCH(K69,Épopées!$A$6:$A$59,0)) -> 46398 | T69: Ouvrir
A70: API-AUTH-12 | B70: API | C70: API-AUTH | D70: Identité, authentification, comptes et RGPD | E70: Rattachement / détachement des fournisseurs sociaux et définition d'un mot de passe | F70: fonctionnel | G70: P1 | H70: M | I70: =VLOOKUP(H70,Paramètres!$A$15:$B$19,2,FALSE()) -> 1 | J70: 1 | K70: =C70&"|"&J70 -> API-AUTH|1 | L70: API-AUTH-11 | M70: 3 | N70: BorisGautier | O70: À faire | R70: =INDEX(Épopées!$L$6:$L$59,MATCH(K70,Épopées!$A$6:$A$59,0)) -> 46364 | S70: =INDEX(Épopées!$M$6:$M$59,MATCH(K70,Épopées!$A$6:$A$59,0)) -> 46398 | T70: Ouvrir
A71: API-AUTH-13 | B71: API | C71: API-AUTH | D71: Identité, authentification, comptes et RGPD | E71: Refresh à rotation : atomicité, tolérance de course et tests de rejeu par famille | F71: securite | G71: P0 | H71: M | I71: =VLOOKUP(H71,Paramètres!$A$15:$B$19,2,FALSE()) -> 1 | J71: 1 | K71: =C71&"|"&J71 -> API-AUTH|1 | M71: 1 | N71: BorisGautier | O71: À faire | R71: =INDEX(Épopées!$L$6:$L$59,MATCH(K71,Épopées!$A$6:$A$59,0)) -> 46364 | S71: =INDEX(Épopées!$M$6:$M$59,MATCH(K71,Épopées!$A$6:$A$59,0)) -> 46398 | T71: Ouvrir
A72: API-AUTH-14 | B72: API | C72: API-AUTH | D72: Identité, authentification, comptes et RGPD | E72: « Rester connecté » : durées de session différenciées | F72: fonctionnel | G72: P2 | H72: S | I72: =VLOOKUP(H72,Paramètres!$A$15:$B$19,2,FALSE()) -> 0.5 | J72: 1 | K72: =C72&"|"&J72 -> API-AUTH|1 | L72: API-AUTH-13 | M72: 1 | N72: BorisGautier | O72: À faire | R72: =INDEX(Épopées!$L$6:$L$59,MATCH(K72,Épopées!$A$6:$A$59,0)) -> 46364 | S72: =INDEX(Épopées!$M$6:$M$59,MATCH(K72,Épopées!$A$6:$A$59,0)) -> 46398 | T72: Ouvrir
A73: API-AUTH-15 | B73: API | C73: API-AUTH | D73: Identité, authentification, comptes et RGPD | E73: Liste des appareils connectés (GET /users/me/sessions) | F73: api | G73: P1 | H73: M | I73: =VLOOKUP(H73,Paramètres!$A$15:$B$19,2,FALSE()) -> 1 | J73: 1 | K73: =C73&"|"&J73 -> API-AUTH|1 | L73: API-AUTH-09 | M73: 2 | N73: BorisGautier | O73: À faire | R73: =INDEX(Épopées!$L$6:$L$59,MATCH(K73,Épopées!$A$6:$A$59,0)) -> 46364 | S73: =INDEX(Épopées!$M$6:$M$59,MATCH(K73,Épopées!$A$6:$A$59,0)) -> 46398 | T73: Ouvrir
A74: API-AUTH-16 | B74: API | C74: API-AUTH | D74: Identité, authentification, comptes et RGPD | E74: Révocation d'un appareil et déconnexion de tous les appareils | F74: fonctionnel | G74: P1 | H74: S | I74: =VLOOKUP(H74,Paramètres!$A$15:$B$19,2,FALSE()) -> 0.5 | J74: 1 | K74: =C74&"|"&J74 -> API-AUTH|1 | L74: API-AUTH-15 | M74: 3 | N74: BorisGautier | O74: À faire | R74: =INDEX(Épopées!$L$6:$L$59,MATCH(K74,Épopées!$A$6:$A$59,0)) -> 46364 | S74: =INDEX(Épopées!$M$6:$M$59,MATCH(K74,Épopées!$A$6:$A$59,0)) -> 46398 | T74: Ouvrir
A75: API-AUTH-17 | B75: API | C75: API-AUTH | D75: Identité, authentification, comptes et RGPD | E75: Mot de passe oublié : envoi réel du lien, anti-énumération et délais | F75: fonctionnel | G75: P0 | H75: M | I75: =VLOOKUP(H75,Paramètres!$A$15:$B$19,2,FALSE()) -> 1 | J75: 1 | K75: =C75&"|"&J75 -> API-AUTH|1 | L75: API-AUTH-03 | M75: 3 | N75: BorisGautier | O75: À faire | R75: =INDEX(Épopées!$L$6:$L$59,MATCH(K75,Épopées!$A$6:$A$59,0)) -> 46364 | S75: =INDEX(Épopées!$M$6:$M$59,MATCH(K75,Épopées!$A$6:$A$59,0)) -> 46398 | T75: Ouvrir
A76: API-AUTH-18 | B76: API | C76: API-AUTH | D76: Identité, authentification, comptes et RGPD | E76: Réinitialisation du mot de passe : politique B-19, usage unique, déconnexion et alerte | F76: securite | G76: P0 | H76: M | I76: =VLOOKUP(H76,Paramètres!$A$15:$B$19,2,FALSE()) -> 1 | J76: 1 | K76: =C76&"|"&J76 -> API-AUTH|1 | L76: API-AUTH-06, API-AUTH-17 | M76: 2 | N76: BorisGautier | O76: À faire | R76: =INDEX(Épopées!$L$6:$L$59,MATCH(K76,Épopées!$A$6:$A$59,0)) -> 46364 | S76: =INDEX(Épopées!$M$6:$M$59,MATCH(K76,Épopées!$A$6:$A$59,0)) -> 46398 | T76: Ouvrir
A77: API-AUTH-19 | B77: API | C77: API-AUTH | D77: Identité, authentification, comptes et RGPD | E77: Changement de mot de passe connecté (POST /users/me/password/change) | F77: fonctionnel | G77: P1 | H77: S | I77: =VLOOKUP(H77,Paramètres!$A$15:$B$19,2,FALSE()) -> 0.5 | J77: 1 | K77: =C77&"|"&J77 -> API-AUTH|1 | L77: API-AUTH-18 | M77: 2 | N77: BorisGautier | O77: À faire | R77: =INDEX(Épopées!$L$6:$L$59,MATCH(K77,Épopées!$A$6:$A$59,0)) -> 46364 | S77: =INDEX(Épopées!$M$6:$M$59,MATCH(K77,Épopées!$A$6:$A$59,0)) -> 46398 | T77: Ouvrir
A78: API-AUTH-20 | B78: API | C78: API-AUTH | D78: Identité, authentification, comptes et RGPD | E78: Changement d'adresse e-mail avec code de vérification | F78: fonctionnel | G78: P1 | H78: M | I78: =VLOOKUP(H78,Paramètres!$A$15:$B$19,2,FALSE()) -> 1 | J78: 1 | K78: =C78&"|"&J78 -> API-AUTH|1 | L78: API-AUTH-04, API-AUTH-06 | M78: 2 | N78: BorisGautier | O78: À faire | R78: =INDEX(Épopées!$L$6:$L$59,MATCH(K78,Épopées!$A$6:$A$59,0)) -> 46364 | S78: =INDEX(Épopées!$M$6:$M$59,MATCH(K78,Épopées!$A$6:$A$59,0)) -> 46398 | T78: Ouvrir
A79: API-AUTH-21 | B79: API | C79: API-AUTH | D79: Identité, authentification, comptes et RGPD | E79: Consentements RGPD : lecture de l'état courant et de l'historique | F79: rgpd | G79: P0 | H79: M | I79: =VLOOKUP(H79,Paramètres!$A$15:$B$19,2,FALSE()) -> 1 | J79: 1 | K79: =C79&"|"&J79 -> API-AUTH|1 | M79: 3 | N79: BorisGautier | O79: À faire | R79: =INDEX(Épopées!$L$6:$L$59,MATCH(K79,Épopées!$A$6:$A$59,0)) -> 46364 | S79: =INDEX(Épopées!$M$6:$M$59,MATCH(K79,Épopées!$A$6:$A$59,0)) -> 46398 | T79: Ouvrir
A80: API-AUTH-22 | B80: API | C80: API-AUTH | D80: Identité, authentification, comptes et RGPD | E80: Versions des documents légaux (CGU, confidentialité, charte) et re-acceptation | F80: rgpd | G80: P1 | H80: M | I80: =VLOOKUP(H80,Paramètres!$A$15:$B$19,2,FALSE()) -> 1 | J80: 1 | K80: =C80&"|"&J80 -> API-AUTH|1 | L80: API-AUTH-21 | M80: 3 | N80: BorisGautier | O80: À faire | R80: =INDEX(Épopées!$L$6:$L$59,MATCH(K80,Épopées!$A$6:$A$59,0)) -> 46364 | S80: =INDEX(Épopées!$M$6:$M$59,MATCH(K80,Épopées!$A$6:$A$59,0)) -> 46398 | T80: Ouvrir
A81: API-AUTH-23 | B81: API | C81: API-AUTH | D81: Identité, authentification, comptes et RGPD | E81: Effets du retrait de consentement : géolocalisation, notifications, statistiques | F81: rgpd | G81: P1 | H81: M | I81: =VLOOKUP(H81,Paramètres!$A$15:$B$19,2,FALSE()) -> 1 | J81: 1 | K81: =C81&"|"&J81 -> API-AUTH|1 | L81: API-AUTH-21 | M81: 2 | N81: BorisGautier | O81: À faire | R81: =INDEX(Épopées!$L$6:$L$59,MATCH(K81,Épopées!$A$6:$A$59,0)) -> 46364 | S81: =INDEX(Épopées!$M$6:$M$59,MATCH(K81,Épopées!$A$6:$A$59,0)) -> 46398 | T81: Ouvrir
A82: API-AUTH-24 | B82: API | C82: API-AUTH | D82: Identité, authentification, comptes et RGPD | E82: Export RGPD asynchrone : demande, job `rgpd` et suivi d'état | F82: rgpd | G82: P0 | H82: L | I82: =VLOOKUP(H82,Paramètres!$A$15:$B$19,2,FALSE()) -> 2 | J82: 1 | K82: =C82&"|"&J82 -> API-AUTH|1 | L82: API-AUTH-02, API-AUTH-16 | M82: 3 | N82: BorisGautier | O82: À faire | R82: =INDEX(Épopées!$L$6:$L$59,MATCH(K82,Épopées!$A$6:$A$59,0)) -> 46364 | S82: =INDEX(Épopées!$M$6:$M$59,MATCH(K82,Épopées!$A$6:$A$59,0)) -> 46398 | T82: Ouvrir
A83: API-AUTH-25 | B83: API | C83: API-AUTH | D83: Identité, authentification, comptes et RGPD | E83: Construction de l'archive d'export, stockage objet et lien temporaire (7 jours) | F83: rgpd | G83: P0 | H83: L | I83: =VLOOKUP(H83,Paramètres!$A$15:$B$19,2,FALSE()) -> 2 | J83: 1 | K83: =C83&"|"&J83 -> API-AUTH|1 | L83: API-AUTH-24, API-AUTH-03 | M83: 2 | N83: BorisGautier | O83: À faire | R83: =INDEX(Épopées!$L$6:$L$59,MATCH(K83,Épopées!$A$6:$A$59,0)) -> 46364 | S83: =INDEX(Épopées!$M$6:$M$59,MATCH(K83,Épopées!$A$6:$A$59,0)) -> 46398 | T83: Ouvrir
A84: API-AUTH-26 | B84: API | C84: API-AUTH | D84: Identité, authentification, comptes et RGPD | E84: Suppression de compte : confirmation forte, période J+30 et annulation | F84: rgpd | G84: P0 | H84: M | I84: =VLOOKUP(H84,Paramètres!$A$15:$B$19,2,FALSE()) -> 1 | J84: 1 | K84: =C84&"|"&J84 -> API-AUTH|1 | L84: API-AUTH-24 | M84: 4 | N84: BorisGautier | O84: À faire | R84: =INDEX(Épopées!$L$6:$L$59,MATCH(K84,Épopées!$A$6:$A$59,0)) -> 46364 | S84: =INDEX(Épopées!$M$6:$M$59,MATCH(K84,Épopées!$A$6:$A$59,0)) -> 46398 | T84: Ouvrir
A85: API-AUTH-27 | B85: API | C85: API-AUTH | D85: Identité, authentification, comptes et RGPD | E85: Purge J+30 : suppression en cascade et anonymisation selon la matrice §4.8 | F85: rgpd | G85: P0 | H85: L | I85: =VLOOKUP(H85,Paramètres!$A$15:$B$19,2,FALSE()) -> 2 | J85: 1 | K85: =C85&"|"&J85 -> API-AUTH|1 | L85: API-AUTH-26, API-AUTH-25 | M85: 2 | N85: BorisGautier | O85: À faire | R85: =INDEX(Épopées!$L$6:$L$59,MATCH(K85,Épopées!$A$6:$A$59,0)) -> 46364 | S85: =INDEX(Épopées!$M$6:$M$59,MATCH(K85,Épopées!$A$6:$A$59,0)) -> 46398 | T85: Ouvrir
A86: API-AUTH-28 | B86: API | C86: API-AUTH | D86: Identité, authentification, comptes et RGPD | E86: Préférences utilisateur : langue, thème, accessibilité, validations de PATCH /users/me | F86: api | G86: P0 | H86: M | I86: =VLOOKUP(H86,Paramètres!$A$15:$B$19,2,FALSE()) -> 1 | J86: 1 | K86: =C86&"|"&J86 -> API-AUTH|1 | M86: 5 | N86: BorisGautier | O86: À faire | R86: =INDEX(Épopées!$L$6:$L$59,MATCH(K86,Épopées!$A$6:$A$59,0)) -> 46364 | S86: =INDEX(Épopées!$M$6:$M$59,MATCH(K86,Épopées!$A$6:$A$59,0)) -> 46398 | T86: Ouvrir
A87: API-AUTH-29 | B87: API | C87: API-AUTH | D87: Identité, authentification, comptes et RGPD | E87: Profil d'onboarding : pays/ville, joueur préféré, ancienneté et progression | F87: fonctionnel | G87: P1 | H87: M | I87: =VLOOKUP(H87,Paramètres!$A$15:$B$19,2,FALSE()) -> 1 | J87: 1 | K87: =C87&"|"&J87 -> API-AUTH|1 | L87: API-AUTH-28 | M87: 6 | N87: BorisGautier | O87: À faire | R87: =INDEX(Épopées!$L$6:$L$59,MATCH(K87,Épopées!$A$6:$A$59,0)) -> 46364 | S87: =INDEX(Épopées!$M$6:$M$59,MATCH(K87,Épopées!$A$6:$A$59,0)) -> 46398 | T87: Ouvrir
A88: API-AUTH-30 | B88: API | C88: API-AUTH | D88: Identité, authentification, comptes et RGPD | E88: Profil public vs privé : projections et visibilité | F88: fonctionnel | G88: P1 | H88: M | I88: =VLOOKUP(H88,Paramètres!$A$15:$B$19,2,FALSE()) -> 1 | J88: 1 | K88: =C88&"|"&J88 -> API-AUTH|1 | L88: API-AUTH-29 | M88: 3 | N88: BorisGautier | O88: À faire | R88: =INDEX(Épopées!$L$6:$L$59,MATCH(K88,Épopées!$A$6:$A$59,0)) -> 46364 | S88: =INDEX(Épopées!$M$6:$M$59,MATCH(K88,Épopées!$A$6:$A$59,0)) -> 46398 | T88: Ouvrir
A89: API-AUTH-31 | B89: API | C89: API-AUTH | D89: Identité, authentification, comptes et RGPD | E89: Avatar : upload, validation, redimensionnement et stockage objet | F89: fonctionnel | G89: P1 | H89: L | I89: =VLOOKUP(H89,Paramètres!$A$15:$B$19,2,FALSE()) -> 2 | J89: 1 | K89: =C89&"|"&J89 -> API-AUTH|1 | L89: API-AUTH-25 | M89: 2 | N89: BorisGautier | O89: À faire | R89: =INDEX(Épopées!$L$6:$L$59,MATCH(K89,Épopées!$A$6:$A$59,0)) -> 46364 | S89: =INDEX(Épopées!$M$6:$M$59,MATCH(K89,Épopées!$A$6:$A$59,0)) -> 46398 | T89: Ouvrir
A90: API-AUTH-32 | B90: API | C90: API-AUTH | D90: Identité, authentification, comptes et RGPD | E90: RBAC admin : matrice de permissions et garde `requirePermission` | F90: securite | G90: P0 | H90: M | I90: =VLOOKUP(H90,Paramètres!$A$15:$B$19,2,FALSE()) -> 1 | J90: 1 | K90: =C90&"|"&J90 -> API-AUTH|1 | M90: 2 | N90: BorisGautier | O90: À faire | R90: =INDEX(Épopées!$L$6:$L$59,MATCH(K90,Épopées!$A$6:$A$59,0)) -> 46364 | S90: =INDEX(Épopées!$M$6:$M$59,MATCH(K90,Épopées!$A$6:$A$59,0)) -> 46398 | T90: Ouvrir
A91: API-AUTH-33 | B91: API | C91: API-AUTH | D91: Identité, authentification, comptes et RGPD | E91: Connexion admin : essais restants, verrouillage 15 min et déblocage super-admin | F91: securite | G91: P0 | H91: M | I91: =VLOOKUP(H91,Paramètres!$A$15:$B$19,2,FALSE()) -> 1 | J91: 1 | K91: =C91&"|"&J91 -> API-AUTH|1 | L91: API-AUTH-32 | M91: 3 | N91: BorisGautier | O91: À faire | R91: =INDEX(Épopées!$L$6:$L$59,MATCH(K91,Épopées!$A$6:$A$59,0)) -> 46364 | S91: =INDEX(Épopées!$M$6:$M$59,MATCH(K91,Épopées!$A$6:$A$59,0)) -> 46398 | T91: Ouvrir
A92: API-AUTH-34 | B92: API | C92: API-AUTH | D92: Identité, authentification, comptes et RGPD | E92: Double authentification : challenge, codes de secours (8) et activation obligatoire super-admin | F92: securite | G92: P0 | H92: L | I92: =VLOOKUP(H92,Paramètres!$A$15:$B$19,2,FALSE()) -> 2 | J92: 1 | K92: =C92&"|"&J92 -> API-AUTH|1 | L92: API-AUTH-33 | M92: 3 | N92: BorisGautier | O92: À faire | R92: =INDEX(Épopées!$L$6:$L$59,MATCH(K92,Épopées!$A$6:$A$59,0)) -> 46364 | S92: =INDEX(Épopées!$M$6:$M$59,MATCH(K92,Épopées!$A$6:$A$59,0)) -> 46398 | T92: Ouvrir
A93: API-AUTH-35 | B93: API | C93: API-AUTH | D93: Identité, authentification, comptes et RGPD | E93: Invitation d'un administrateur : création par super-admin et e-mail à usage unique 48 h | F93: fonctionnel | G93: P0 | H93: M | I93: =VLOOKUP(H93,Paramètres!$A$15:$B$19,2,FALSE()) -> 1 | J93: 1 | K93: =C93&"|"&J93 -> API-AUTH|1 | L93: API-AUTH-32, API-AUTH-03 | M93: 1 | N93: BorisGautier | O93: À faire | R93: =INDEX(Épopées!$L$6:$L$59,MATCH(K93,Épopées!$A$6:$A$59,0)) -> 46364 | S93: =INDEX(Épopées!$M$6:$M$59,MATCH(K93,Épopées!$A$6:$A$59,0)) -> 46398 | T93: Ouvrir
A94: API-AUTH-36 | B94: API | C94: API-AUTH | D94: Identité, authentification, comptes et RGPD | E94: Activation du compte admin : définition du mot de passe (WA-05) et configuration 2FA | F94: fonctionnel | G94: P0 | H94: M | I94: =VLOOKUP(H94,Paramètres!$A$15:$B$19,2,FALSE()) -> 1 | J94: 1 | K94: =C94&"|"&J94 -> API-AUTH|1 | L94: API-AUTH-35, API-AUTH-06 | M94: 2 | N94: BorisGautier | O94: À faire | R94: =INDEX(Épopées!$L$6:$L$59,MATCH(K94,Épopées!$A$6:$A$59,0)) -> 46364 | S94: =INDEX(Épopées!$M$6:$M$59,MATCH(K94,Épopées!$A$6:$A$59,0)) -> 46398 | T94: Ouvrir
A95: API-AUTH-37 | B95: API | C95: API-AUTH | D95: Identité, authentification, comptes et RGPD | E95: Gestion des comptes admin : liste, modification de rôle, désactivation, suppression | F95: api | G95: P1 | H95: M | I95: =VLOOKUP(H95,Paramètres!$A$15:$B$19,2,FALSE()) -> 1 | J95: 1 | K95: =C95&"|"&J95 -> API-AUTH|1 | L95: API-AUTH-35 | M95: 1 | N95: BorisGautier | O95: À faire | R95: =INDEX(Épopées!$L$6:$L$59,MATCH(K95,Épopées!$A$6:$A$59,0)) -> 46364 | S95: =INDEX(Épopées!$M$6:$M$59,MATCH(K95,Épopées!$A$6:$A$59,0)) -> 46398 | T95: Ouvrir
A96: API-AUTH-38 | B96: API | C96: API-AUTH | D96: Identité, authentification, comptes et RGPD | E96: Sessions admin : expiration 8 h d'inactivité, liste et révocation à distance | F96: securite | G96: P1 | H96: M | I96: =VLOOKUP(H96,Paramètres!$A$15:$B$19,2,FALSE()) -> 1 | J96: 1 | K96: =C96&"|"&J96 -> API-AUTH|1 | L96: API-AUTH-37, API-AUTH-09 | M96: 2 | N96: BorisGautier | O96: À faire | R96: =INDEX(Épopées!$L$6:$L$59,MATCH(K96,Épopées!$A$6:$A$59,0)) -> 46364 | S96: =INDEX(Épopées!$M$6:$M$59,MATCH(K96,Épopées!$A$6:$A$59,0)) -> 46398 | T96: Ouvrir
A97: API-AUTH-39 | B97: API | C97: API-AUTH | D97: Identité, authentification, comptes et RGPD | E97: Journal d'audit des connexions admin et helper d'écriture `audit()` | F97: securite | G97: P1 | H97: M | I97: =VLOOKUP(H97,Paramètres!$A$15:$B$19,2,FALSE()) -> 1 | J97: 1 | K97: =C97&"|"&J97 -> API-AUTH|1 | L97: API-AUTH-33, API-AUTH-32 | M97: 4 | N97: BorisGautier | O97: À faire | R97: =INDEX(Épopées!$L$6:$L$59,MATCH(K97,Épopées!$A$6:$A$59,0)) -> 46364 | S97: =INDEX(Épopées!$M$6:$M$59,MATCH(K97,Épopées!$A$6:$A$59,0)) -> 46398 | T97: Ouvrir
A98: API-AUTH-40 | B98: API | C98: API-AUTH | D98: Identité, authentification, comptes et RGPD | E98: Mot de passe oublié admin : réinitialisation par lien et par super-admin | F98: securite | G98: P1 | H98: M | I98: =VLOOKUP(H98,Paramètres!$A$15:$B$19,2,FALSE()) -> 1 | J98: 1 | K98: =C98&"|"&J98 -> API-AUTH|1 | L98: API-AUTH-36, API-AUTH-34 | M98: 2 | N98: BorisGautier | O98: À faire | R98: =INDEX(Épopées!$L$6:$L$59,MATCH(K98,Épopées!$A$6:$A$59,0)) -> 46364 | S98: =INDEX(Épopées!$M$6:$M$59,MATCH(K98,Épopées!$A$6:$A$59,0)) -> 46398 | T98: Ouvrir
A99: API-AUTH-41 | B99: API | C99: API-AUTH | D99: Identité, authentification, comptes et RGPD | E99: Rate limiting spécifique par route et par compte (auth, 2FA, e-mails) | F99: securite | G99: P0 | H99: M | I99: =VLOOKUP(H99,Paramètres!$A$15:$B$19,2,FALSE()) -> 1 | J99: 1 | K99: =C99&"|"&J99 -> API-AUTH|1 | L99: API-AUTH-07 | M99: 4 | N99: BorisGautier | O99: À faire | R99: =INDEX(Épopées!$L$6:$L$59,MATCH(K99,Épopées!$A$6:$A$59,0)) -> 46364 | S99: =INDEX(Épopées!$M$6:$M$59,MATCH(K99,Épopées!$A$6:$A$59,0)) -> 46398 | T99: Ouvrir
A100: API-AUTH-42 | B100: API | C100: API-AUTH | D100: Identité, authentification, comptes et RGPD | E100: Suite de tests de sécurité : JWT, en-têtes HTTP, énumération de comptes, injections | F100: tests | G100: P0 | H100: L | I100: =VLOOKUP(H100,Paramètres!$A$15:$B$19,2,FALSE()) -> 2 | J100: 1 | K100: =C100&"|"&J100 -> API-AUTH|1 | L100: API-AUTH-09, API-AUTH-17, API-AUTH-33 | M100: 5 | N100: BorisGautier | O100: À faire | R100: =INDEX(Épopées!$L$6:$L$59,MATCH(K100,Épopées!$A$6:$A$59,0)) -> 46364 | S100: =INDEX(Épopées!$M$6:$M$59,MATCH(K100,Épopées!$A$6:$A$59,0)) -> 46398 | T100: Ouvrir
A101: API-AUTH-43 | B101: API | C101: API-AUTH | D101: Identité, authentification, comptes et RGPD | E101: Tests d'intégration et e2e des parcours d'authentification | F101: tests | G101: P0 | H101: L | I101: =VLOOKUP(H101,Paramètres!$A$15:$B$19,2,FALSE()) -> 2 | J101: 1 | K101: =C101&"|"&J101 -> API-AUTH|1 | L101: API-AUTH-27, API-AUTH-36, API-AUTH-16, API-AUTH-12, API-AUTH-23 | M101: 10 | N101: BorisGautier | O101: À faire | R101: =INDEX(Épopées!$L$6:$L$59,MATCH(K101,Épopées!$A$6:$A$59,0)) -> 46364 | S101: =INDEX(Épopées!$M$6:$M$59,MATCH(K101,Épopées!$A$6:$A$59,0)) -> 46398 | T101: Ouvrir
A102: API-AUTH-44 | B102: API | C102: API-AUTH | D102: Identité, authentification, comptes et RGPD | E102: Internationalisation des messages d'erreur API (FR/EN/ES) et identifiants de trace | F102: i18n | G102: P1 | H102: M | I102: =VLOOKUP(H102,Paramètres!$A$15:$B$19,2,FALSE()) -> 1 | J102: 1 | K102: =C102&"|"&J102 -> API-AUTH|1 | L102: API-AUTH-09 | M102: 7 | N102: BorisGautier | O102: À faire | R102: =INDEX(Épopées!$L$6:$L$59,MATCH(K102,Épopées!$A$6:$A$59,0)) -> 46364 | S102: =INDEX(Épopées!$M$6:$M$59,MATCH(K102,Épopées!$A$6:$A$59,0)) -> 46398 | T102: Ouvrir
...

Sheet Suivi
A1: Tableau de bord de suivi
A2: Mis à jour automatiquement à partir des statuts saisis dans « Backlog ».
D3: Par phase
A4: Issues au total | B4: =COUNTA(Backlog!$A$6:$A$1327) -> 1322 | D4: Phase | E4: Issues | F4: Terminées | G4: % issues | H4: Charge (j) | I4: Réalisée (j) | J4: % charge | K4: Fin prévue
A5: Terminées | B5: =COUNTIFS(Backlog!$O$6:$O$1327,"Terminé") -> 0 | D5: Phase 0 — Socle technique | E5: =COUNTIFS(Backlog!$J$6:$J$1327,0) -> 223 | F5: =COUNTIFS(Backlog!$J$6:$J$1327,0,Backlog!$O$6:$O$1327,"Terminé") -> 0 | G5: =IF(E5=0,0,F5/E5) -> 0 | H5: =SUMIFS(Backlog!$I$6:$I$1327,Backlog!$J$6:$J$1327,0) -> 224.5 | I5: =SUMIFS(Backlog!$I$6:$I$1327,Backlog!$J$6:$J$1327,0,Backlog!$O$6:$O$1327,"Terminé") -> 0 | J5: =IF(H5=0,0,I5/H5) -> 0 | K5: =_xlfn.MAXIFS(Épopées!$M$6:$M$59,Épopées!$E$6:$E$59,0) -> 46435
A6: En cours | B6: =COUNTIFS(Backlog!$O$6:$O$1327,"En cours")+COUNTIFS(Backlog!$O$6:$O$1327,"En revue") -> 0 | D6: Phase 1 — MVP | E6: =COUNTIFS(Backlog!$J$6:$J$1327,1) -> 688 | F6: =COUNTIFS(Backlog!$J$6:$J$1327,1,Backlog!$O$6:$O$1327,"Terminé") -> 0 | G6: =IF(E6=0,0,F6/E6) -> 0 | H6: =SUMIFS(Backlog!$I$6:$I$1327,Backlog!$J$6:$J$1327,1) -> 714.5 | I6: =SUMIFS(Backlog!$I$6:$I$1327,Backlog!$J$6:$J$1327,1,Backlog!$O$6:$O$1327,"Terminé") -> 0 | J6: =IF(H6=0,0,I6/H6) -> 0 | K6: =_xlfn.MAXIFS(Épopées!$M$6:$M$59,Épopées!$E$6:$E$59,1) -> 46615
A7: Bloquées | B7: =COUNTIFS(Backlog!$O$6:$O$1327,"Bloqué") -> 0 | D7: Phase 2 — Communautaire & compétitif | E7: =COUNTIFS(Backlog!$J$6:$J$1327,2) -> 313 | F7: =COUNTIFS(Backlog!$J$6:$J$1327,2,Backlog!$O$6:$O$1327,"Terminé") -> 0 | G7: =IF(E7=0,0,F7/E7) -> 0 | H7: =SUMIFS(Backlog!$I$6:$I$1327,Backlog!$J$6:$J$1327,2) -> 340.5 | I7: =SUMIFS(Backlog!$I$6:$I$1327,Backlog!$J$6:$J$1327,2,Backlog!$O$6:$O$1327,"Terminé") -> 0 | J7: =IF(H7=0,0,I7/H7) -> 0 | K7: =_xlfn.MAXIFS(Épopées!$M$6:$M$59,Épopées!$E$6:$E$59,2) -> 46710
A8: Avancement (issues) | B8: =IF(B4=0,0,B5/B4) -> 0 | D8: Phase 3 — Fonctionnalités avancées | E8: =COUNTIFS(Backlog!$J$6:$J$1327,3) -> 98 | F8: =COUNTIFS(Backlog!$J$6:$J$1327,3,Backlog!$O$6:$O$1327,"Terminé") -> 0 | G8: =IF(E8=0,0,F8/E8) -> 0 | H8: =SUMIFS(Backlog!$I$6:$I$1327,Backlog!$J$6:$J$1327,3) -> 92.25 | I8: =SUMIFS(Backlog!$I$6:$I$1327,Backlog!$J$6:$J$1327,3,Backlog!$O$6:$O$1327,"Terminé") -> 0 | J8: =IF(H8=0,0,I8/H8) -> 0 | K8: =_xlfn.MAXIFS(Épopées!$M$6:$M$59,Épopées!$E$6:$E$59,3) -> 46748
A9: Charge totale (j) | B9: =SUM(Backlog!$I$6:$I$1327) -> 1371.75
A10: Charge réalisée (j) | B10: =SUMIFS(Backlog!$I$6:$I$1327,Backlog!$O$6:$O$1327,"Terminé") -> 0
A11: Avancement (charge) | B11: =IF(B9=0,0,B10/B9) -> 0 | D11: Par flux
A12: Début prévu | B12: =Épopées!L60 -> 46328 | D12: Flux | E12: Issues | F12: Terminées | G12: % issues | H12: Charge (j) | I12: Réalisée (j) | J12: % charge | K12: Fin prévue
A13: Fin prévue | B13: =Épopées!M60 -> 46748 | D13: API | E13: =COUNTIFS(Backlog!$B$6:$B$1327,D13) -> 471 | F13: =COUNTIFS(Backlog!$B$6:$B$1327,D13,Backlog!$O$6:$O$1327,"Terminé") -> 0 | G13: =IF(E13=0,0,F13/E13) -> 0 | H13: =SUMIFS(Backlog!$I$6:$I$1327,Backlog!$B$6:$B$1327,D13) -> 493.5 | I13: =SUMIFS(Backlog!$I$6:$I$1327,Backlog!$B$6:$B$1327,D13,Backlog!$O$6:$O$1327,"Terminé") -> 0 | J13: =IF(H13=0,0,I13/H13) -> 0 | K13: =_xlfn.MAXIFS(Épopées!$M$6:$M$59,Épopées!$B$6:$B$59,D13) -> 46667
A14: Aujourd’hui | B14: =TODAY() -> 46311 | D14: Mobile | E14: =COUNTIFS(Backlog!$B$6:$B$1327,D14) -> 599 | F14: =COUNTIFS(Backlog!$B$6:$B$1327,D14,Backlog!$O$6:$O$1327,"Terminé") -> 0 | G14: =IF(E14=0,0,F14/E14) -> 0 | H14: =SUMIFS(Backlog!$I$6:$I$1327,Backlog!$B$6:$B$1327,D14) -> 599.75 | I14: =SUMIFS(Backlog!$I$6:$I$1327,Backlog!$B$6:$B$1327,D14,Backlog!$O$6:$O$1327,"Terminé") -> 0 | J14: =IF(H14=0,0,I14/H14) -> 0 | K14: =_xlfn.MAXIFS(Épopées!$M$6:$M$59,Épopées!$B$6:$B$59,D14) -> 46748
D15: Admin | E15: =COUNTIFS(Backlog!$B$6:$B$1327,D15) -> 252 | F15: =COUNTIFS(Backlog!$B$6:$B$1327,D15,Backlog!$O$6:$O$1327,"Terminé") -> 0 | G15: =IF(E15=0,0,F15/E15) -> 0 | H15: =SUMIFS(Backlog!$I$6:$I$1327,Backlog!$B$6:$B$1327,D15) -> 278.5 | I15: =SUMIFS(Backlog!$I$6:$I$1327,Backlog!$B$6:$B$1327,D15,Backlog!$O$6:$O$1327,"Terminé") -> 0 | J15: =IF(H15=0,0,I15/H15) -> 0 | K15: =_xlfn.MAXIFS(Épopées!$M$6:$M$59,Épopées!$B$6:$B$59,D15) -> 46679
D17: Par statut
D18: Statut | E18: Issues
D19: À faire | E19: =COUNTIFS(Backlog!$O$6:$O$1327,D19) -> 1322
D20: En cours | E20: =COUNTIFS(Backlog!$O$6:$O$1327,D20) -> 0
D21: En revue | E21: =COUNTIFS(Backlog!$O$6:$O$1327,D21) -> 0
D22: Terminé | E22: =COUNTIFS(Backlog!$O$6:$O$1327,D22) -> 0
D23: Bloqué | E23: =COUNTIFS(Backlog!$O$6:$O$1327,D23) -> 0

Sheet Scénarios
A1: Scénarios d’équipe (durée estimée)
A2: Compare des tailles d’équipe : durée (semaines) = charge × (1+marge) ÷ (devs × focus × 5). Les devs sont modifiables (cellules bleues).
A4: Flux | B4: Charge (j) | C4: Solo (1 dev au total) | D4: Petite équipe | E4: Équipe cible (Paramètres) | F4: Équipe renforcée
A5: Développeurs | C5: 1 | D5: 3 | E5: =Paramètres!$B$7+Paramètres!$B$8+Paramètres!$B$9 -> 8 | F5: 12
A6: API | B6: =SUMIFS(Backlog!$I$6:$I$1327,Backlog!$B$6:$B$1327,A6) -> 493.5
A7: Mobile | B7: =SUMIFS(Backlog!$I$6:$I$1327,Backlog!$B$6:$B$1327,A7) -> 599.75
A8: Admin | B8: =SUMIFS(Backlog!$I$6:$I$1327,Backlog!$B$6:$B$1327,A8) -> 278.5
A9: Durée totale (semaines) | B9: =SUM(B6:B8) -> 1371.75 | C9: =ROUNDUP($B$9*(1+Paramètres!$B$6)/(C5*Paramètres!$B$5*5),0) -> 395 | D9: =ROUNDUP($B$9*(1+Paramètres!$B$6)/(D5*Paramètres!$B$5*5),0) -> 132 | E9: =ROUNDUP($B$9*(1+Paramètres!$B$6)/(E5*Paramètres!$B$5*5),0) -> 50 | F9: =ROUNDUP($B$9*(1+Paramètres!$B$6)/(F5*Paramètres!$B$5*5),0) -> 33
A10: Fin estimée | C10: =WORKDAY(Paramètres!$B$4,C9*5) -> 49093 | D10: =WORKDAY(Paramètres!$B$4,D9*5) -> 47252 | E10: =WORKDAY(Paramètres!$B$4,E9*5) -> 46678 | F10: =WORKDAY(Paramètres!$B$4,F9*5) -> 46559
A12: Lecture : la durée suppose une répartition parfaite des développeurs entre les 3 flux au prorata de la charge. Les dépendances (API avant Mobile/Admin) et la recette rallongent le calendrier réel : le planning détaillé (feuilles Épopées / Gantt) fait foi.

Sheet Décisions et risques
A1: Décisions à trancher et risques
A2: Les décisions « à confirmer » proviennent de la rédaction du backlog (écarts CDC ↔ maquettes ↔ code). Les risques reprennent le CDC §9.
A4: ID | B4: Sujet | C4: Constat | D4: Proposition retenue dans les issues | E4: Issues impactées | F4: Décision | G4: Statut
A5: D01 | B5: Fuseau du « jeu du jour » | C5: CDC : « à définir » ; minuit local ou serveur ambigu. | D5: Europe/Madrid (minuit heure du serveur). | E5: API-JEUX, MOB-D, MOB-E | F5: Décidé par défaut — voir docs/DECISIONS.md | G5: Décidé
A6: D02 | B6: Quotas de l’assistant IA et des wallpapers | C6: CDC : 30 messages et 5 générations/jour ; maquettes : 40 et 3. | D6: Valeurs des maquettes, configurables côté back-office. | E6: API-IA, API-WALL, MOB-N, MOB-M | F6: Décidé par défaut — voir docs/DECISIONS.md | G6: Décidé
A7: D03 | B7: Délais de modération (SLA) et contestation | C7: Non définis au CDC. | D7: SLA 1 h / 24 h / 72 h selon gravité ; contestation sous 14 jours. | E7: API-MODER, ADM-WG | F7: Décidé par défaut — voir docs/DECISIONS.md | G7: Décidé
A8: D04 | B8: Barème Guess the Player et seuils « proche » | C8: Non définis au CDC. | D8: Barème 100/80/60/40/25/10 ; seuils à valider. | E8: API-JEUX, MOB-D | F8: Décidé par défaut — voir docs/DECISIONS.md | G8: Décidé
A9: D05 | B9: Barème quiz (+150 pts, bonus de rapidité) | C9: Le maximum « +150 pts » n’apparaît qu’au niveau 2. | D9: Base par niveau + bonus de rapidité. | E9: API-JEUX, MOB-E | F9: Décidé par défaut — voir docs/DECISIONS.md | G9: Décidé
A10: D06 | B10: Niveaux d’XP du Culé Passport | C10: CDC : seulement 5 niveaux de quiz. | D10: Seuils 0/500/3000/8000/20000 XP (à confirmer). | E10: API-PASS, MOB-P | F10: Décidé par défaut — voir docs/DECISIONS.md | G10: Décidé
A11: D07 | B11: Budget et mercato du Fantasy | C11: Absents du CDC et des maquettes. | D11: Non spécifiés (hors périmètre). | E11: API-FANT, MOB-H | F11: Décidé par défaut — voir docs/DECISIONS.md | G11: Décidé
A12: D08 | B12: Règles de La Masia (gains, fatigue, catégories, décision « mental ») | C12: Valeurs absentes ; « mental » sans carte sur I-06. | D12: Propositions marquées « à confirmer ». | E12: API-FANT, MOB-I | F12: Décidé par défaut — voir docs/DECISIONS.md | G12: Décidé
A13: D09 | B13: Critères de vote GOAT secondaires | C13: Extension du CDC. | D13: Désactivés par défaut. | E13: API-GOAT, MOB-G | F13: Décidé par défaut — voir docs/DECISIONS.md | G13: Décidé
A14: D10 | B14: Ligues d’amis et endpoints hors CDC §3.5 | C14: Ligues, profil public, barème, badges non décrits au CDC. | D14: Ajoutés comme extensions, marqués « proposé ». | E14: API-FANT, API-PASS, MOB-H, MOB-P | F14: Décidé par défaut — voir docs/DECISIONS.md | G14: Décidé
A15: D11 | B15: Heures calmes par jour, « Buts en direct », compétitions suivies | C15: Absents du modèle API. | D15: Modèle NotificationPreference à étendre. | E15: API-NOTIF, MOB-O | F15: Décidé par défaut — voir docs/DECISIONS.md | G15: Décidé
... A23: D19 | B23: Statut « En cours » et rang de récidive en modération | C23: Absents du CDC ; définition floue. | D23: À préciser avec le modérateur. | E23: API-MODER, ADM-WG | F23: Décidé par défaut — voir docs/DECISIONS.md | G23: Décidé
A26: Risques (CDC §9)
A27: ID | B27: Risque | C27: Impact | D27: Mesures de mitigation | E27: Rattachement backlog | F27: Probabilité | G27: Statut
A28: R01 | B28: Indisponibilité ou changement de l’API football externe | C28: Élevé | D28: Cache des dernières données, dégradation gracieuse, veille d’alternatives. | E28: API-FOOT (sync, quotas, reprise) | F28: Moyenne | G28: Ouvert
A29: R02 | B29: Dérive de l’assistant IA (hors sujet, erreurs) | C29: Moyen | D29: RAG sur faits, garde-fous entrées/sorties, tests de non-régression de prompts. | E29: API-IA | F29: Moyenne | G29: Ouvert
A30: R03 | B30: Abus de la carte communautaire | C30: Élevé | D30: Agrégation des positions, signalement, modération réactive. | E30: API-COMM, API-MODER | F30: Moyenne | G30: Ouvert
A31: R04 | B31: Panne du VPS de production | C31: Élevé | D31: Sauvegardes, restauration testée, monitoring et alertes. | E31: API-PLAT, docs/DISASTER_RECOVERY.md | F31: Faible | G31: Ouvert
A32: R05 | B32: Non-conformité RGPD | C32: Élevé | D32: Consentement explicite, minimisation, registre, revue légale. | E32: API-AUTH, API-COMM | F32: Faible à moyenne | G32: Ouvert
A33: R06 | B33: Charge de développement sous-estimée | C33: Moyen | D33: Phases, priorités P0/P1/P2, revue du périmètre, scénarios d’équipe. | E33: Feuille Scénarios | F33: Élevée | G33: Ouvert
A34: R07 | B34: Coût de génération IA supérieur aux attentes | C34: Moyen | D34: Plafonds par utilisateur, cache, modèles proportionnés. | E34: API-IA, API-WALL | F34: Moyenne | G34: Ouvert
